{"relatedACDCClusters":{"org.apache.catalina.users.ss":{"id":"a8f8aad5-1721-11ea-8ada-add5f6e8eea0","cluster":"org.apache.catalina.users.ss","elements":["org.apache.catalina.users.MemoryRoleCreationFactory","org.apache.tomcat.util.digester.AbstractObjectCreationFactory","org.apache.catalina.users.MemoryUserDatabase","org.apache.catalina.users.MemoryGroupCreationFactory","org.apache.catalina.users.Constants","org.apache.catalina.users.MemoryUserCreationFactory","org.apache.catalina.Group","org.apache.catalina.Role","org.apache.catalina.UserDatabase","org.apache.catalina.User","org.apache.catalina.mbeans.GroupMBean","org.apache.catalina.mbeans.MemoryUserDatabaseMBean","org.apache.catalina.mbeans.UserMBean","org.apache.catalina.users.MemoryGroup","org.apache.catalina.users.AbstractGroup","org.apache.catalina.users.AbstractRole","org.apache.catalina.users.MemoryRole","org.apache.catalina.users.MemoryUser","org.apache.catalina.users.AbstractUser"]}},"nodes":[{"id":"4412","name":"org.apache.catalina.UserDatabase:createGroup()","value":1,"children":{},"label":"UserDatabase:createGroup()","className":"org.apache.catalina.UserDatabase","acdcCluster":"org.apache.catalina.users.ss","groupId":"cluster"},{"id":"7697","name":"org.apache.catalina.mbeans.MemoryUserDatabaseMBean:createGroup()","value":11,"children":{"org.apache.catalina.UserDatabase:createGroup()":true,"org.apache.catalina.mbeans.MBeanUtils:createMBean()":true,"java.lang.StringBuilder:<init>()":true,"java.lang.StringBuilder:append()":true,"java.lang.StringBuilder:toString()":true,"java.lang.IllegalArgumentException:<init>()":true,"java.lang.IllegalArgumentException:initCause()":true,"org.apache.catalina.mbeans.MemoryUserDatabaseMBean:findGroup()":true},"label":"MemoryUserDatabaseMBean:createGroup()","className":"org.apache.catalina.mbeans.MemoryUserDatabaseMBean","acdcCluster":"org.apache.catalina.users.ss","groupId":"cluster"},{"id":"7700","name":"org.apache.catalina.mbeans.MemoryUserDatabaseMBean:findGroup()","value":12,"children":{"org.apache.catalina.UserDatabase:findGroup()":true,"org.apache.tomcat.util.modeler.ManagedBean:getDomain()":true,"org.apache.catalina.mbeans.MBeanUtils:createObjectName()":true,"javax.management.ObjectName:toString()":true,"java.lang.StringBuilder:<init>()":true,"java.lang.StringBuilder:append()":true,"java.lang.StringBuilder:toString()":true,"java.lang.IllegalArgumentException:<init>()":true,"java.lang.IllegalArgumentException:initCause()":true},"label":"MemoryUserDatabaseMBean:findGroup()","className":"org.apache.catalina.mbeans.MemoryUserDatabaseMBean","acdcCluster":"org.apache.catalina.users.ss","groupId":"cluster"},{"id":"7694","name":"org.apache.catalina.mbeans.MemoryUserDatabaseMBean:getGroups()","value":10,"children":{"java.util.ArrayList:<init>()":true,"org.apache.catalina.UserDatabase:getGroups()":true,"java.util.Iterator:hasNext()":true,"java.util.Iterator:next()":true,"org.apache.catalina.Group:getGroupname()":true,"org.apache.catalina.mbeans.MemoryUserDatabaseMBean:findGroup()":true,"java.util.ArrayList:add()":true,"java.util.ArrayList:size()":true,"java.util.ArrayList:toArray()":true},"label":"MemoryUserDatabaseMBean:getGroups()","className":"org.apache.catalina.mbeans.MemoryUserDatabaseMBean","acdcCluster":"org.apache.catalina.users.ss","groupId":"cluster"},{"id":"7687","name":"org.apache.catalina.mbeans.MBeanUtils:createMBean()","value":106,"children":{"org.apache.catalina.mbeans.MBeanUtils:createManagedName()":true,"org.apache.tomcat.util.modeler.Registry:findManagedBean()":true,"java.lang.StringBuilder:<init>()":true,"java.lang.StringBuilder:append()":true,"java.lang.StringBuilder:toString()":true,"java.lang.Exception:<init>()":true,"javax.management.MBeanException:<init>()":true,"org.apache.tomcat.util.modeler.ManagedBean:getDomain()":true,"javax.management.MBeanServer:getDefaultDomain()":true,"org.apache.tomcat.util.modeler.ManagedBean:createMBean()":true,"org.apache.catalina.mbeans.MBeanUtils:createObjectName()":true,"javax.management.MBeanServer:isRegistered()":true,"javax.management.MBeanServer:unregisterMBean()":true,"javax.management.MBeanServer:registerMBean()":true},"label":"MBeanUtils:createMBean()","className":"org.apache.catalina.mbeans.MBeanUtils","acdcCluster":"org.apache.catalina.startup.ss"},{"id":"169","name":"java.lang.StringBuilder:<init>()","value":1,"children":{},"label":"StringBuilder:<init>()","className":"java.lang.StringBuilder","acdcCluster":"org.apache.tomcat.util.descriptor.web.ss"},{"id":"170","name":"java.lang.StringBuilder:append()","value":1,"children":{},"label":"StringBuilder:append()","className":"java.lang.StringBuilder","acdcCluster":"org.apache.tomcat.util.descriptor.web.ss"},{"id":"171","name":"java.lang.StringBuilder:toString()","value":1,"children":{},"label":"StringBuilder:toString()","className":"java.lang.StringBuilder","acdcCluster":"org.apache.tomcat.util.descriptor.web.ss"},{"id":"201","name":"java.lang.IllegalArgumentException:<init>()","value":1,"children":{},"label":"IllegalArgumentException:<init>()","className":"java.lang.IllegalArgumentException","acdcCluster":"org.apache.tomcat.util.descriptor.web.ss"},{"id":"11406","name":"java.lang.IllegalArgumentException:initCause()","value":1,"children":{},"label":"IllegalArgumentException:initCause()","className":"java.lang.IllegalArgumentException","acdcCluster":"org.apache.tomcat.util.descriptor.web.ss"},{"id":"7686","name":"org.apache.catalina.mbeans.MBeanUtils:createManagedName()","value":6,"children":{"java.lang.Object:getClass()":true,"java.lang.Class:getName()":true,"java.lang.String:equals()":true,"java.lang.String:lastIndexOf()":true,"java.lang.String:substring()":true},"label":"MBeanUtils:createManagedName()","className":"org.apache.catalina.mbeans.MBeanUtils","acdcCluster":"org.apache.catalina.startup.ss"},{"id":"2051","name":"org.apache.tomcat.util.modeler.Registry:findManagedBean()","value":21,"children":{"java.util.HashMap:get()":true,"java.lang.Object:getClass()":true,"java.lang.Class:getName()":true,"org.apache.tomcat.util.modeler.Registry:findManagedBean()":true,"org.apache.juli.logging.Log:isDebugEnabled()":true,"org.apache.juli.logging.Log:debug()":true,"org.apache.tomcat.util.modeler.Registry:findDescriptor()":true,"org.apache.tomcat.util.modeler.Registry:load()":true,"java.lang.StringBuilder:<init>()":true,"java.lang.StringBuilder:append()":true,"java.lang.StringBuilder:toString()":true,"org.apache.juli.logging.Log:warn()":true,"org.apache.tomcat.util.modeler.ManagedBean:setName()":true,"org.apache.tomcat.util.modeler.Registry:addManagedBean()":true},"label":"Registry:findManagedBean()","className":"org.apache.tomcat.util.modeler.Registry","acdcCluster":"org.apache.tomcat.util.modeler.ss"},{"id":"1314","name":"java.lang.Exception:<init>()","value":1,"children":{},"label":"Exception:<init>()","className":"java.lang.Exception","acdcCluster":"org.apache.tomcat.util.descriptor.web.ss"},{"id":"12254","name":"javax.management.MBeanException:<init>()","value":1,"children":{},"label":"MBeanException:<init>()","className":"javax.management.MBeanException","acdcCluster":"org.apache.catalina.mbeans.ss"},{"id":"12295","name":"org.apache.tomcat.util.modeler.ManagedBean:getDomain()","value":1,"children":{},"label":"ManagedBean:getDomain()","className":"org.apache.tomcat.util.modeler.ManagedBean","acdcCluster":"org.apache.tomcat.util.modeler.ss"},{"id":"12313","name":"javax.management.MBeanServer:getDefaultDomain()","value":1,"children":{},"label":"MBeanServer:getDefaultDomain()","className":"javax.management.MBeanServer","acdcCluster":"org.apache.catalina.manager.ss"},{"id":"2052","name":"org.apache.tomcat.util.modeler.ManagedBean:createMBean()","value":25,"children":{"org.apache.tomcat.util.modeler.ManagedBean:getClassName()":true,"java.lang.String:equals()":true,"org.apache.tomcat.util.modeler.BaseModelMBean:<init>()":true,"java.lang.Class:forName()":true,"java.lang.Thread:currentThread()":true,"java.lang.Thread:getContextClassLoader()":true,"java.lang.ClassLoader:loadClass()":true,"java.lang.StringBuilder:<init>()":true,"java.lang.StringBuilder:append()":true,"java.lang.StringBuilder:toString()":true,"javax.management.MBeanException:<init>()":true,"java.lang.Class:newInstance()":true,"org.apache.tomcat.util.modeler.BaseModelMBean:setManagedBean()":true,"org.apache.tomcat.util.modeler.BaseModelMBean:setManagedResource()":true},"label":"ManagedBean:createMBean()","className":"org.apache.tomcat.util.modeler.ManagedBean","acdcCluster":"org.apache.tomcat.util.modeler.ss"},{"id":"7688","name":"org.apache.catalina.mbeans.MBeanUtils:createObjectName()","value":139,"children":{"org.apache.tomcat.util.descriptor.web.ContextEnvironment:getNamingResources()":true,"org.apache.tomcat.util.descriptor.web.NamingResources:getContainer()":true,"java.lang.StringBuilder:<init>()":true,"java.lang.StringBuilder:append()":true,"org.apache.tomcat.util.descriptor.web.ContextEnvironment:getName()":true,"java.lang.StringBuilder:toString()":true,"javax.management.ObjectName:<init>()":true,"org.apache.catalina.Context:getName()":true,"org.apache.catalina.util.ContextName:<init>()":true,"org.apache.catalina.Context:getParent()":true,"org.apache.catalina.Container:getName()":true,"org.apache.catalina.util.ContextName:getDisplayName()":true,"org.apache.tomcat.util.descriptor.web.ContextResource:getName()":true,"javax.management.ObjectName:quote()":true,"org.apache.tomcat.util.descriptor.web.ContextResource:getNamingResources()":true,"org.apache.tomcat.util.descriptor.web.ContextResource:getType()":true,"org.apache.tomcat.util.descriptor.web.ContextResourceLink:getName()":true,"org.apache.tomcat.util.descriptor.web.ContextResourceLink:getNamingResources()":true,"org.apache.catalina.Group:getGroupname()":true,"org.apache.catalina.Group:getUserDatabase()":true,"org.apache.catalina.UserDatabase:getId()":true,"org.apache.catalina.Loader:getContext()":true,"org.apache.catalina.Role:getRolename()":true,"org.apache.catalina.Role:getUserDatabase()":true,"org.apache.catalina.User:getUsername()":true,"org.apache.catalina.User:getUserDatabase()":true},"label":"MBeanUtils:createObjectName()","className":"org.apache.catalina.mbeans.MBeanUtils","acdcCluster":"org.apache.catalina.startup.ss"},{"id":"2045","name":"javax.management.MBeanServer:isRegistered()","value":1,"children":{},"label":"MBeanServer:isRegistered()","className":"javax.management.MBeanServer","acdcCluster":"org.apache.catalina.manager.ss"},{"id":"12314","name":"javax.management.MBeanServer:unregisterMBean()","value":1,"children":{},"label":"MBeanServer:unregisterMBean()","className":"javax.management.MBeanServer","acdcCluster":"org.apache.catalina.manager.ss"},{"id":"12315","name":"javax.management.MBeanServer:registerMBean()","value":1,"children":{},"label":"MBeanServer:registerMBean()","className":"javax.management.MBeanServer","acdcCluster":"org.apache.catalina.manager.ss"},{"id":"165","name":"java.lang.Object:getClass()","value":1,"children":{},"label":"Object:getClass()","className":"java.lang.Object","acdcCluster":"org.apache.el.parser.ss"},{"id":"1520","name":"java.lang.Class:getName()","value":1,"children":{},"label":"Class:getName()","className":"java.lang.Class","acdcCluster":"org.apache.el.parser.ss"},{"id":"172","name":"java.lang.String:equals()","value":1,"children":{},"label":"String:equals()","className":"java.lang.String","acdcCluster":"org.apache.catalina.valves.ss"},{"id":"11308","name":"java.lang.String:lastIndexOf()","value":1,"children":{},"label":"String:lastIndexOf()","className":"java.lang.String","acdcCluster":"org.apache.catalina.valves.ss"},{"id":"178","name":"java.lang.String:substring()","value":1,"children":{},"label":"String:substring()","className":"java.lang.String","acdcCluster":"org.apache.catalina.valves.ss"},{"id":"1376","name":"java.util.HashMap:get()","value":1,"children":{},"label":"HashMap:get()","className":"java.util.HashMap","acdcCluster":"org.apache.jasper.compiler.ss"},{"id":"183","name":"org.apache.juli.logging.Log:isDebugEnabled()","value":1,"children":{},"label":"Log:isDebugEnabled()","className":"org.apache.juli.logging.Log","acdcCluster":"org.apache.tomcat.util.descriptor.web.ss"},{"id":"184","name":"org.apache.juli.logging.Log:debug()","value":1,"children":{},"label":"Log:debug()","className":"org.apache.juli.logging.Log","acdcCluster":"org.apache.tomcat.util.descriptor.web.ss"},{"id":"30015","name":"org.apache.tomcat.util.modeler.Registry:findDescriptor()","value":12,"children":{"java.lang.Class:getName()":true,"java.lang.Class:getClassLoader()":true,"java.lang.Thread:currentThread()":true,"java.lang.Thread:getContextClassLoader()":true,"java.lang.Object:getClass()":true,"java.lang.String:indexOf()":true,"java.lang.String:lastIndexOf()":true,"java.lang.String:substring()":true,"java.util.HashMap:get()":true,"org.apache.tomcat.util.modeler.Registry:loadDescriptors()":true},"label":"Registry:findDescriptor()","className":"org.apache.tomcat.util.modeler.Registry","acdcCluster":"org.apache.tomcat.util.modeler.ss"},{"id":"30014","name":"org.apache.tomcat.util.modeler.Registry:load()","value":16,"children":{"org.apache.juli.logging.Log:isTraceEnabled()":true,"java.lang.StringBuilder:<init>()":true,"java.lang.StringBuilder:append()":true,"java.lang.StringBuilder:toString()":true,"org.apache.juli.logging.Log:trace()":true,"java.net.URL:toString()":true,"java.net.URL:openStream()":true,"java.lang.String:endsWith()":true,"java.io.File:getAbsolutePath()":true,"java.io.FileInputStream:<init>()":true,"java.lang.Class:getName()":true,"org.apache.tomcat.util.modeler.Registry:getModelerSource()":true,"org.apache.tomcat.util.modeler.modules.ModelerSource:loadDescriptors()":true},"label":"Registry:load()","className":"org.apache.tomcat.util.modeler.Registry","acdcCluster":"org.apache.tomcat.util.modeler.ss"},{"id":"191","name":"org.apache.juli.logging.Log:warn()","value":1,"children":{},"label":"Log:warn()","className":"org.apache.juli.logging.Log","acdcCluster":"org.apache.tomcat.util.descriptor.web.ss"},{"id":"29970","name":"org.apache.tomcat.util.modeler.ManagedBean:setName()","value":7,"children":{"java.util.concurrent.locks.ReadWriteLock:writeLock()":true,"java.util.concurrent.locks.Lock:lock()":true,"java.util.concurrent.locks.Lock:unlock()":true},"label":"ManagedBean:setName()","className":"org.apache.tomcat.util.modeler.ManagedBean","acdcCluster":"org.apache.tomcat.util.modeler.ss"},{"id":"30013","name":"org.apache.tomcat.util.modeler.Registry:addManagedBean()","value":6,"children":{"org.apache.tomcat.util.modeler.ManagedBean:getName()":true,"java.util.HashMap:put()":true,"org.apache.tomcat.util.modeler.ManagedBean:getType()":true},"label":"Registry:addManagedBean()","className":"org.apache.tomcat.util.modeler.Registry","acdcCluster":"org.apache.tomcat.util.modeler.ss"},{"id":"29962","name":"org.apache.tomcat.util.modeler.ManagedBean:getClassName()","value":1,"children":{},"label":"ManagedBean:getClassName()","className":"org.apache.tomcat.util.modeler.ManagedBean","acdcCluster":"org.apache.tomcat.util.modeler.ss"},{"id":"12251","name":"org.apache.tomcat.util.modeler.BaseModelMBean:<init>()","value":2,"children":{"java.lang.Object:<init>()":true},"label":"BaseModelMBean:<init>()","className":"org.apache.tomcat.util.modeler.BaseModelMBean","acdcCluster":"org.apache.tomcat.util.modeler.ss"},{"id":"185","name":"java.lang.Class:forName()","value":1,"children":{},"label":"Class:forName()","className":"java.lang.Class","acdcCluster":"org.apache.el.parser.ss"},{"id":"181","name":"java.lang.Thread:currentThread()","value":1,"children":{},"label":"Thread:currentThread()","className":"java.lang.Thread","acdcCluster":"org.apache.catalina.tribes.membership.ss"},{"id":"615","name":"java.lang.Thread:getContextClassLoader()","value":1,"children":{},"label":"Thread:getContextClassLoader()","className":"java.lang.Thread","acdcCluster":"org.apache.catalina.tribes.membership.ss"},{"id":"163","name":"java.lang.ClassLoader:loadClass()","value":1,"children":{},"label":"ClassLoader:loadClass()","className":"java.lang.ClassLoader","acdcCluster":"javax.el.ss"},{"id":"164","name":"java.lang.Class:newInstance()","value":1,"children":{},"label":"Class:newInstance()","className":"java.lang.Class","acdcCluster":"org.apache.el.parser.ss"},{"id":"29919","name":"org.apache.tomcat.util.modeler.BaseModelMBean:setManagedBean()","value":1,"children":{},"label":"BaseModelMBean:setManagedBean()","className":"org.apache.tomcat.util.modeler.BaseModelMBean","acdcCluster":"org.apache.tomcat.util.modeler.ss"},{"id":"29926","name":"org.apache.tomcat.util.modeler.BaseModelMBean:setManagedResource()","value":5,"children":{"java.lang.IllegalArgumentException:<init>()":true,"javax.management.RuntimeOperationsException:<init>()":true,"java.lang.Object:getClass()":true,"java.lang.Class:getName()":true},"label":"BaseModelMBean:setManagedResource()","className":"org.apache.tomcat.util.modeler.BaseModelMBean","acdcCluster":"org.apache.tomcat.util.modeler.ss"},{"id":"12263","name":"org.apache.tomcat.util.descriptor.web.ContextEnvironment:getNamingResources()","value":1,"children":{},"label":"ContextEnvironment:getNamingResources()","className":"org.apache.tomcat.util.descriptor.web.ContextEnvironment","acdcCluster":"org.apache.tomcat.util.descriptor.web.ss"},{"id":"12316","name":"org.apache.tomcat.util.descriptor.web.NamingResources:getContainer()","value":1,"children":{},"label":"NamingResources:getContainer()","className":"org.apache.tomcat.util.descriptor.web.NamingResources","acdcCluster":"org.apache.catalina.startup.ss"},{"id":"11658","name":"org.apache.tomcat.util.descriptor.web.ContextEnvironment:getName()","value":1,"children":{},"label":"ContextEnvironment:getName()","className":"org.apache.tomcat.util.descriptor.web.ContextEnvironment","acdcCluster":"org.apache.tomcat.util.descriptor.web.ss"},{"id":"635","name":"javax.management.ObjectName:<init>()","value":1,"children":{},"label":"ObjectName:<init>()","className":"javax.management.ObjectName","acdcCluster":"org.apache.catalina.core.ss"},{"id":"1572","name":"org.apache.catalina.Context:getName()","value":1,"children":{},"label":"Context:getName()","className":"org.apache.catalina.Context","acdcCluster":"org.apache.catalina.startup.ss"},{"id":"1380","name":"org.apache.catalina.util.ContextName:<init>()","value":50,"children":{"java.lang.Object:<init>()":true,"java.lang.String:startsWith()":true,"java.lang.String:substring()":true,"java.lang.String:replaceAll()":true,"java.lang.String:equals()":true,"java.lang.StringBuilder:<init>()":true,"java.lang.StringBuilder:append()":true,"java.lang.StringBuilder:toString()":true,"java.lang.String:toLowerCase()":true,"java.lang.String:endsWith()":true,"java.lang.String:length()":true,"java.lang.String:indexOf()":true},"label":"ContextName:<init>()","className":"org.apache.catalina.util.ContextName","acdcCluster":"org.apache.catalina.startup.ss"},{"id":"1605","name":"org.apache.catalina.Context:getParent()","value":1,"children":{},"label":"Context:getParent()","className":"org.apache.catalina.Context","acdcCluster":"org.apache.catalina.startup.ss"},{"id":"1598","name":"org.apache.catalina.Container:getName()","value":1,"children":{},"label":"Container:getName()","className":"org.apache.catalina.Container","acdcCluster":"org.apache.catalina.core.ss"},{"id":"9578","name":"org.apache.catalina.util.ContextName:getDisplayName()","value":9,"children":{"java.lang.StringBuilder:<init>()":true,"java.lang.String:equals()":true,"java.lang.StringBuilder:append()":true,"java.lang.StringBuilder:toString()":true},"label":"ContextName:getDisplayName()","className":"org.apache.catalina.util.ContextName","acdcCluster":"org.apache.catalina.startup.ss"},{"id":"11660","name":"org.apache.tomcat.util.descriptor.web.ContextResource:getName()","value":1,"children":{},"label":"ContextResource:getName()","className":"org.apache.tomcat.util.descriptor.web.ContextResource","acdcCluster":"org.apache.tomcat.util.descriptor.web.ss"},{"id":"1631","name":"javax.management.ObjectName:quote()","value":1,"children":{},"label":"ObjectName:quote()","className":"javax.management.ObjectName","acdcCluster":"org.apache.catalina.core.ss"},{"id":"12290","name":"org.apache.tomcat.util.descriptor.web.ContextResource:getNamingResources()","value":1,"children":{},"label":"ContextResource:getNamingResources()","className":"org.apache.tomcat.util.descriptor.web.ContextResource","acdcCluster":"org.apache.tomcat.util.descriptor.web.ss"},{"id":"11672","name":"org.apache.tomcat.util.descriptor.web.ContextResource:getType()","value":1,"children":{},"label":"ContextResource:getType()","className":"org.apache.tomcat.util.descriptor.web.ContextResource","acdcCluster":"org.apache.tomcat.util.descriptor.web.ss"},{"id":"11662","name":"org.apache.tomcat.util.descriptor.web.ContextResourceLink:getName()","value":1,"children":{},"label":"ContextResourceLink:getName()","className":"org.apache.tomcat.util.descriptor.web.ContextResourceLink","acdcCluster":"org.apache.catalina.startup.ss"},{"id":"12280","name":"org.apache.tomcat.util.descriptor.web.ContextResourceLink:getNamingResources()","value":1,"children":{},"label":"ContextResourceLink:getNamingResources()","className":"org.apache.tomcat.util.descriptor.web.ContextResourceLink","acdcCluster":"org.apache.catalina.startup.ss"},{"id":"4157","name":"org.apache.catalina.Group:getGroupname()","value":1,"children":{},"label":"Group:getGroupname()","className":"org.apache.catalina.Group","acdcCluster":"org.apache.catalina.users.ss"},{"id":"4160","name":"org.apache.catalina.Group:getUserDatabase()","value":1,"children":{},"label":"Group:getUserDatabase()","className":"org.apache.catalina.Group","acdcCluster":"org.apache.catalina.users.ss"},{"id":"4408","name":"org.apache.catalina.UserDatabase:getId()","value":1,"children":{},"label":"UserDatabase:getId()","className":"org.apache.catalina.UserDatabase","acdcCluster":"org.apache.catalina.users.ss"},{"id":"4216","name":"org.apache.catalina.Loader:getContext()","value":1,"children":{},"label":"Loader:getContext()","className":"org.apache.catalina.Loader","acdcCluster":"org.apache.catalina.startup.ss"},{"id":"4275","name":"org.apache.catalina.Role:getRolename()","value":1,"children":{},"label":"Role:getRolename()","className":"org.apache.catalina.Role","acdcCluster":"org.apache.catalina.users.ss"},{"id":"4277","name":"org.apache.catalina.Role:getUserDatabase()","value":1,"children":{},"label":"Role:getUserDatabase()","className":"org.apache.catalina.Role","acdcCluster":"org.apache.catalina.users.ss"},{"id":"4396","name":"org.apache.catalina.User:getUsername()","value":1,"children":{},"label":"User:getUsername()","className":"org.apache.catalina.User","acdcCluster":"org.apache.catalina.users.ss"},{"id":"4395","name":"org.apache.catalina.User:getUserDatabase()","value":1,"children":{},"label":"User:getUserDatabase()","className":"org.apache.catalina.User","acdcCluster":"org.apache.catalina.users.ss"},{"id":"4415","name":"org.apache.catalina.UserDatabase:findGroup()","value":1,"children":{},"label":"UserDatabase:findGroup()","className":"org.apache.catalina.UserDatabase","acdcCluster":"org.apache.catalina.users.ss"},{"id":"666","name":"javax.management.ObjectName:toString()","value":1,"children":{},"label":"ObjectName:toString()","className":"javax.management.ObjectName","acdcCluster":"org.apache.catalina.core.ss"},{"id":"173","name":"java.util.ArrayList:<init>()","value":1,"children":{},"label":"ArrayList:<init>()","className":"java.util.ArrayList","acdcCluster":"org.apache.el.parser.ss"},{"id":"4407","name":"org.apache.catalina.UserDatabase:getGroups()","value":1,"children":{},"label":"UserDatabase:getGroups()","className":"org.apache.catalina.UserDatabase","acdcCluster":"org.apache.catalina.users.ss"},{"id":"237","name":"java.util.Iterator:hasNext()","value":1,"children":{},"label":"Iterator:hasNext()","className":"java.util.Iterator","acdcCluster":"org.apache.el.stream.ss"},{"id":"238","name":"java.util.Iterator:next()","value":1,"children":{},"label":"Iterator:next()","className":"java.util.Iterator","acdcCluster":"org.apache.el.stream.ss"},{"id":"241","name":"java.util.ArrayList:add()","value":1,"children":{},"label":"ArrayList:add()","className":"java.util.ArrayList","acdcCluster":"org.apache.el.parser.ss"},{"id":"1462","name":"java.util.ArrayList:size()","value":1,"children":{},"label":"ArrayList:size()","className":"java.util.ArrayList","acdcCluster":"org.apache.el.parser.ss"},{"id":"242","name":"java.util.ArrayList:toArray()","value":1,"children":{},"label":"ArrayList:toArray()","className":"java.util.ArrayList","acdcCluster":"org.apache.el.parser.ss"}],"edges":[{"source":"7697","target":"7700"},{"source":"7697","target":"4412"},{"source":"7697","target":"7687"},{"source":"7697","target":"169"},{"source":"7697","target":"170"},{"source":"7697","target":"171"},{"source":"7697","target":"201"},{"source":"7697","target":"11406"},{"source":"7687","target":"7686"},{"source":"7687","target":"2051"},{"source":"7687","target":"169"},{"source":"7687","target":"170"},{"source":"7687","target":"171"},{"source":"7687","target":"1314"},{"source":"7687","target":"12254"},{"source":"7687","target":"12295"},{"source":"7687","target":"12313"},{"source":"7687","target":"2052"},{"source":"7687","target":"7688"},{"source":"7687","target":"2045"},{"source":"7687","target":"12314"},{"source":"7687","target":"12315"},{"source":"7686","target":"165"},{"source":"7686","target":"1520"},{"source":"7686","target":"172"},{"source":"7686","target":"11308"},{"source":"7686","target":"178"},{"source":"2051","target":"1376"},{"source":"2051","target":"165"},{"source":"2051","target":"1520"},{"source":"2051","target":"2051"},{"source":"2051","target":"183"},{"source":"2051","target":"184"},{"source":"2051","target":"30015"},{"source":"2051","target":"30014"},{"source":"2051","target":"169"},{"source":"2051","target":"170"},{"source":"2051","target":"171"},{"source":"2051","target":"191"},{"source":"2051","target":"29970"},{"source":"2051","target":"30013"},{"source":"2052","target":"29962"},{"source":"2052","target":"172"},{"source":"2052","target":"12251"},{"source":"2052","target":"185"},{"source":"2052","target":"181"},{"source":"2052","target":"615"},{"source":"2052","target":"163"},{"source":"2052","target":"169"},{"source":"2052","target":"170"},{"source":"2052","target":"171"},{"source":"2052","target":"12254"},{"source":"2052","target":"164"},{"source":"2052","target":"29919"},{"source":"2052","target":"29926"},{"source":"7688","target":"12263"},{"source":"7688","target":"12316"},{"source":"7688","target":"169"},{"source":"7688","target":"170"},{"source":"7688","target":"11658"},{"source":"7688","target":"171"},{"source":"7688","target":"635"},{"source":"7688","target":"1572"},{"source":"7688","target":"1380"},{"source":"7688","target":"1605"},{"source":"7688","target":"1598"},{"source":"7688","target":"9578"},{"source":"7688","target":"11660"},{"source":"7688","target":"1631"},{"source":"7688","target":"12290"},{"source":"7688","target":"11672"},{"source":"7688","target":"11662"},{"source":"7688","target":"12280"},{"source":"7688","target":"4157"},{"source":"7688","target":"4160"},{"source":"7688","target":"4408"},{"source":"7688","target":"4216"},{"source":"7688","target":"4275"},{"source":"7688","target":"4277"},{"source":"7688","target":"4396"},{"source":"7688","target":"4395"},{"source":"7700","target":"4415"},{"source":"7700","target":"12295"},{"source":"7700","target":"7688"},{"source":"7700","target":"666"},{"source":"7700","target":"169"},{"source":"7700","target":"170"},{"source":"7700","target":"171"},{"source":"7700","target":"201"},{"source":"7700","target":"11406"},{"source":"7694","target":"173"},{"source":"7694","target":"4407"},{"source":"7694","target":"237"},{"source":"7694","target":"238"},{"source":"7694","target":"4157"},{"source":"7694","target":"7700"},{"source":"7694","target":"241"},{"source":"7694","target":"1462"},{"source":"7694","target":"242"}],"groups":[{"id":"cluster","title":"org.apache.catalina.mbeans.MemoryUserDatabaseMBean.ss4"}]}
