{"relatedACDCClusters":{"org.eclipse.jdt.internal.compiler.tool.ss":{"id":"a8f835c1-1721-11ea-8ada-add5f6e8eea0","cluster":"org.eclipse.jdt.internal.compiler.tool.ss","elements":["org.eclipse.jdt.internal.compiler.tool.EclipseCompilerImpl$3","org.eclipse.jdt.internal.compiler.tool.EclipseCompilerImpl$3$2","org.eclipse.jdt.internal.compiler.tool.EclipseCompilerImpl$3$1","org.eclipse.jdt.internal.compiler.problem.DefaultProblemFactory","org.eclipse.jdt.internal.compiler.IProblemFactory","org.eclipse.jdt.core.compiler.CategorizedProblem","org.eclipse.jdt.internal.compiler.problem.DefaultProblem","javax.tools.Diagnostic$Kind","javax.tools.Diagnostic","org.eclipse.jdt.internal.compiler.util.HashtableOfInt","org.eclipse.jdt.internal.compiler.tool.EclipseFileObject","org.eclipse.jdt.internal.compiler.tool.EclipseBatchRequestor","org.eclipse.jdt.internal.compiler.tool.EclipseDiagnostic","org.eclipse.jdt.internal.compiler.tool.EclipseCompilerRequestor","javax.tools.JavaCompiler","org.eclipse.jdt.internal.compiler.tool.EclipseCompiler","javax.tools.JavaCompiler$CompilationTask","org.eclipse.jdt.internal.compiler.tool.EclipseCompiler$1","java.util.WeakHashMap","java.io.OutputStreamWriter","java.io.Writer","javax.lang.model.SourceVersion","javax.tools.DiagnosticListener","org.eclipse.jdt.internal.compiler.tool.Util$EncodingError","org.eclipse.jdt.internal.compiler.tool.Util$EncodingErrorCollector","org.eclipse.jdt.internal.compiler.tool.Util","java.io.PrintStream","java.nio.charset.IllegalCharsetNameException","java.nio.charset.UnsupportedCharsetException","org.eclipse.jdt.internal.compiler.tool.EclipseFileManager","org.eclipse.jdt.internal.compiler.tool.Archive","org.eclipse.jdt.internal.compiler.tool.ArchiveFileObject","java.util.ResourceBundle","java.util.MissingResourceException","java.net.URISyntaxException","java.util.zip.ZipException","java.util.zip.ZipEntry","java.util.zip.ZipFile","javax.tools.StandardLocation","javax.tools.StandardJavaFileManager","org.eclipse.jdt.internal.compiler.batch.Main$ResourceBundleFactory","org.eclipse.jdt.internal.compiler.env.AccessRule","org.eclipse.jdt.internal.compiler.tool.Options","org.eclipse.jdt.internal.compiler.tool.EclipseCompilerImpl$2","org.eclipse.jdt.internal.compiler.batch.ClasspathJsr199","org.eclipse.jdt.internal.compiler.tool.EclipseCompilerImpl$1","org.eclipse.jdt.internal.compiler.tool.EclipseCompilerImpl","org.eclipse.jdt.internal.compiler.tool.EclipseCompilerImpl$4","java.net.URI","java.lang.Iterable","javax.tools.JavaFileManager","javax.tools.JavaFileManager$Location","javax.tools.JavaFileObject","javax.tools.JavaFileObject$Kind","org.eclipse.jdt.internal.compiler.batch.CompilationUnit","org.eclipse.jdt.internal.compiler.batch.ClasspathLocation"]},"org.eclipse.jdt.internal.compiler.classfmt.ss":{"id":"a8f835c2-1721-11ea-8ada-add5f6e8eea0","cluster":"org.eclipse.jdt.internal.compiler.classfmt.ss","elements":["org.eclipse.jdt.internal.compiler.classfmt.AnnotationMethodInfo","org.eclipse.jdt.internal.compiler.classfmt.AnnotationMethodInfoWithAnnotations","org.eclipse.jdt.internal.compiler.classfmt.NonNullDefaultAwareTypeAnnotationWalker","org.eclipse.jdt.internal.compiler.classfmt.NonNullDefaultAwareTypeAnnotationWalker$1","org.eclipse.jdt.internal.compiler.classfmt.MethodInfoWithTypeAnnotations","org.eclipse.jdt.internal.compiler.classfmt.MethodInfo","org.eclipse.jdt.internal.compiler.classfmt.MethodInfoWithParameterAnnotations","org.eclipse.jdt.internal.compiler.classfmt.AnnotationInfo","org.eclipse.jdt.internal.compiler.classfmt.ClassFileStruct","org.eclipse.jdt.internal.compiler.classfmt.MethodInfoWithAnnotations","org.eclipse.jdt.internal.compiler.classfmt.TypeAnnotationInfo","org.eclipse.jdt.internal.compiler.classfmt.ExternalAnnotationProvider$DispatchingAnnotationWalker","org.eclipse.jdt.internal.compiler.classfmt.ExternalAnnotationProvider","org.eclipse.jdt.internal.compiler.classfmt.ExternalAnnotationProvider$2","org.eclipse.jdt.internal.compiler.classfmt.ExternalAnnotationProvider$FieldAnnotationWalker","org.eclipse.jdt.internal.compiler.classfmt.ExternalAnnotationProvider$SuperTypesAnnotationWalker","org.eclipse.jdt.internal.compiler.classfmt.ExternalAnnotationProvider$TypeParametersAnnotationWalker","org.eclipse.jdt.internal.compiler.classfmt.ExternalAnnotationProvider$SingleMarkerAnnotation","org.eclipse.jdt.internal.compiler.classfmt.ExternalAnnotationProvider$BasicAnnotationWalker","org.eclipse.jdt.internal.compiler.classfmt.ExternalAnnotationProvider$MethodAnnotationWalker","org.eclipse.jdt.internal.compiler.classfmt.ExternalAnnotationProvider$1","java.lang.UnsupportedOperationException","org.eclipse.jdt.core.compiler.CharOperation","java.io.LineNumberReader","org.eclipse.jdt.internal.compiler.env.IBinaryAnnotation","org.eclipse.jdt.internal.compiler.classfmt.ElementValuePairInfo","org.eclipse.jdt.internal.compiler.env.IBinaryElementValuePair","org.eclipse.jdt.internal.compiler.classfmt.ExternalAnnotationProvider$IMethodAnnotationWalker","org.eclipse.jdt.internal.compiler.lookup.SignatureWrapper","org.eclipse.jdt.internal.compiler.util.HashtableOfIntValues","org.eclipse.jdt.internal.compiler.classfmt.FieldInfoWithAnnotation","org.eclipse.jdt.internal.compiler.classfmt.FieldInfo","org.eclipse.jdt.internal.compiler.classfmt.FieldInfoWithTypeAnnotation","org.eclipse.jdt.internal.compiler.classfmt.ClassFileReader","org.eclipse.jdt.internal.compiler.classfmt.InnerClassInfo","org.eclipse.jdt.internal.compiler.env.IBinaryNestedType","org.eclipse.jdt.internal.compiler.classfmt.ClassFileReader$ZipFileProducer"]},"org.eclipse.jdt.internal.compiler.util.ss":{"id":"a8f835bc-1721-11ea-8ada-add5f6e8eea0","cluster":"org.eclipse.jdt.internal.compiler.util.ss","elements":["org.eclipse.jdt.internal.compiler.util.Sorting","org.eclipse.jdt.internal.compiler.util.Sorting$1","org.eclipse.jdt.internal.compiler.util.GenericXMLWriter","org.eclipse.jdt.internal.compiler.util.GenericXMLWriter$1","org.eclipse.jdt.internal.compiler.util.Messages$MessagesProperties","org.eclipse.jdt.internal.compiler.util.Messages","java.lang.SecurityException","java.lang.reflect.Field","java.text.MessageFormat","org.eclipse.jdt.internal.compiler.util.Util","org.eclipse.jdt.internal.compiler.util.Util$1","org.eclipse.jdt.internal.compiler.util.Util$Displayable","java.lang.ArrayIndexOutOfBoundsException","java.io.InputStreamReader","java.io.BufferedOutputStream","java.io.BufferedInputStream","java.io.ByteArrayInputStream","java.io.StringWriter","org.eclipse.jdt.internal.compiler.util.SuffixConstants"]},"org.eclipse.jdt.internal.compiler.apt.dispatch.ss":{"id":"a8f883da-1721-11ea-8ada-add5f6e8eea0","cluster":"org.eclipse.jdt.internal.compiler.apt.dispatch.ss","elements":["org.eclipse.jdt.internal.compiler.apt.dispatch.BaseAnnotationProcessorManager","org.eclipse.jdt.internal.compiler.apt.dispatch.IProcessorProvider","org.eclipse.jdt.internal.compiler.apt.dispatch.RoundDispatcher","javax.annotation.processing.RoundEnvironment","org.eclipse.jdt.internal.compiler.apt.util.ManyToMany","org.eclipse.jdt.internal.compiler.apt.dispatch.RoundEnvImpl","javax.lang.model.util.ElementFilter","org.eclipse.jdt.internal.compiler.apt.dispatch.AnnotationDiscoveryVisitor","java.util.Set","java.lang.AssertionError","javax.lang.model.element.TypeElement","org.eclipse.jdt.internal.compiler.apt.dispatch.ProcessorInfo","javax.annotation.processing.Processor","org.eclipse.jdt.internal.compiler.apt.dispatch.BaseProcessingEnvImpl","org.eclipse.jdt.internal.compiler.apt.model.TypesImpl","org.eclipse.jdt.internal.compiler.apt.model.ElementsImpl","javax.lang.model.util.Types","javax.lang.model.util.Elements","javax.lang.model.type.DeclaredType","javax.lang.model.type.ArrayType","javax.lang.model.type.ExecutableType","javax.lang.model.type.PrimitiveType","org.eclipse.jdt.internal.compiler.apt.dispatch.HookedJavaFileObject$ForwardingWriter","org.eclipse.jdt.internal.compiler.apt.dispatch.HookedJavaFileObject$ForwardingOutputStream","org.eclipse.jdt.internal.compiler.apt.dispatch.HookedJavaFileObject","javax.tools.ForwardingJavaFileObject","java.lang.CloneNotSupportedException","java.lang.Appendable","org.eclipse.jdt.internal.compiler.apt.dispatch.BatchFilerImpl","javax.annotation.processing.FilerException","java.util.ServiceConfigurationError","org.eclipse.jdt.internal.compiler.apt.dispatch.BatchAnnotationProcessorManager","java.util.ServiceLoader","javax.annotation.processing.ProcessingEnvironment","org.eclipse.jdt.internal.compiler.apt.util.EclipseFileObject","org.eclipse.jdt.internal.compiler.apt.util.EclipseFileManager","org.eclipse.jdt.internal.compiler.apt.util.Options","org.eclipse.jdt.internal.compiler.apt.dispatch.BatchProcessingEnvImpl","org.eclipse.jdt.internal.compiler.apt.util.Archive","org.eclipse.jdt.internal.compiler.apt.util.ArchiveFileObject","java.util.StringTokenizer","java.nio.charset.Charset","java.lang.NoSuchFieldError","java.io.FileReader","org.eclipse.jdt.internal.compiler.classfmt.ClassFormatException","javax.annotation.processing.Filer","javax.annotation.processing.Messager","javax.tools.FileObject","javax.lang.model.element.NestingKind","javax.tools.SimpleJavaFileObject","org.eclipse.jdt.internal.compiler.apt.dispatch.BaseMessagerImpl","org.eclipse.jdt.internal.compiler.apt.dispatch.BatchMessagerImpl","org.eclipse.jdt.internal.compiler.apt.dispatch.AptProblem","org.eclipse.jdt.internal.compiler.lookup.AptSourceLocalVariableBinding","javax.lang.model.element.AnnotationValue"]},"org.eclipse.jdt.internal.compiler.apt.util.ss":{"id":"a8f883dd-1721-11ea-8ada-add5f6e8eea0","cluster":"org.eclipse.jdt.internal.compiler.apt.util.ss","elements":["org.eclipse.jdt.internal.compiler.apt.util.Util$EncodingError","org.eclipse.jdt.internal.compiler.apt.util.Util$EncodingErrorCollector","org.eclipse.jdt.internal.compiler.apt.util.Util"]}},"nodes":[{"id":"21235","name":"org.eclipse.jdt.internal.compiler.tool.EclipseFileObject:$SWITCH_TABLE$javax$tools$JavaFileObject$Kind()","value":6,"children":{"javax.tools.JavaFileObject$Kind:values()":true,"javax.tools.JavaFileObject$Kind:ordinal()":true},"label":"EclipseFileObject:$SWITCH_TABLE$javax$tools$JavaFileObject$Kind()","className":"org.eclipse.jdt.internal.compiler.tool.EclipseFileObject","acdcCluster":"org.eclipse.jdt.internal.compiler.tool.ss","groupId":"cluster"},{"id":"21222","name":"org.eclipse.jdt.internal.compiler.tool.EclipseFileObject:getNestingKind()","value":7,"children":{"org.eclipse.jdt.internal.compiler.tool.EclipseFileObject:$SWITCH_TABLE$javax$tools$JavaFileObject$Kind()":true,"javax.tools.JavaFileObject$Kind:ordinal()":true,"org.eclipse.jdt.internal.compiler.classfmt.ClassFileReader:read()":true,"org.eclipse.jdt.internal.compiler.classfmt.ClassFileReader:isAnonymous()":true,"org.eclipse.jdt.internal.compiler.classfmt.ClassFileReader:isLocal()":true,"org.eclipse.jdt.internal.compiler.classfmt.ClassFileReader:isMember()":true},"label":"EclipseFileObject:getNestingKind()","className":"org.eclipse.jdt.internal.compiler.tool.EclipseFileObject","acdcCluster":"org.eclipse.jdt.internal.compiler.tool.ss","groupId":"cluster"},{"id":"16205","name":"org.eclipse.jdt.internal.compiler.classfmt.ClassFileReader:read()","value":21,"children":{"org.eclipse.jdt.internal.compiler.classfmt.ClassFileReader:read()":true,"org.eclipse.jdt.internal.compiler.util.Util:getFileByteContent()":true,"java.io.File:getAbsolutePath()":true,"java.lang.String:toCharArray()":true,"org.eclipse.jdt.internal.compiler.classfmt.ClassFileReader:<init>()":true,"org.eclipse.jdt.internal.compiler.classfmt.ClassFileReader:initialize()":true,"org.eclipse.jdt.internal.compiler.util.Util:getInputStreamAsByteArray()":true,"java.util.zip.ZipFile:getEntry()":true,"org.eclipse.jdt.internal.compiler.util.Util:getZipEntryByteContent()":true,"java.io.File:<init>()":true},"label":"ClassFileReader:read()","className":"org.eclipse.jdt.internal.compiler.classfmt.ClassFileReader","acdcCluster":"org.eclipse.jdt.internal.compiler.classfmt.ss","groupId":"cluster"},{"id":"16240","name":"org.eclipse.jdt.internal.compiler.classfmt.ClassFileReader:isAnonymous()","value":2,"children":{"org.eclipse.jdt.internal.compiler.classfmt.InnerClassInfo:getSourceName()":true},"label":"ClassFileReader:isAnonymous()","className":"org.eclipse.jdt.internal.compiler.classfmt.ClassFileReader","acdcCluster":"org.eclipse.jdt.internal.compiler.classfmt.ss","groupId":"cluster"},{"id":"16242","name":"org.eclipse.jdt.internal.compiler.classfmt.ClassFileReader:isLocal()","value":3,"children":{"org.eclipse.jdt.internal.compiler.classfmt.InnerClassInfo:getEnclosingTypeName()":true,"org.eclipse.jdt.internal.compiler.classfmt.InnerClassInfo:getSourceName()":true},"label":"ClassFileReader:isLocal()","className":"org.eclipse.jdt.internal.compiler.classfmt.ClassFileReader","acdcCluster":"org.eclipse.jdt.internal.compiler.classfmt.ss","groupId":"cluster"},{"id":"16243","name":"org.eclipse.jdt.internal.compiler.classfmt.ClassFileReader:isMember()","value":3,"children":{"org.eclipse.jdt.internal.compiler.classfmt.InnerClassInfo:getEnclosingTypeName()":true,"org.eclipse.jdt.internal.compiler.classfmt.InnerClassInfo:getSourceName()":true},"label":"ClassFileReader:isMember()","className":"org.eclipse.jdt.internal.compiler.classfmt.ClassFileReader","acdcCluster":"org.eclipse.jdt.internal.compiler.classfmt.ss","groupId":"cluster"},{"id":"21476","name":"org.eclipse.jdt.internal.compiler.util.Util:getZipEntryByteContent()","value":12,"children":{"java.util.zip.ZipFile:getInputStream()":true,"java.lang.StringBuilder:<init>()":true,"java.util.zip.ZipEntry:getName()":true,"java.lang.StringBuilder:append()":true,"java.lang.StringBuilder:toString()":true,"java.io.IOException:<init>()":true,"java.io.BufferedInputStream:<init>()":true,"java.util.zip.ZipEntry:getSize()":true,"org.eclipse.jdt.internal.compiler.util.Util:getInputStreamAsByteArray()":true,"java.io.InputStream:close()":true},"label":"Util:getZipEntryByteContent()","className":"org.eclipse.jdt.internal.compiler.util.Util","acdcCluster":"org.eclipse.jdt.internal.compiler.util.ss","groupId":"cluster"},{"id":"21469","name":"org.eclipse.jdt.internal.compiler.util.Util:getFileByteContent()","value":7,"children":{"java.io.FileInputStream:<init>()":true,"java.io.BufferedInputStream:<init>()":true,"java.io.File:length()":true,"org.eclipse.jdt.internal.compiler.util.Util:getInputStreamAsByteArray()":true,"java.io.InputStream:close()":true},"label":"Util:getFileByteContent()","className":"org.eclipse.jdt.internal.compiler.util.Util","acdcCluster":"org.eclipse.jdt.internal.compiler.util.ss","groupId":"cluster"},{"id":"21472","name":"org.eclipse.jdt.internal.compiler.util.Util:getInputStreamAsByteArray()","value":7,"children":{"java.io.InputStream:available()":true,"java.lang.Math:max()":true,"java.lang.System:arraycopy()":true,"java.io.InputStream:read()":true},"label":"Util:getInputStreamAsByteArray()","className":"org.eclipse.jdt.internal.compiler.util.Util","acdcCluster":"org.eclipse.jdt.internal.compiler.util.ss","groupId":"cluster"},{"id":"16402","name":"org.eclipse.jdt.internal.compiler.classfmt.InnerClassInfo:getEnclosingTypeName()","value":4,"children":{"org.eclipse.jdt.internal.compiler.classfmt.InnerClassInfo:u2At()":true,"org.eclipse.jdt.internal.compiler.classfmt.InnerClassInfo:utf8At()":true},"label":"InnerClassInfo:getEnclosingTypeName()","className":"org.eclipse.jdt.internal.compiler.classfmt.InnerClassInfo","acdcCluster":"org.eclipse.jdt.internal.compiler.classfmt.ss","groupId":"cluster"},{"id":"16405","name":"org.eclipse.jdt.internal.compiler.classfmt.InnerClassInfo:getSourceName()","value":3,"children":{"org.eclipse.jdt.internal.compiler.classfmt.InnerClassInfo:u2At()":true,"org.eclipse.jdt.internal.compiler.classfmt.InnerClassInfo:utf8At()":true},"label":"InnerClassInfo:getSourceName()","className":"org.eclipse.jdt.internal.compiler.classfmt.InnerClassInfo","acdcCluster":"org.eclipse.jdt.internal.compiler.classfmt.ss","groupId":"cluster"},{"id":"22213","name":"org.eclipse.jdt.internal.compiler.classfmt.InnerClassInfo:u2At()","value":1,"children":{},"label":"InnerClassInfo:u2At()","className":"org.eclipse.jdt.internal.compiler.classfmt.InnerClassInfo","acdcCluster":"org.eclipse.jdt.internal.compiler.classfmt.ss","groupId":"cluster"},{"id":"22214","name":"org.eclipse.jdt.internal.compiler.classfmt.InnerClassInfo:utf8At()","value":1,"children":{},"label":"InnerClassInfo:utf8At()","className":"org.eclipse.jdt.internal.compiler.classfmt.InnerClassInfo","acdcCluster":"org.eclipse.jdt.internal.compiler.classfmt.ss","groupId":"cluster"},{"id":"13700","name":"org.eclipse.jdt.internal.compiler.apt.util.ArchiveFileObject:getAccessLevel()","value":8,"children":{"org.eclipse.jdt.internal.compiler.apt.util.ArchiveFileObject:getKind()":true,"java.util.zip.ZipFile:<init>()":true,"org.eclipse.jdt.internal.compiler.classfmt.ClassFileReader:read()":true,"java.util.zip.ZipFile:close()":true,"java.lang.Throwable:addSuppressed()":true,"org.eclipse.jdt.internal.compiler.classfmt.ClassFileReader:accessFlags()":true},"label":"ArchiveFileObject:getAccessLevel()","className":"org.eclipse.jdt.internal.compiler.apt.util.ArchiveFileObject","acdcCluster":"org.eclipse.jdt.internal.compiler.apt.dispatch.ss","groupId":"cluster"},{"id":"13707","name":"org.eclipse.jdt.internal.compiler.apt.util.ArchiveFileObject:getCharContent()","value":10,"children":{"org.eclipse.jdt.internal.compiler.apt.util.ArchiveFileObject:getKind()":true,"java.util.zip.ZipFile:<init>()":true,"java.util.zip.ZipFile:getEntry()":true,"org.eclipse.jdt.internal.compiler.util.Util:getZipEntryByteContent()":true,"java.nio.charset.Charset:name()":true,"org.eclipse.jdt.internal.compiler.apt.util.Util:getCharContents()":true,"java.util.zip.ZipFile:close()":true,"java.lang.Throwable:addSuppressed()":true},"label":"ArchiveFileObject:getCharContent()","className":"org.eclipse.jdt.internal.compiler.apt.util.ArchiveFileObject","acdcCluster":"org.eclipse.jdt.internal.compiler.apt.dispatch.ss","groupId":"cluster"},{"id":"13762","name":"org.eclipse.jdt.internal.compiler.apt.util.EclipseFileObject:getCharContent()","value":4,"children":{"org.eclipse.jdt.internal.compiler.util.Util:getFileByteContent()":true,"java.nio.charset.Charset:name()":true,"org.eclipse.jdt.internal.compiler.apt.util.Util:getCharContents()":true},"label":"EclipseFileObject:getCharContent()","className":"org.eclipse.jdt.internal.compiler.apt.util.EclipseFileObject","acdcCluster":"org.eclipse.jdt.internal.compiler.apt.dispatch.ss","groupId":"cluster"},{"id":"13808","name":"org.eclipse.jdt.internal.compiler.apt.util.Util:getInputStreamAsCharArray()","value":19,"children":{"java.nio.charset.Charset:forName()":true,"java.lang.StringBuilder:<init>()":true,"java.lang.StringBuilder:append()":true,"java.lang.StringBuilder:toString()":true,"java.io.PrintStream:println()":true,"java.nio.charset.Charset:newDecoder()":true,"java.nio.charset.CharsetDecoder:onMalformedInput()":true,"java.nio.charset.CharsetDecoder:onUnmappableCharacter()":true,"org.eclipse.jdt.internal.compiler.util.Util:getInputStreamAsByteArray()":true,"java.nio.ByteBuffer:allocate()":true,"java.nio.ByteBuffer:put()":true,"java.nio.ByteBuffer:flip()":true,"java.nio.charset.CharsetDecoder:decode()":true,"java.nio.CharBuffer:array()":true},"label":"Util:getInputStreamAsCharArray()","className":"org.eclipse.jdt.internal.compiler.apt.util.Util","acdcCluster":"org.eclipse.jdt.internal.compiler.apt.util.ss","groupId":"cluster"},{"id":"16406","name":"org.eclipse.jdt.internal.compiler.classfmt.InnerClassInfo:toString()","value":14,"children":{"java.lang.StringBuffer:<init>()":true,"org.eclipse.jdt.internal.compiler.classfmt.InnerClassInfo:getName()":true,"java.lang.StringBuffer:append()":true,"org.eclipse.jdt.internal.compiler.classfmt.InnerClassInfo:getEnclosingTypeName()":true,"org.eclipse.jdt.internal.compiler.classfmt.InnerClassInfo:getSourceName()":true,"java.lang.StringBuffer:toString()":true},"label":"InnerClassInfo:toString()","className":"org.eclipse.jdt.internal.compiler.classfmt.InnerClassInfo","acdcCluster":"org.eclipse.jdt.internal.compiler.classfmt.ss","groupId":"cluster"},{"id":"21081","name":"org.eclipse.jdt.internal.compiler.tool.ArchiveFileObject:getCharContent()","value":10,"children":{"org.eclipse.jdt.internal.compiler.tool.ArchiveFileObject:getKind()":true,"java.util.zip.ZipFile:<init>()":true,"java.util.zip.ZipFile:getEntry()":true,"org.eclipse.jdt.internal.compiler.util.Util:getZipEntryByteContent()":true,"java.nio.charset.Charset:name()":true,"org.eclipse.jdt.internal.compiler.tool.Util:getCharContents()":true,"java.util.zip.ZipFile:close()":true,"java.lang.Throwable:addSuppressed()":true},"label":"ArchiveFileObject:getCharContent()","className":"org.eclipse.jdt.internal.compiler.tool.ArchiveFileObject","acdcCluster":"org.eclipse.jdt.internal.compiler.tool.ss","groupId":"cluster"},{"id":"21225","name":"org.eclipse.jdt.internal.compiler.tool.EclipseFileObject:getCharContent()","value":4,"children":{"org.eclipse.jdt.internal.compiler.util.Util:getFileByteContent()":true,"java.nio.charset.Charset:name()":true,"org.eclipse.jdt.internal.compiler.tool.Util:getCharContents()":true},"label":"EclipseFileObject:getCharContent()","className":"org.eclipse.jdt.internal.compiler.tool.EclipseFileObject","acdcCluster":"org.eclipse.jdt.internal.compiler.tool.ss","groupId":"cluster"},{"id":"21251","name":"org.eclipse.jdt.internal.compiler.tool.Util:getInputStreamAsCharArray()","value":19,"children":{"java.nio.charset.Charset:forName()":true,"java.lang.StringBuilder:<init>()":true,"java.lang.StringBuilder:append()":true,"java.lang.StringBuilder:toString()":true,"java.io.PrintStream:println()":true,"java.nio.charset.Charset:newDecoder()":true,"java.nio.charset.CharsetDecoder:onMalformedInput()":true,"java.nio.charset.CharsetDecoder:onUnmappableCharacter()":true,"org.eclipse.jdt.internal.compiler.util.Util:getInputStreamAsByteArray()":true,"java.nio.ByteBuffer:allocate()":true,"java.nio.ByteBuffer:put()":true,"java.nio.ByteBuffer:flip()":true,"java.nio.charset.CharsetDecoder:decode()":true,"java.nio.CharBuffer:array()":true},"label":"Util:getInputStreamAsCharArray()","className":"org.eclipse.jdt.internal.compiler.tool.Util","acdcCluster":"org.eclipse.jdt.internal.compiler.tool.ss","groupId":"cluster"},{"id":"21538","name":"javax.tools.JavaFileObject$Kind:values()","value":1,"children":{},"label":"JavaFileObject$Kind:values()","className":"javax.tools.JavaFileObject$Kind","acdcCluster":"org.eclipse.jdt.internal.compiler.tool.ss"},{"id":"21536","name":"javax.tools.JavaFileObject$Kind:ordinal()","value":1,"children":{},"label":"JavaFileObject$Kind:ordinal()","className":"javax.tools.JavaFileObject$Kind","acdcCluster":"org.eclipse.jdt.internal.compiler.tool.ss"},{"id":"232","name":"java.io.File:getAbsolutePath()","value":1,"children":{},"label":"File:getAbsolutePath()","className":"java.io.File","acdcCluster":"org.apache.catalina.startup.ss"},{"id":"11236","name":"java.lang.String:toCharArray()","value":1,"children":{},"label":"String:toCharArray()","className":"java.lang.String","acdcCluster":"org.apache.catalina.valves.ss"},{"id":"16206","name":"org.eclipse.jdt.internal.compiler.classfmt.ClassFileReader:<init>()","value":67,"children":{"org.eclipse.jdt.internal.compiler.classfmt.ClassFileReader:<init>()":true,"org.eclipse.jdt.internal.compiler.classfmt.ClassFileStruct:<init>()":true,"org.eclipse.jdt.internal.compiler.classfmt.ClassFileReader:u2At()":true,"org.eclipse.jdt.internal.compiler.classfmt.ClassFileReader:u1At()":true,"org.eclipse.jdt.internal.compiler.classfmt.ClassFileReader:getConstantClassNameAt()":true,"org.eclipse.jdt.internal.compiler.classfmt.FieldInfo:createField()":true,"org.eclipse.jdt.internal.compiler.classfmt.FieldInfo:sizeInBytes()":true,"org.eclipse.jdt.internal.compiler.classfmt.AnnotationMethodInfo:createAnnotationMethod()":true,"org.eclipse.jdt.internal.compiler.classfmt.MethodInfo:createMethod()":true,"org.eclipse.jdt.internal.compiler.classfmt.MethodInfo:sizeInBytes()":true,"org.eclipse.jdt.internal.compiler.classfmt.ClassFileReader:utf8At()":true,"org.eclipse.jdt.internal.compiler.classfmt.ClassFileReader:u4At()":true,"org.eclipse.jdt.core.compiler.CharOperation:equals()":true,"org.eclipse.jdt.internal.compiler.classfmt.InnerClassInfo:<init>()":true,"org.eclipse.jdt.internal.compiler.classfmt.InnerClassInfo:getEnclosingTypeName()":true,"org.eclipse.jdt.internal.compiler.classfmt.ClassFileReader:decodeAnnotations()":true,"org.eclipse.jdt.internal.compiler.classfmt.ClassFileReader:decodeTypeAnnotations()":true,"org.eclipse.jdt.core.compiler.CharOperation:splitOn()":true,"org.eclipse.jdt.internal.compiler.classfmt.ClassFileReader:initialize()":true,"org.eclipse.jdt.internal.compiler.classfmt.ClassFormatException:<init>()":true},"label":"ClassFileReader:<init>()","className":"org.eclipse.jdt.internal.compiler.classfmt.ClassFileReader","acdcCluster":"org.eclipse.jdt.internal.compiler.classfmt.ss"},{"id":"16239","name":"org.eclipse.jdt.internal.compiler.classfmt.ClassFileReader:initialize()","value":8,"children":{"org.eclipse.jdt.internal.compiler.classfmt.FieldInfo:initialize()":true,"org.eclipse.jdt.internal.compiler.classfmt.MethodInfo:initialize()":true,"org.eclipse.jdt.internal.compiler.classfmt.InnerClassInfo:initialize()":true,"org.eclipse.jdt.internal.compiler.classfmt.AnnotationInfo:initialize()":true,"org.eclipse.jdt.internal.compiler.classfmt.ClassFileReader:getEnclosingMethod()":true,"org.eclipse.jdt.internal.compiler.classfmt.ClassFileReader:reset()":true,"org.eclipse.jdt.internal.compiler.classfmt.ClassFormatException:<init>()":true},"label":"ClassFileReader:initialize()","className":"org.eclipse.jdt.internal.compiler.classfmt.ClassFileReader","acdcCluster":"org.eclipse.jdt.internal.compiler.classfmt.ss"},{"id":"21647","name":"java.util.zip.ZipFile:getEntry()","value":1,"children":{},"label":"ZipFile:getEntry()","className":"java.util.zip.ZipFile","acdcCluster":"org.eclipse.jdt.internal.compiler.tool.ss"},{"id":"206","name":"java.io.File:<init>()","value":1,"children":{},"label":"File:<init>()","className":"java.io.File","acdcCluster":"org.apache.catalina.startup.ss"},{"id":"16248","name":"org.eclipse.jdt.internal.compiler.classfmt.ClassFileStruct:<init>()","value":2,"children":{"java.lang.Object:<init>()":true},"label":"ClassFileStruct:<init>()","className":"org.eclipse.jdt.internal.compiler.classfmt.ClassFileStruct","acdcCluster":"org.eclipse.jdt.internal.compiler.classfmt.ss"},{"id":"22189","name":"org.eclipse.jdt.internal.compiler.classfmt.ClassFileReader:u2At()","value":1,"children":{},"label":"ClassFileReader:u2At()","className":"org.eclipse.jdt.internal.compiler.classfmt.ClassFileReader","acdcCluster":"org.eclipse.jdt.internal.compiler.classfmt.ss"},{"id":"22190","name":"org.eclipse.jdt.internal.compiler.classfmt.ClassFileReader:u1At()","value":1,"children":{},"label":"ClassFileReader:u1At()","className":"org.eclipse.jdt.internal.compiler.classfmt.ClassFileReader","acdcCluster":"org.eclipse.jdt.internal.compiler.classfmt.ss"},{"id":"16215","name":"org.eclipse.jdt.internal.compiler.classfmt.ClassFileReader:getConstantClassNameAt()","value":4,"children":{"org.eclipse.jdt.internal.compiler.classfmt.ClassFileReader:u2At()":true,"org.eclipse.jdt.internal.compiler.classfmt.ClassFileReader:utf8At()":true},"label":"ClassFileReader:getConstantClassNameAt()","className":"org.eclipse.jdt.internal.compiler.classfmt.ClassFileReader","acdcCluster":"org.eclipse.jdt.internal.compiler.classfmt.ss"},{"id":"16363","name":"org.eclipse.jdt.internal.compiler.classfmt.FieldInfo:createField()","value":23,"children":{"org.eclipse.jdt.internal.compiler.classfmt.FieldInfo:<init>()":true,"org.eclipse.jdt.internal.compiler.classfmt.FieldInfo:u2At()":true,"org.eclipse.jdt.internal.compiler.classfmt.FieldInfo:utf8At()":true,"org.eclipse.jdt.core.compiler.CharOperation:equals()":true,"org.eclipse.jdt.internal.compiler.classfmt.FieldInfo:decodeAnnotations()":true,"org.eclipse.jdt.internal.compiler.classfmt.FieldInfo:decodeTypeAnnotations()":true,"java.lang.System:arraycopy()":true,"org.eclipse.jdt.internal.compiler.classfmt.FieldInfo:u4At()":true,"org.eclipse.jdt.internal.compiler.classfmt.FieldInfoWithTypeAnnotation:<init>()":true,"org.eclipse.jdt.internal.compiler.classfmt.FieldInfoWithAnnotation:<init>()":true},"label":"FieldInfo:createField()","className":"org.eclipse.jdt.internal.compiler.classfmt.FieldInfo","acdcCluster":"org.eclipse.jdt.internal.compiler.classfmt.ss"},{"id":"16384","name":"org.eclipse.jdt.internal.compiler.classfmt.FieldInfo:sizeInBytes()","value":1,"children":{},"label":"FieldInfo:sizeInBytes()","className":"org.eclipse.jdt.internal.compiler.classfmt.FieldInfo","acdcCluster":"org.eclipse.jdt.internal.compiler.classfmt.ss"},{"id":"16191","name":"org.eclipse.jdt.internal.compiler.classfmt.AnnotationMethodInfo:createAnnotationMethod()","value":21,"children":{"org.eclipse.jdt.internal.compiler.classfmt.MethodInfo:<init>()":true,"org.eclipse.jdt.internal.compiler.classfmt.MethodInfo:u2At()":true,"org.eclipse.jdt.internal.compiler.classfmt.MethodInfo:utf8At()":true,"org.eclipse.jdt.core.compiler.CharOperation:equals()":true,"org.eclipse.jdt.internal.compiler.classfmt.AnnotationInfo:<init>()":true,"org.eclipse.jdt.internal.compiler.classfmt.AnnotationInfo:decodeDefaultValue()":true,"org.eclipse.jdt.internal.compiler.classfmt.AnnotationMethodInfo:decodeMethodAnnotations()":true,"java.lang.System:arraycopy()":true,"org.eclipse.jdt.internal.compiler.classfmt.MethodInfo:u4At()":true,"org.eclipse.jdt.internal.compiler.classfmt.AnnotationMethodInfoWithAnnotations:<init>()":true,"org.eclipse.jdt.internal.compiler.classfmt.AnnotationMethodInfo:<init>()":true,"org.eclipse.jdt.internal.compiler.classfmt.MethodInfoWithAnnotations:<init>()":true},"label":"AnnotationMethodInfo:createAnnotationMethod()","className":"org.eclipse.jdt.internal.compiler.classfmt.AnnotationMethodInfo","acdcCluster":"org.eclipse.jdt.internal.compiler.classfmt.ss"},{"id":"16410","name":"org.eclipse.jdt.internal.compiler.classfmt.MethodInfo:createMethod()","value":32,"children":{"org.eclipse.jdt.internal.compiler.classfmt.MethodInfo:<init>()":true,"org.eclipse.jdt.internal.compiler.classfmt.MethodInfo:u2At()":true,"org.eclipse.jdt.internal.compiler.classfmt.MethodInfo:utf8At()":true,"org.eclipse.jdt.core.compiler.CharOperation:equals()":true,"org.eclipse.jdt.internal.compiler.classfmt.MethodInfo:decodeMethodParameters()":true,"org.eclipse.jdt.internal.compiler.classfmt.MethodInfo:decodeMethodAnnotations()":true,"org.eclipse.jdt.internal.compiler.classfmt.MethodInfo:decodeParamAnnotations()":true,"org.eclipse.jdt.internal.compiler.classfmt.MethodInfo:decodeTypeAnnotations()":true,"java.lang.System:arraycopy()":true,"org.eclipse.jdt.internal.compiler.classfmt.MethodInfo:u4At()":true,"org.eclipse.jdt.internal.compiler.classfmt.MethodInfoWithTypeAnnotations:<init>()":true,"org.eclipse.jdt.internal.compiler.classfmt.MethodInfoWithParameterAnnotations:<init>()":true,"org.eclipse.jdt.internal.compiler.classfmt.MethodInfoWithAnnotations:<init>()":true},"label":"MethodInfo:createMethod()","className":"org.eclipse.jdt.internal.compiler.classfmt.MethodInfo","acdcCluster":"org.eclipse.jdt.internal.compiler.classfmt.ss"},{"id":"16437","name":"org.eclipse.jdt.internal.compiler.classfmt.MethodInfo:sizeInBytes()","value":1,"children":{},"label":"MethodInfo:sizeInBytes()","className":"org.eclipse.jdt.internal.compiler.classfmt.MethodInfo","acdcCluster":"org.eclipse.jdt.internal.compiler.classfmt.ss"},{"id":"22191","name":"org.eclipse.jdt.internal.compiler.classfmt.ClassFileReader:utf8At()","value":1,"children":{},"label":"ClassFileReader:utf8At()","className":"org.eclipse.jdt.internal.compiler.classfmt.ClassFileReader","acdcCluster":"org.eclipse.jdt.internal.compiler.classfmt.ss"},{"id":"22192","name":"org.eclipse.jdt.internal.compiler.classfmt.ClassFileReader:u4At()","value":1,"children":{},"label":"ClassFileReader:u4At()","className":"org.eclipse.jdt.internal.compiler.classfmt.ClassFileReader","acdcCluster":"org.eclipse.jdt.internal.compiler.classfmt.ss"},{"id":"13861","name":"org.eclipse.jdt.core.compiler.CharOperation:equals()","value":10,"children":{"org.eclipse.jdt.core.compiler.CharOperation:equals()":true,"org.eclipse.jdt.internal.compiler.parser.ScannerHelper:toLowerCase()":true},"label":"CharOperation:equals()","className":"org.eclipse.jdt.core.compiler.CharOperation","acdcCluster":"org.eclipse.jdt.internal.compiler.classfmt.ss"},{"id":"16401","name":"org.eclipse.jdt.internal.compiler.classfmt.InnerClassInfo:<init>()","value":5,"children":{"org.eclipse.jdt.internal.compiler.classfmt.ClassFileStruct:<init>()":true,"org.eclipse.jdt.internal.compiler.classfmt.InnerClassInfo:u2At()":true},"label":"InnerClassInfo:<init>()","className":"org.eclipse.jdt.internal.compiler.classfmt.InnerClassInfo","acdcCluster":"org.eclipse.jdt.internal.compiler.classfmt.ss"},{"id":"16211","name":"org.eclipse.jdt.internal.compiler.classfmt.ClassFileReader:decodeAnnotations()","value":6,"children":{"org.eclipse.jdt.internal.compiler.classfmt.ClassFileReader:u2At()":true,"org.eclipse.jdt.internal.compiler.classfmt.AnnotationInfo:<init>()":true,"java.lang.System:arraycopy()":true},"label":"ClassFileReader:decodeAnnotations()","className":"org.eclipse.jdt.internal.compiler.classfmt.ClassFileReader","acdcCluster":"org.eclipse.jdt.internal.compiler.classfmt.ss"},{"id":"16212","name":"org.eclipse.jdt.internal.compiler.classfmt.ClassFileReader:decodeTypeAnnotations()","value":5,"children":{"org.eclipse.jdt.internal.compiler.classfmt.ClassFileReader:u2At()":true,"org.eclipse.jdt.internal.compiler.classfmt.TypeAnnotationInfo:<init>()":true,"java.lang.System:arraycopy()":true},"label":"ClassFileReader:decodeTypeAnnotations()","className":"org.eclipse.jdt.internal.compiler.classfmt.ClassFileReader","acdcCluster":"org.eclipse.jdt.internal.compiler.classfmt.ss"},{"id":"13877","name":"org.eclipse.jdt.core.compiler.CharOperation:splitOn()","value":5,"children":{"java.lang.System:arraycopy()":true},"label":"CharOperation:splitOn()","className":"org.eclipse.jdt.core.compiler.CharOperation","acdcCluster":"org.eclipse.jdt.internal.compiler.classfmt.ss"},{"id":"16259","name":"org.eclipse.jdt.internal.compiler.classfmt.ClassFormatException:<init>()","value":4,"children":{"java.lang.Exception:<init>()":true},"label":"ClassFormatException:<init>()","className":"org.eclipse.jdt.internal.compiler.classfmt.ClassFormatException","acdcCluster":"org.eclipse.jdt.internal.compiler.apt.dispatch.ss"},{"id":"16380","name":"org.eclipse.jdt.internal.compiler.classfmt.FieldInfo:initialize()","value":7,"children":{"org.eclipse.jdt.internal.compiler.classfmt.FieldInfo:getModifiers()":true,"org.eclipse.jdt.internal.compiler.classfmt.FieldInfo:getName()":true,"org.eclipse.jdt.internal.compiler.classfmt.FieldInfo:getConstant()":true,"org.eclipse.jdt.internal.compiler.classfmt.FieldInfo:getTypeName()":true,"org.eclipse.jdt.internal.compiler.classfmt.FieldInfo:getGenericSignature()":true,"org.eclipse.jdt.internal.compiler.classfmt.FieldInfo:reset()":true},"label":"FieldInfo:initialize()","className":"org.eclipse.jdt.internal.compiler.classfmt.FieldInfo","acdcCluster":"org.eclipse.jdt.internal.compiler.classfmt.ss"},{"id":"16431","name":"org.eclipse.jdt.internal.compiler.classfmt.MethodInfo:initialize()","value":8,"children":{"org.eclipse.jdt.internal.compiler.classfmt.MethodInfo:getModifiers()":true,"org.eclipse.jdt.internal.compiler.classfmt.MethodInfo:getSelector()":true,"org.eclipse.jdt.internal.compiler.classfmt.MethodInfo:getMethodDescriptor()":true,"org.eclipse.jdt.internal.compiler.classfmt.MethodInfo:getExceptionTypeNames()":true,"org.eclipse.jdt.internal.compiler.classfmt.MethodInfo:getGenericSignature()":true,"org.eclipse.jdt.internal.compiler.classfmt.MethodInfo:getArgumentNames()":true,"org.eclipse.jdt.internal.compiler.classfmt.MethodInfo:reset()":true},"label":"MethodInfo:initialize()","className":"org.eclipse.jdt.internal.compiler.classfmt.MethodInfo","acdcCluster":"org.eclipse.jdt.internal.compiler.classfmt.ss"},{"id":"16407","name":"org.eclipse.jdt.internal.compiler.classfmt.InnerClassInfo:initialize()","value":6,"children":{"org.eclipse.jdt.internal.compiler.classfmt.InnerClassInfo:getModifiers()":true,"org.eclipse.jdt.internal.compiler.classfmt.InnerClassInfo:getName()":true,"org.eclipse.jdt.internal.compiler.classfmt.InnerClassInfo:getSourceName()":true,"org.eclipse.jdt.internal.compiler.classfmt.InnerClassInfo:getEnclosingTypeName()":true,"org.eclipse.jdt.internal.compiler.classfmt.InnerClassInfo:reset()":true},"label":"InnerClassInfo:initialize()","className":"org.eclipse.jdt.internal.compiler.classfmt.InnerClassInfo","acdcCluster":"org.eclipse.jdt.internal.compiler.classfmt.ss"},{"id":"16182","name":"org.eclipse.jdt.internal.compiler.classfmt.AnnotationInfo:initialize()","value":2,"children":{"org.eclipse.jdt.internal.compiler.classfmt.AnnotationInfo:decodeAnnotation()":true},"label":"AnnotationInfo:initialize()","className":"org.eclipse.jdt.internal.compiler.classfmt.AnnotationInfo","acdcCluster":"org.eclipse.jdt.internal.compiler.classfmt.ss"},{"id":"16217","name":"org.eclipse.jdt.internal.compiler.classfmt.ClassFileReader:getEnclosingMethod()","value":12,"children":{"java.lang.StringBuffer:<init>()":true,"org.eclipse.jdt.internal.compiler.classfmt.ClassFileReader:u2At()":true,"org.eclipse.jdt.internal.compiler.classfmt.ClassFileReader:utf8At()":true,"java.lang.StringBuffer:append()":true,"java.lang.String:valueOf()":true,"java.lang.String:toCharArray()":true},"label":"ClassFileReader:getEnclosingMethod()","className":"org.eclipse.jdt.internal.compiler.classfmt.ClassFileReader","acdcCluster":"org.eclipse.jdt.internal.compiler.classfmt.ss"},{"id":"22194","name":"org.eclipse.jdt.internal.compiler.classfmt.ClassFileReader:reset()","value":1,"children":{},"label":"ClassFileReader:reset()","className":"org.eclipse.jdt.internal.compiler.classfmt.ClassFileReader","acdcCluster":"org.eclipse.jdt.internal.compiler.classfmt.ss"},{"id":"161","name":"java.lang.Object:<init>()","value":1,"children":{},"label":"Object:<init>()","className":"java.lang.Object","acdcCluster":"org.apache.el.parser.ss"},{"id":"16364","name":"org.eclipse.jdt.internal.compiler.classfmt.FieldInfo:<init>()","value":2,"children":{"org.eclipse.jdt.internal.compiler.classfmt.ClassFileStruct:<init>()":true},"label":"FieldInfo:<init>()","className":"org.eclipse.jdt.internal.compiler.classfmt.FieldInfo","acdcCluster":"org.eclipse.jdt.internal.compiler.classfmt.ss"},{"id":"22202","name":"org.eclipse.jdt.internal.compiler.classfmt.FieldInfo:u2At()","value":1,"children":{},"label":"FieldInfo:u2At()","className":"org.eclipse.jdt.internal.compiler.classfmt.FieldInfo","acdcCluster":"org.eclipse.jdt.internal.compiler.classfmt.ss"},{"id":"22203","name":"org.eclipse.jdt.internal.compiler.classfmt.FieldInfo:utf8At()","value":1,"children":{},"label":"FieldInfo:utf8At()","className":"org.eclipse.jdt.internal.compiler.classfmt.FieldInfo","acdcCluster":"org.eclipse.jdt.internal.compiler.classfmt.ss"},{"id":"16365","name":"org.eclipse.jdt.internal.compiler.classfmt.FieldInfo:decodeAnnotations()","value":4,"children":{"org.eclipse.jdt.internal.compiler.classfmt.FieldInfo:u2At()":true,"org.eclipse.jdt.internal.compiler.classfmt.AnnotationInfo:<init>()":true,"java.lang.System:arraycopy()":true},"label":"FieldInfo:decodeAnnotations()","className":"org.eclipse.jdt.internal.compiler.classfmt.FieldInfo","acdcCluster":"org.eclipse.jdt.internal.compiler.classfmt.ss"},{"id":"16366","name":"org.eclipse.jdt.internal.compiler.classfmt.FieldInfo:decodeTypeAnnotations()","value":3,"children":{"org.eclipse.jdt.internal.compiler.classfmt.FieldInfo:u2At()":true,"org.eclipse.jdt.internal.compiler.classfmt.TypeAnnotationInfo:<init>()":true},"label":"FieldInfo:decodeTypeAnnotations()","className":"org.eclipse.jdt.internal.compiler.classfmt.FieldInfo","acdcCluster":"org.eclipse.jdt.internal.compiler.classfmt.ss"},{"id":"244","name":"java.lang.System:arraycopy()","value":1,"children":{},"label":"System:arraycopy()","className":"java.lang.System","acdcCluster":"org.apache.catalina.ssi.ss"},{"id":"22204","name":"org.eclipse.jdt.internal.compiler.classfmt.FieldInfo:u4At()","value":1,"children":{},"label":"FieldInfo:u4At()","className":"org.eclipse.jdt.internal.compiler.classfmt.FieldInfo","acdcCluster":"org.eclipse.jdt.internal.compiler.classfmt.ss"},{"id":"16395","name":"org.eclipse.jdt.internal.compiler.classfmt.FieldInfoWithTypeAnnotation:<init>()","value":2,"children":{"org.eclipse.jdt.internal.compiler.classfmt.FieldInfoWithAnnotation:<init>()":true},"label":"FieldInfoWithTypeAnnotation:<init>()","className":"org.eclipse.jdt.internal.compiler.classfmt.FieldInfoWithTypeAnnotation","acdcCluster":"org.eclipse.jdt.internal.compiler.classfmt.ss"},{"id":"16389","name":"org.eclipse.jdt.internal.compiler.classfmt.FieldInfoWithAnnotation:<init>()","value":2,"children":{"org.eclipse.jdt.internal.compiler.classfmt.FieldInfo:<init>()":true},"label":"FieldInfoWithAnnotation:<init>()","className":"org.eclipse.jdt.internal.compiler.classfmt.FieldInfoWithAnnotation","acdcCluster":"org.eclipse.jdt.internal.compiler.classfmt.ss"},{"id":"16415","name":"org.eclipse.jdt.internal.compiler.classfmt.MethodInfo:<init>()","value":2,"children":{"org.eclipse.jdt.internal.compiler.classfmt.ClassFileStruct:<init>()":true},"label":"MethodInfo:<init>()","className":"org.eclipse.jdt.internal.compiler.classfmt.MethodInfo","acdcCluster":"org.eclipse.jdt.internal.compiler.classfmt.ss"},{"id":"22181","name":"org.eclipse.jdt.internal.compiler.classfmt.MethodInfo:u2At()","value":1,"children":{},"label":"MethodInfo:u2At()","className":"org.eclipse.jdt.internal.compiler.classfmt.MethodInfo","acdcCluster":"org.eclipse.jdt.internal.compiler.classfmt.ss"},{"id":"22182","name":"org.eclipse.jdt.internal.compiler.classfmt.MethodInfo:utf8At()","value":1,"children":{},"label":"MethodInfo:utf8At()","className":"org.eclipse.jdt.internal.compiler.classfmt.MethodInfo","acdcCluster":"org.eclipse.jdt.internal.compiler.classfmt.ss"},{"id":"16177","name":"org.eclipse.jdt.internal.compiler.classfmt.AnnotationInfo:<init>()","value":5,"children":{"org.eclipse.jdt.internal.compiler.classfmt.ClassFileStruct:<init>()":true,"org.eclipse.jdt.internal.compiler.classfmt.AnnotationInfo:<init>()":true,"org.eclipse.jdt.internal.compiler.classfmt.AnnotationInfo:decodeAnnotation()":true,"org.eclipse.jdt.internal.compiler.classfmt.AnnotationInfo:scanAnnotation()":true},"label":"AnnotationInfo:<init>()","className":"org.eclipse.jdt.internal.compiler.classfmt.AnnotationInfo","acdcCluster":"org.eclipse.jdt.internal.compiler.classfmt.ss"},{"id":"16179","name":"org.eclipse.jdt.internal.compiler.classfmt.AnnotationInfo:decodeDefaultValue()","value":49,"children":{"org.eclipse.jdt.internal.compiler.classfmt.AnnotationInfo:u1At()":true,"org.eclipse.jdt.internal.compiler.classfmt.AnnotationInfo:u2At()":true,"org.eclipse.jdt.internal.compiler.classfmt.AnnotationInfo:i4At()":true,"org.eclipse.jdt.internal.compiler.impl.BooleanConstant:fromValue()":true,"org.eclipse.jdt.internal.compiler.impl.IntConstant:fromValue()":true,"org.eclipse.jdt.internal.compiler.impl.CharConstant:fromValue()":true,"org.eclipse.jdt.internal.compiler.impl.ByteConstant:fromValue()":true,"org.eclipse.jdt.internal.compiler.impl.ShortConstant:fromValue()":true,"org.eclipse.jdt.internal.compiler.classfmt.AnnotationInfo:doubleAt()":true,"org.eclipse.jdt.internal.compiler.impl.DoubleConstant:fromValue()":true,"org.eclipse.jdt.internal.compiler.classfmt.AnnotationInfo:floatAt()":true,"org.eclipse.jdt.internal.compiler.impl.FloatConstant:fromValue()":true,"org.eclipse.jdt.internal.compiler.classfmt.AnnotationInfo:i8At()":true,"org.eclipse.jdt.internal.compiler.impl.LongConstant:fromValue()":true,"org.eclipse.jdt.internal.compiler.classfmt.AnnotationInfo:utf8At()":true,"java.lang.String:valueOf()":true,"org.eclipse.jdt.internal.compiler.impl.StringConstant:fromValue()":true,"org.eclipse.jdt.internal.compiler.env.EnumConstantSignature:<init>()":true,"org.eclipse.jdt.internal.compiler.env.ClassSignature:<init>()":true,"org.eclipse.jdt.internal.compiler.classfmt.AnnotationInfo:<init>()":true,"org.eclipse.jdt.internal.compiler.classfmt.AnnotationInfo:decodeDefaultValue()":true,"java.lang.StringBuilder:<init>()":true,"java.lang.StringBuilder:append()":true,"java.lang.StringBuilder:toString()":true,"java.lang.IllegalStateException:<init>()":true},"label":"AnnotationInfo:decodeDefaultValue()","className":"org.eclipse.jdt.internal.compiler.classfmt.AnnotationInfo","acdcCluster":"org.eclipse.jdt.internal.compiler.classfmt.ss"},{"id":"22183","name":"org.eclipse.jdt.internal.compiler.classfmt.AnnotationMethodInfo:decodeMethodAnnotations()","value":1,"children":{},"label":"AnnotationMethodInfo:decodeMethodAnnotations()","className":"org.eclipse.jdt.internal.compiler.classfmt.AnnotationMethodInfo","acdcCluster":"org.eclipse.jdt.internal.compiler.classfmt.ss"},{"id":"22184","name":"org.eclipse.jdt.internal.compiler.classfmt.MethodInfo:u4At()","value":1,"children":{},"label":"MethodInfo:u4At()","className":"org.eclipse.jdt.internal.compiler.classfmt.MethodInfo","acdcCluster":"org.eclipse.jdt.internal.compiler.classfmt.ss"},{"id":"16196","name":"org.eclipse.jdt.internal.compiler.classfmt.AnnotationMethodInfoWithAnnotations:<init>()","value":2,"children":{"org.eclipse.jdt.internal.compiler.classfmt.AnnotationMethodInfo:<init>()":true},"label":"AnnotationMethodInfoWithAnnotations:<init>()","className":"org.eclipse.jdt.internal.compiler.classfmt.AnnotationMethodInfoWithAnnotations","acdcCluster":"org.eclipse.jdt.internal.compiler.classfmt.ss"},{"id":"16192","name":"org.eclipse.jdt.internal.compiler.classfmt.AnnotationMethodInfo:<init>()","value":2,"children":{"org.eclipse.jdt.internal.compiler.classfmt.MethodInfo:<init>()":true},"label":"AnnotationMethodInfo:<init>()","className":"org.eclipse.jdt.internal.compiler.classfmt.AnnotationMethodInfo","acdcCluster":"org.eclipse.jdt.internal.compiler.classfmt.ss"},{"id":"16445","name":"org.eclipse.jdt.internal.compiler.classfmt.MethodInfoWithAnnotations:<init>()","value":2,"children":{"org.eclipse.jdt.internal.compiler.classfmt.MethodInfo:<init>()":true},"label":"MethodInfoWithAnnotations:<init>()","className":"org.eclipse.jdt.internal.compiler.classfmt.MethodInfoWithAnnotations","acdcCluster":"org.eclipse.jdt.internal.compiler.classfmt.ss"},{"id":"16443","name":"org.eclipse.jdt.internal.compiler.classfmt.MethodInfo:decodeMethodParameters()","value":8,"children":{"org.eclipse.jdt.internal.compiler.classfmt.MethodInfo:u1At()":true,"org.eclipse.jdt.internal.compiler.classfmt.MethodInfo:u2At()":true,"org.eclipse.jdt.internal.compiler.classfmt.MethodInfo:utf8At()":true,"java.lang.String:valueOf()":true,"java.lang.String:toCharArray()":true,"org.eclipse.jdt.core.compiler.CharOperation:concat()":true},"label":"MethodInfo:decodeMethodParameters()","className":"org.eclipse.jdt.internal.compiler.classfmt.MethodInfo","acdcCluster":"org.eclipse.jdt.internal.compiler.classfmt.ss"},{"id":"16412","name":"org.eclipse.jdt.internal.compiler.classfmt.MethodInfo:decodeMethodAnnotations()","value":3,"children":{"org.eclipse.jdt.internal.compiler.classfmt.MethodInfo:u2At()":true,"org.eclipse.jdt.internal.compiler.classfmt.MethodInfo:decodeAnnotations()":true},"label":"MethodInfo:decodeMethodAnnotations()","className":"org.eclipse.jdt.internal.compiler.classfmt.MethodInfo","acdcCluster":"org.eclipse.jdt.internal.compiler.classfmt.ss"},{"id":"16414","name":"org.eclipse.jdt.internal.compiler.classfmt.MethodInfo:decodeParamAnnotations()","value":4,"children":{"org.eclipse.jdt.internal.compiler.classfmt.MethodInfo:u1At()":true,"org.eclipse.jdt.internal.compiler.classfmt.MethodInfo:u2At()":true,"org.eclipse.jdt.internal.compiler.classfmt.MethodInfo:decodeAnnotations()":true},"label":"MethodInfo:decodeParamAnnotations()","className":"org.eclipse.jdt.internal.compiler.classfmt.MethodInfo","acdcCluster":"org.eclipse.jdt.internal.compiler.classfmt.ss"},{"id":"16413","name":"org.eclipse.jdt.internal.compiler.classfmt.MethodInfo:decodeTypeAnnotations()","value":3,"children":{"org.eclipse.jdt.internal.compiler.classfmt.MethodInfo:u2At()":true,"org.eclipse.jdt.internal.compiler.classfmt.TypeAnnotationInfo:<init>()":true},"label":"MethodInfo:decodeTypeAnnotations()","className":"org.eclipse.jdt.internal.compiler.classfmt.MethodInfo","acdcCluster":"org.eclipse.jdt.internal.compiler.classfmt.ss"},{"id":"16458","name":"org.eclipse.jdt.internal.compiler.classfmt.MethodInfoWithTypeAnnotations:<init>()","value":2,"children":{"org.eclipse.jdt.internal.compiler.classfmt.MethodInfoWithParameterAnnotations:<init>()":true},"label":"MethodInfoWithTypeAnnotations:<init>()","className":"org.eclipse.jdt.internal.compiler.classfmt.MethodInfoWithTypeAnnotations","acdcCluster":"org.eclipse.jdt.internal.compiler.classfmt.ss"},{"id":"16451","name":"org.eclipse.jdt.internal.compiler.classfmt.MethodInfoWithParameterAnnotations:<init>()","value":2,"children":{"org.eclipse.jdt.internal.compiler.classfmt.MethodInfoWithAnnotations:<init>()":true},"label":"MethodInfoWithParameterAnnotations:<init>()","className":"org.eclipse.jdt.internal.compiler.classfmt.MethodInfoWithParameterAnnotations","acdcCluster":"org.eclipse.jdt.internal.compiler.classfmt.ss"},{"id":"20374","name":"org.eclipse.jdt.internal.compiler.parser.ScannerHelper:toLowerCase()","value":2,"children":{"java.lang.Character:toLowerCase()":true},"label":"ScannerHelper:toLowerCase()","className":"org.eclipse.jdt.internal.compiler.parser.ScannerHelper","acdcCluster":"org.eclipse.jdt.internal.compiler.parser.ss"},{"id":"16479","name":"org.eclipse.jdt.internal.compiler.classfmt.TypeAnnotationInfo:<init>()","value":18,"children":{"org.eclipse.jdt.internal.compiler.classfmt.ClassFileStruct:<init>()":true,"org.eclipse.jdt.internal.compiler.classfmt.TypeAnnotationInfo:<init>()":true,"org.eclipse.jdt.internal.compiler.classfmt.TypeAnnotationInfo:u1At()":true,"org.eclipse.jdt.internal.compiler.classfmt.TypeAnnotationInfo:u2At()":true,"java.lang.StringBuilder:<init>()":true,"java.lang.StringBuilder:append()":true,"java.lang.StringBuilder:toString()":true,"java.lang.IllegalStateException:<init>()":true,"org.eclipse.jdt.internal.compiler.classfmt.AnnotationInfo:<init>()":true},"label":"TypeAnnotationInfo:<init>()","className":"org.eclipse.jdt.internal.compiler.classfmt.TypeAnnotationInfo","acdcCluster":"org.eclipse.jdt.internal.compiler.classfmt.ss"},{"id":"1314","name":"java.lang.Exception:<init>()","value":1,"children":{},"label":"Exception:<init>()","className":"java.lang.Exception","acdcCluster":"org.apache.tomcat.util.descriptor.web.ss"},{"id":"16372","name":"org.eclipse.jdt.internal.compiler.classfmt.FieldInfo:getModifiers()","value":3,"children":{"org.eclipse.jdt.internal.compiler.classfmt.FieldInfo:u2At()":true,"org.eclipse.jdt.internal.compiler.classfmt.FieldInfo:readModifierRelatedAttributes()":true},"label":"FieldInfo:getModifiers()","className":"org.eclipse.jdt.internal.compiler.classfmt.FieldInfo","acdcCluster":"org.eclipse.jdt.internal.compiler.classfmt.ss"},{"id":"16373","name":"org.eclipse.jdt.internal.compiler.classfmt.FieldInfo:getName()","value":4,"children":{"org.eclipse.jdt.internal.compiler.classfmt.FieldInfo:u2At()":true,"org.eclipse.jdt.internal.compiler.classfmt.FieldInfo:utf8At()":true},"label":"FieldInfo:getName()","className":"org.eclipse.jdt.internal.compiler.classfmt.FieldInfo","acdcCluster":"org.eclipse.jdt.internal.compiler.classfmt.ss"},{"id":"16370","name":"org.eclipse.jdt.internal.compiler.classfmt.FieldInfo:getConstant()","value":2,"children":{"org.eclipse.jdt.internal.compiler.classfmt.FieldInfo:readConstantAttribute()":true},"label":"FieldInfo:getConstant()","className":"org.eclipse.jdt.internal.compiler.classfmt.FieldInfo","acdcCluster":"org.eclipse.jdt.internal.compiler.classfmt.ss"},{"id":"16375","name":"org.eclipse.jdt.internal.compiler.classfmt.FieldInfo:getTypeName()","value":4,"children":{"org.eclipse.jdt.internal.compiler.classfmt.FieldInfo:u2At()":true,"org.eclipse.jdt.internal.compiler.classfmt.FieldInfo:utf8At()":true},"label":"FieldInfo:getTypeName()","className":"org.eclipse.jdt.internal.compiler.classfmt.FieldInfo","acdcCluster":"org.eclipse.jdt.internal.compiler.classfmt.ss"},{"id":"16371","name":"org.eclipse.jdt.internal.compiler.classfmt.FieldInfo:getGenericSignature()","value":3,"children":{"org.eclipse.jdt.internal.compiler.classfmt.FieldInfo:u2At()":true,"org.eclipse.jdt.internal.compiler.classfmt.FieldInfo:utf8At()":true},"label":"FieldInfo:getGenericSignature()","className":"org.eclipse.jdt.internal.compiler.classfmt.FieldInfo","acdcCluster":"org.eclipse.jdt.internal.compiler.classfmt.ss"},{"id":"22205","name":"org.eclipse.jdt.internal.compiler.classfmt.FieldInfo:reset()","value":1,"children":{},"label":"FieldInfo:reset()","className":"org.eclipse.jdt.internal.compiler.classfmt.FieldInfo","acdcCluster":"org.eclipse.jdt.internal.compiler.classfmt.ss"},{"id":"16425","name":"org.eclipse.jdt.internal.compiler.classfmt.MethodInfo:getModifiers()","value":3,"children":{"org.eclipse.jdt.internal.compiler.classfmt.MethodInfo:u2At()":true,"org.eclipse.jdt.internal.compiler.classfmt.MethodInfo:readModifierRelatedAttributes()":true},"label":"MethodInfo:getModifiers()","className":"org.eclipse.jdt.internal.compiler.classfmt.MethodInfo","acdcCluster":"org.eclipse.jdt.internal.compiler.classfmt.ss"},{"id":"16429","name":"org.eclipse.jdt.internal.compiler.classfmt.MethodInfo:getSelector()","value":4,"children":{"org.eclipse.jdt.internal.compiler.classfmt.MethodInfo:u2At()":true,"org.eclipse.jdt.internal.compiler.classfmt.MethodInfo:utf8At()":true},"label":"MethodInfo:getSelector()","className":"org.eclipse.jdt.internal.compiler.classfmt.MethodInfo","acdcCluster":"org.eclipse.jdt.internal.compiler.classfmt.ss"},{"id":"16424","name":"org.eclipse.jdt.internal.compiler.classfmt.MethodInfo:getMethodDescriptor()","value":4,"children":{"org.eclipse.jdt.internal.compiler.classfmt.MethodInfo:u2At()":true,"org.eclipse.jdt.internal.compiler.classfmt.MethodInfo:utf8At()":true},"label":"MethodInfo:getMethodDescriptor()","className":"org.eclipse.jdt.internal.compiler.classfmt.MethodInfo","acdcCluster":"org.eclipse.jdt.internal.compiler.classfmt.ss"},{"id":"16422","name":"org.eclipse.jdt.internal.compiler.classfmt.MethodInfo:getExceptionTypeNames()","value":2,"children":{"org.eclipse.jdt.internal.compiler.classfmt.MethodInfo:readExceptionAttributes()":true},"label":"MethodInfo:getExceptionTypeNames()","className":"org.eclipse.jdt.internal.compiler.classfmt.MethodInfo","acdcCluster":"org.eclipse.jdt.internal.compiler.classfmt.ss"},{"id":"16423","name":"org.eclipse.jdt.internal.compiler.classfmt.MethodInfo:getGenericSignature()","value":3,"children":{"org.eclipse.jdt.internal.compiler.classfmt.MethodInfo:u2At()":true,"org.eclipse.jdt.internal.compiler.classfmt.MethodInfo:utf8At()":true},"label":"MethodInfo:getGenericSignature()","className":"org.eclipse.jdt.internal.compiler.classfmt.MethodInfo","acdcCluster":"org.eclipse.jdt.internal.compiler.classfmt.ss"},{"id":"16420","name":"org.eclipse.jdt.internal.compiler.classfmt.MethodInfo:getArgumentNames()","value":2,"children":{"org.eclipse.jdt.internal.compiler.classfmt.MethodInfo:readCodeAttribute()":true},"label":"MethodInfo:getArgumentNames()","className":"org.eclipse.jdt.internal.compiler.classfmt.MethodInfo","acdcCluster":"org.eclipse.jdt.internal.compiler.classfmt.ss"},{"id":"22217","name":"org.eclipse.jdt.internal.compiler.classfmt.MethodInfo:reset()","value":1,"children":{},"label":"MethodInfo:reset()","className":"org.eclipse.jdt.internal.compiler.classfmt.MethodInfo","acdcCluster":"org.eclipse.jdt.internal.compiler.classfmt.ss"},{"id":"16403","name":"org.eclipse.jdt.internal.compiler.classfmt.InnerClassInfo:getModifiers()","value":2,"children":{"org.eclipse.jdt.internal.compiler.classfmt.InnerClassInfo:u2At()":true},"label":"InnerClassInfo:getModifiers()","className":"org.eclipse.jdt.internal.compiler.classfmt.InnerClassInfo","acdcCluster":"org.eclipse.jdt.internal.compiler.classfmt.ss"},{"id":"16404","name":"org.eclipse.jdt.internal.compiler.classfmt.InnerClassInfo:getName()","value":4,"children":{"org.eclipse.jdt.internal.compiler.classfmt.InnerClassInfo:u2At()":true,"org.eclipse.jdt.internal.compiler.classfmt.InnerClassInfo:utf8At()":true},"label":"InnerClassInfo:getName()","className":"org.eclipse.jdt.internal.compiler.classfmt.InnerClassInfo","acdcCluster":"org.eclipse.jdt.internal.compiler.classfmt.ss"},{"id":"22215","name":"org.eclipse.jdt.internal.compiler.classfmt.InnerClassInfo:reset()","value":1,"children":{},"label":"InnerClassInfo:reset()","className":"org.eclipse.jdt.internal.compiler.classfmt.InnerClassInfo","acdcCluster":"org.eclipse.jdt.internal.compiler.classfmt.ss"},{"id":"16178","name":"org.eclipse.jdt.internal.compiler.classfmt.AnnotationInfo:decodeAnnotation()","value":10,"children":{"org.eclipse.jdt.internal.compiler.classfmt.AnnotationInfo:u2At()":true,"org.eclipse.jdt.internal.compiler.classfmt.AnnotationInfo:utf8At()":true,"org.eclipse.jdt.internal.compiler.classfmt.AnnotationInfo:decodeDefaultValue()":true,"org.eclipse.jdt.internal.compiler.classfmt.ElementValuePairInfo:<init>()":true},"label":"AnnotationInfo:decodeAnnotation()","className":"org.eclipse.jdt.internal.compiler.classfmt.AnnotationInfo","acdcCluster":"org.eclipse.jdt.internal.compiler.classfmt.ss"},{"id":"2039","name":"java.lang.StringBuffer:<init>()","value":1,"children":{},"label":"StringBuffer:<init>()","className":"java.lang.StringBuffer","acdcCluster":"org.eclipse.jdt.internal.compiler.codegen.ss"},{"id":"2040","name":"java.lang.StringBuffer:append()","value":1,"children":{},"label":"StringBuffer:append()","className":"java.lang.StringBuffer","acdcCluster":"org.eclipse.jdt.internal.compiler.codegen.ss"},{"id":"3553","name":"java.lang.String:valueOf()","value":1,"children":{},"label":"String:valueOf()","className":"java.lang.String","acdcCluster":"org.apache.catalina.valves.ss"},{"id":"21653","name":"java.util.zip.ZipFile:getInputStream()","value":1,"children":{},"label":"ZipFile:getInputStream()","className":"java.util.zip.ZipFile","acdcCluster":"org.eclipse.jdt.internal.compiler.tool.ss"},{"id":"169","name":"java.lang.StringBuilder:<init>()","value":1,"children":{},"label":"StringBuilder:<init>()","className":"java.lang.StringBuilder","acdcCluster":"org.apache.tomcat.util.descriptor.web.ss"},{"id":"21646","name":"java.util.zip.ZipEntry:getName()","value":1,"children":{},"label":"ZipEntry:getName()","className":"java.util.zip.ZipEntry","acdcCluster":"org.eclipse.jdt.internal.compiler.tool.ss"},{"id":"170","name":"java.lang.StringBuilder:append()","value":1,"children":{},"label":"StringBuilder:append()","className":"java.lang.StringBuilder","acdcCluster":"org.apache.tomcat.util.descriptor.web.ss"},{"id":"171","name":"java.lang.StringBuilder:toString()","value":1,"children":{},"label":"StringBuilder:toString()","className":"java.lang.StringBuilder","acdcCluster":"org.apache.tomcat.util.descriptor.web.ss"},{"id":"1398","name":"java.io.IOException:<init>()","value":1,"children":{},"label":"IOException:<init>()","className":"java.io.IOException","acdcCluster":"org.apache.coyote.http11.ss"},{"id":"593","name":"java.io.BufferedInputStream:<init>()","value":1,"children":{},"label":"BufferedInputStream:<init>()","className":"java.io.BufferedInputStream","acdcCluster":"org.eclipse.jdt.internal.compiler.util.ss"},{"id":"22645","name":"java.util.zip.ZipEntry:getSize()","value":1,"children":{},"label":"ZipEntry:getSize()","className":"java.util.zip.ZipEntry","acdcCluster":"org.eclipse.jdt.internal.compiler.tool.ss"},{"id":"217","name":"java.io.InputStream:close()","value":1,"children":{},"label":"InputStream:close()","className":"java.io.InputStream","acdcCluster":"org.apache.jasper.xmlparser.ss"},{"id":"213","name":"java.io.FileInputStream:<init>()","value":1,"children":{},"label":"FileInputStream:<init>()","className":"java.io.FileInputStream","acdcCluster":"org.apache.catalina.ha.deploy.ss"},{"id":"1399","name":"java.io.File:length()","value":1,"children":{},"label":"File:length()","className":"java.io.File","acdcCluster":"org.apache.catalina.startup.ss"},{"id":"13002","name":"java.io.InputStream:available()","value":1,"children":{},"label":"InputStream:available()","className":"java.io.InputStream","acdcCluster":"org.apache.jasper.xmlparser.ss"},{"id":"3564","name":"java.lang.Math:max()","value":1,"children":{},"label":"Math:max()","className":"java.lang.Math","acdcCluster":"org.apache.tomcat.websocket.ss"},{"id":"553","name":"java.io.InputStream:read()","value":1,"children":{},"label":"InputStream:read()","className":"java.io.InputStream","acdcCluster":"org.apache.jasper.xmlparser.ss"},{"id":"13701","name":"org.eclipse.jdt.internal.compiler.apt.util.ArchiveFileObject:getKind()","value":5,"children":{"java.lang.String:toLowerCase()":true,"java.lang.String:endsWith()":true},"label":"ArchiveFileObject:getKind()","className":"org.eclipse.jdt.internal.compiler.apt.util.ArchiveFileObject","acdcCluster":"org.eclipse.jdt.internal.compiler.apt.dispatch.ss"},{"id":"21644","name":"java.util.zip.ZipFile:<init>()","value":1,"children":{},"label":"ZipFile:<init>()","className":"java.util.zip.ZipFile","acdcCluster":"org.eclipse.jdt.internal.compiler.tool.ss"},{"id":"21649","name":"java.util.zip.ZipFile:close()","value":1,"children":{},"label":"ZipFile:close()","className":"java.util.zip.ZipFile","acdcCluster":"org.eclipse.jdt.internal.compiler.tool.ss"},{"id":"557","name":"java.lang.Throwable:addSuppressed()","value":1,"children":{},"label":"Throwable:addSuppressed()","className":"java.lang.Throwable","acdcCluster":"org.apache.tomcat.util.net.ss"},{"id":"16210","name":"org.eclipse.jdt.internal.compiler.classfmt.ClassFileReader:accessFlags()","value":1,"children":{},"label":"ClassFileReader:accessFlags()","className":"org.eclipse.jdt.internal.compiler.classfmt.ClassFileReader","acdcCluster":"org.eclipse.jdt.internal.compiler.classfmt.ss"},{"id":"231","name":"java.lang.String:toLowerCase()","value":1,"children":{},"label":"String:toLowerCase()","className":"java.lang.String","acdcCluster":"org.apache.catalina.valves.ss"},{"id":"176","name":"java.lang.String:endsWith()","value":1,"children":{},"label":"String:endsWith()","className":"java.lang.String","acdcCluster":"org.apache.catalina.valves.ss"},{"id":"11957","name":"java.nio.charset.Charset:name()","value":1,"children":{},"label":"Charset:name()","className":"java.nio.charset.Charset","acdcCluster":"org.eclipse.jdt.internal.compiler.apt.dispatch.ss"},{"id":"13809","name":"org.eclipse.jdt.internal.compiler.apt.util.Util:getCharContents()","value":47,"children":{"java.nio.charset.Charset:forName()":true,"java.lang.StringBuilder:<init>()":true,"java.lang.StringBuilder:append()":true,"java.lang.StringBuilder:toString()":true,"java.io.PrintStream:println()":true,"java.nio.charset.Charset:newDecoder()":true,"java.nio.ByteBuffer:allocate()":true,"java.nio.ByteBuffer:put()":true,"java.nio.ByteBuffer:flip()":true,"java.nio.charset.CharsetDecoder:onMalformedInput()":true,"java.nio.charset.CharsetDecoder:onUnmappableCharacter()":true,"java.nio.charset.CharsetDecoder:decode()":true,"java.nio.CharBuffer:allocate()":true,"java.nio.charset.CharsetDecoder:replacement()":true,"java.lang.String:length()":true,"java.nio.charset.CoderResult:isMalformed()":true,"java.nio.charset.CoderResult:isUnmappable()":true,"org.eclipse.jdt.internal.compiler.apt.util.Util$EncodingErrorCollector:<init>()":true,"java.nio.CharBuffer:position()":true,"java.nio.charset.CoderResult:length()":true,"org.eclipse.jdt.internal.compiler.apt.util.Util:reportEncodingError()":true,"java.nio.CharBuffer:capacity()":true,"java.nio.CharBuffer:flip()":true,"java.nio.CharBuffer:put()":true,"java.nio.CharBuffer:append()":true,"java.nio.ByteBuffer:position()":true,"java.nio.charset.CoderResult:isOverflow()":true,"java.nio.CharBuffer:toString()":true,"org.eclipse.jdt.internal.compiler.apt.util.Util$EncodingErrorCollector:reportAllEncodingErrors()":true},"label":"Util:getCharContents()","className":"org.eclipse.jdt.internal.compiler.apt.util.Util","acdcCluster":"org.eclipse.jdt.internal.compiler.apt.util.ss"},{"id":"21528","name":"java.nio.charset.Charset:forName()","value":1,"children":{},"label":"Charset:forName()","className":"java.nio.charset.Charset","acdcCluster":"org.eclipse.jdt.internal.compiler.apt.dispatch.ss"},{"id":"587","name":"java.io.PrintStream:println()","value":1,"children":{},"label":"PrintStream:println()","className":"java.io.PrintStream","acdcCluster":"org.eclipse.jdt.internal.compiler.tool.ss"},{"id":"21665","name":"java.nio.charset.Charset:newDecoder()","value":1,"children":{},"label":"Charset:newDecoder()","className":"java.nio.charset.Charset","acdcCluster":"org.eclipse.jdt.internal.compiler.apt.dispatch.ss"},{"id":"3789","name":"java.nio.ByteBuffer:allocate()","value":1,"children":{},"label":"ByteBuffer:allocate()","className":"java.nio.ByteBuffer","acdcCluster":"org.apache.tomcat.util.net.ss"},{"id":"3848","name":"java.nio.ByteBuffer:put()","value":1,"children":{},"label":"ByteBuffer:put()","className":"java.nio.ByteBuffer","acdcCluster":"org.apache.tomcat.util.net.ss"},{"id":"3793","name":"java.nio.ByteBuffer:flip()","value":1,"children":{},"label":"ByteBuffer:flip()","className":"java.nio.ByteBuffer","acdcCluster":"org.apache.tomcat.util.net.ss"},{"id":"21666","name":"java.nio.charset.CharsetDecoder:onMalformedInput()","value":1,"children":{},"label":"CharsetDecoder:onMalformedInput()","className":"java.nio.charset.CharsetDecoder","acdcCluster":"org.apache.tomcat.websocket.ss"},{"id":"21667","name":"java.nio.charset.CharsetDecoder:onUnmappableCharacter()","value":1,"children":{},"label":"CharsetDecoder:onUnmappableCharacter()","className":"java.nio.charset.CharsetDecoder","acdcCluster":"org.apache.tomcat.websocket.ss"},{"id":"21668","name":"java.nio.charset.CharsetDecoder:decode()","value":1,"children":{},"label":"CharsetDecoder:decode()","className":"java.nio.charset.CharsetDecoder","acdcCluster":"org.apache.tomcat.websocket.ss"},{"id":"21670","name":"java.nio.CharBuffer:allocate()","value":1,"children":{},"label":"CharBuffer:allocate()","className":"java.nio.CharBuffer","acdcCluster":"org.apache.tomcat.websocket.ss"},{"id":"21671","name":"java.nio.charset.CharsetDecoder:replacement()","value":1,"children":{},"label":"CharsetDecoder:replacement()","className":"java.nio.charset.CharsetDecoder","acdcCluster":"org.apache.tomcat.websocket.ss"},{"id":"177","name":"java.lang.String:length()","value":1,"children":{},"label":"String:length()","className":"java.lang.String","acdcCluster":"org.apache.catalina.valves.ss"},{"id":"21672","name":"java.nio.charset.CoderResult:isMalformed()","value":1,"children":{},"label":"CoderResult:isMalformed()","className":"java.nio.charset.CoderResult","acdcCluster":"org.apache.tomcat.websocket.ss"},{"id":"21673","name":"java.nio.charset.CoderResult:isUnmappable()","value":1,"children":{},"label":"CoderResult:isUnmappable()","className":"java.nio.charset.CoderResult","acdcCluster":"org.apache.tomcat.websocket.ss"},{"id":"13802","name":"org.eclipse.jdt.internal.compiler.apt.util.Util$EncodingErrorCollector:<init>()","value":3,"children":{"java.lang.Object:<init>()":true,"java.util.ArrayList:<init>()":true},"label":"Util$EncodingErrorCollector:<init>()","className":"org.eclipse.jdt.internal.compiler.apt.util.Util$EncodingErrorCollector","acdcCluster":"org.eclipse.jdt.internal.compiler.apt.util.ss"},{"id":"21674","name":"java.nio.CharBuffer:position()","value":1,"children":{},"label":"CharBuffer:position()","className":"java.nio.CharBuffer","acdcCluster":"org.apache.tomcat.websocket.ss"},{"id":"21675","name":"java.nio.charset.CoderResult:length()","value":1,"children":{},"label":"CoderResult:length()","className":"java.nio.charset.CoderResult","acdcCluster":"org.apache.tomcat.websocket.ss"},{"id":"13810","name":"org.eclipse.jdt.internal.compiler.apt.util.Util:reportEncodingError()","value":2,"children":{"org.eclipse.jdt.internal.compiler.apt.util.Util$EncodingErrorCollector:collect()":true},"label":"Util:reportEncodingError()","className":"org.eclipse.jdt.internal.compiler.apt.util.Util","acdcCluster":"org.eclipse.jdt.internal.compiler.apt.util.ss"},{"id":"21676","name":"java.nio.CharBuffer:capacity()","value":1,"children":{},"label":"CharBuffer:capacity()","className":"java.nio.CharBuffer","acdcCluster":"org.apache.tomcat.websocket.ss"},{"id":"21677","name":"java.nio.CharBuffer:flip()","value":1,"children":{},"label":"CharBuffer:flip()","className":"java.nio.CharBuffer","acdcCluster":"org.apache.tomcat.websocket.ss"},{"id":"21678","name":"java.nio.CharBuffer:put()","value":1,"children":{},"label":"CharBuffer:put()","className":"java.nio.CharBuffer","acdcCluster":"org.apache.tomcat.websocket.ss"},{"id":"21679","name":"java.nio.CharBuffer:append()","value":1,"children":{},"label":"CharBuffer:append()","className":"java.nio.CharBuffer","acdcCluster":"org.apache.tomcat.websocket.ss"},{"id":"3798","name":"java.nio.ByteBuffer:position()","value":1,"children":{},"label":"ByteBuffer:position()","className":"java.nio.ByteBuffer","acdcCluster":"org.apache.tomcat.util.net.ss"},{"id":"21680","name":"java.nio.charset.CoderResult:isOverflow()","value":1,"children":{},"label":"CoderResult:isOverflow()","className":"java.nio.charset.CoderResult","acdcCluster":"org.apache.tomcat.websocket.ss"},{"id":"21681","name":"java.nio.CharBuffer:toString()","value":1,"children":{},"label":"CharBuffer:toString()","className":"java.nio.CharBuffer","acdcCluster":"org.apache.tomcat.websocket.ss"},{"id":"13804","name":"org.eclipse.jdt.internal.compiler.apt.util.Util$EncodingErrorCollector:reportAllEncodingErrors()","value":14,"children":{"java.lang.String:toCharArray()":true,"java.util.ArrayList:iterator()":true,"java.util.Iterator:next()":true,"javax.tools.FileObject:getName()":true,"java.lang.String:valueOf()":true,"java.lang.StringBuilder:<init>()":true,"java.lang.StringBuilder:append()":true,"java.lang.StringBuilder:toString()":true,"java.io.PrintStream:println()":true,"org.eclipse.jdt.internal.compiler.apt.util.Util$EncodingError:getSource()":true,"java.util.Iterator:hasNext()":true},"label":"Util$EncodingErrorCollector:reportAllEncodingErrors()","className":"org.eclipse.jdt.internal.compiler.apt.util.Util$EncodingErrorCollector","acdcCluster":"org.eclipse.jdt.internal.compiler.apt.util.ss"},{"id":"173","name":"java.util.ArrayList:<init>()","value":1,"children":{},"label":"ArrayList:<init>()","className":"java.util.ArrayList","acdcCluster":"org.apache.el.parser.ss"},{"id":"13803","name":"org.eclipse.jdt.internal.compiler.apt.util.Util$EncodingErrorCollector:collect()","value":3,"children":{"org.eclipse.jdt.internal.compiler.apt.util.Util$EncodingError:<init>()":true,"java.util.ArrayList:add()":true},"label":"Util$EncodingErrorCollector:collect()","className":"org.eclipse.jdt.internal.compiler.apt.util.Util$EncodingErrorCollector","acdcCluster":"org.eclipse.jdt.internal.compiler.apt.util.ss"},{"id":"1489","name":"java.util.ArrayList:iterator()","value":1,"children":{},"label":"ArrayList:iterator()","className":"java.util.ArrayList","acdcCluster":"org.apache.el.parser.ss"},{"id":"238","name":"java.util.Iterator:next()","value":1,"children":{},"label":"Iterator:next()","className":"java.util.Iterator","acdcCluster":"org.apache.el.stream.ss"},{"id":"21664","name":"javax.tools.FileObject:getName()","value":1,"children":{},"label":"FileObject:getName()","className":"javax.tools.FileObject","acdcCluster":"org.eclipse.jdt.internal.compiler.apt.dispatch.ss"},{"id":"13800","name":"org.eclipse.jdt.internal.compiler.apt.util.Util$EncodingError:getSource()","value":9,"children":{"java.lang.StringBuffer:<init>()":true,"java.lang.StringBuffer:append()":true,"java.lang.StringBuffer:toString()":true},"label":"Util$EncodingError:getSource()","className":"org.eclipse.jdt.internal.compiler.apt.util.Util$EncodingError","acdcCluster":"org.eclipse.jdt.internal.compiler.apt.util.ss"},{"id":"237","name":"java.util.Iterator:hasNext()","value":1,"children":{},"label":"Iterator:hasNext()","className":"java.util.Iterator","acdcCluster":"org.apache.el.stream.ss"},{"id":"21669","name":"java.nio.CharBuffer:array()","value":1,"children":{},"label":"CharBuffer:array()","className":"java.nio.CharBuffer","acdcCluster":"org.apache.tomcat.websocket.ss"},{"id":"2041","name":"java.lang.StringBuffer:toString()","value":1,"children":{},"label":"StringBuffer:toString()","className":"java.lang.StringBuffer","acdcCluster":"org.eclipse.jdt.internal.compiler.codegen.ss"},{"id":"21075","name":"org.eclipse.jdt.internal.compiler.tool.ArchiveFileObject:getKind()","value":5,"children":{"java.lang.String:toLowerCase()":true,"java.lang.String:endsWith()":true},"label":"ArchiveFileObject:getKind()","className":"org.eclipse.jdt.internal.compiler.tool.ArchiveFileObject","acdcCluster":"org.eclipse.jdt.internal.compiler.tool.ss"},{"id":"21252","name":"org.eclipse.jdt.internal.compiler.tool.Util:getCharContents()","value":47,"children":{"java.nio.charset.Charset:forName()":true,"java.lang.StringBuilder:<init>()":true,"java.lang.StringBuilder:append()":true,"java.lang.StringBuilder:toString()":true,"java.io.PrintStream:println()":true,"java.nio.charset.Charset:newDecoder()":true,"java.nio.ByteBuffer:allocate()":true,"java.nio.ByteBuffer:put()":true,"java.nio.ByteBuffer:flip()":true,"java.nio.charset.CharsetDecoder:onMalformedInput()":true,"java.nio.charset.CharsetDecoder:onUnmappableCharacter()":true,"java.nio.charset.CharsetDecoder:decode()":true,"java.nio.CharBuffer:allocate()":true,"java.nio.charset.CharsetDecoder:replacement()":true,"java.lang.String:length()":true,"java.nio.charset.CoderResult:isMalformed()":true,"java.nio.charset.CoderResult:isUnmappable()":true,"org.eclipse.jdt.internal.compiler.tool.Util$EncodingErrorCollector:<init>()":true,"java.nio.CharBuffer:position()":true,"java.nio.charset.CoderResult:length()":true,"org.eclipse.jdt.internal.compiler.tool.Util:reportEncodingError()":true,"java.nio.CharBuffer:capacity()":true,"java.nio.CharBuffer:flip()":true,"java.nio.CharBuffer:put()":true,"java.nio.CharBuffer:append()":true,"java.nio.ByteBuffer:position()":true,"java.nio.charset.CoderResult:isOverflow()":true,"java.nio.CharBuffer:toString()":true,"org.eclipse.jdt.internal.compiler.tool.Util$EncodingErrorCollector:reportAllEncodingErrors()":true},"label":"Util:getCharContents()","className":"org.eclipse.jdt.internal.compiler.tool.Util","acdcCluster":"org.eclipse.jdt.internal.compiler.tool.ss"},{"id":"21245","name":"org.eclipse.jdt.internal.compiler.tool.Util$EncodingErrorCollector:<init>()","value":3,"children":{"java.lang.Object:<init>()":true,"java.util.ArrayList:<init>()":true},"label":"Util$EncodingErrorCollector:<init>()","className":"org.eclipse.jdt.internal.compiler.tool.Util$EncodingErrorCollector","acdcCluster":"org.eclipse.jdt.internal.compiler.tool.ss"},{"id":"21253","name":"org.eclipse.jdt.internal.compiler.tool.Util:reportEncodingError()","value":2,"children":{"org.eclipse.jdt.internal.compiler.tool.Util$EncodingErrorCollector:collect()":true},"label":"Util:reportEncodingError()","className":"org.eclipse.jdt.internal.compiler.tool.Util","acdcCluster":"org.eclipse.jdt.internal.compiler.tool.ss"},{"id":"21247","name":"org.eclipse.jdt.internal.compiler.tool.Util$EncodingErrorCollector:reportAllEncodingErrors()","value":14,"children":{"java.lang.String:toCharArray()":true,"java.util.ArrayList:iterator()":true,"java.util.Iterator:next()":true,"javax.tools.FileObject:getName()":true,"java.lang.String:valueOf()":true,"java.lang.StringBuilder:<init>()":true,"java.lang.StringBuilder:append()":true,"java.lang.StringBuilder:toString()":true,"java.io.PrintStream:println()":true,"org.eclipse.jdt.internal.compiler.tool.Util$EncodingError:getSource()":true,"java.util.Iterator:hasNext()":true},"label":"Util$EncodingErrorCollector:reportAllEncodingErrors()","className":"org.eclipse.jdt.internal.compiler.tool.Util$EncodingErrorCollector","acdcCluster":"org.eclipse.jdt.internal.compiler.tool.ss"},{"id":"21246","name":"org.eclipse.jdt.internal.compiler.tool.Util$EncodingErrorCollector:collect()","value":3,"children":{"org.eclipse.jdt.internal.compiler.tool.Util$EncodingError:<init>()":true,"java.util.ArrayList:add()":true},"label":"Util$EncodingErrorCollector:collect()","className":"org.eclipse.jdt.internal.compiler.tool.Util$EncodingErrorCollector","acdcCluster":"org.eclipse.jdt.internal.compiler.tool.ss"},{"id":"21243","name":"org.eclipse.jdt.internal.compiler.tool.Util$EncodingError:getSource()","value":9,"children":{"java.lang.StringBuffer:<init>()":true,"java.lang.StringBuffer:append()":true,"java.lang.StringBuffer:toString()":true},"label":"Util$EncodingError:getSource()","className":"org.eclipse.jdt.internal.compiler.tool.Util$EncodingError","acdcCluster":"org.eclipse.jdt.internal.compiler.tool.ss"}],"edges":[{"source":"21222","target":"16205"},{"source":"21222","target":"16240"},{"source":"21222","target":"16242"},{"source":"21222","target":"16243"},{"source":"16205","target":"16205"},{"source":"16205","target":"21476"},{"source":"16205","target":"21469"},{"source":"16205","target":"21472"},{"source":"16240","target":"16405"},{"source":"16242","target":"16402"},{"source":"16242","target":"16405"},{"source":"16243","target":"16402"},{"source":"16243","target":"16405"},{"source":"21476","target":"21472"},{"source":"21469","target":"21472"},{"source":"16402","target":"22213"},{"source":"16402","target":"22214"},{"source":"16405","target":"22213"},{"source":"16405","target":"22214"},{"source":"21235","target":"21538"},{"source":"21235","target":"21536"},{"source":"21222","target":"21235"},{"source":"21222","target":"21536"},{"source":"16205","target":"232"},{"source":"16205","target":"11236"},{"source":"16205","target":"16206"},{"source":"16205","target":"16239"},{"source":"16205","target":"21647"},{"source":"16205","target":"206"},{"source":"16206","target":"16206"},{"source":"16206","target":"16248"},{"source":"16206","target":"22189"},{"source":"16206","target":"22190"},{"source":"16206","target":"16215"},{"source":"16206","target":"16363"},{"source":"16206","target":"16384"},{"source":"16206","target":"16191"},{"source":"16206","target":"16410"},{"source":"16206","target":"16437"},{"source":"16206","target":"22191"},{"source":"16206","target":"22192"},{"source":"16206","target":"13861"},{"source":"16206","target":"16401"},{"source":"16206","target":"16402"},{"source":"16206","target":"16211"},{"source":"16206","target":"16212"},{"source":"16206","target":"13877"},{"source":"16206","target":"16239"},{"source":"16206","target":"16259"},{"source":"16239","target":"16380"},{"source":"16239","target":"16431"},{"source":"16239","target":"16407"},{"source":"16239","target":"16182"},{"source":"16239","target":"16217"},{"source":"16239","target":"22194"},{"source":"16239","target":"16259"},{"source":"16248","target":"161"},{"source":"16215","target":"22189"},{"source":"16215","target":"22191"},{"source":"16363","target":"16364"},{"source":"16363","target":"22202"},{"source":"16363","target":"22203"},{"source":"16363","target":"13861"},{"source":"16363","target":"16365"},{"source":"16363","target":"16366"},{"source":"16363","target":"244"},{"source":"16363","target":"22204"},{"source":"16363","target":"16395"},{"source":"16363","target":"16389"},{"source":"16191","target":"16415"},{"source":"16191","target":"22181"},{"source":"16191","target":"22182"},{"source":"16191","target":"13861"},{"source":"16191","target":"16177"},{"source":"16191","target":"16179"},{"source":"16191","target":"22183"},{"source":"16191","target":"244"},{"source":"16191","target":"22184"},{"source":"16191","target":"16196"},{"source":"16191","target":"16192"},{"source":"16191","target":"16445"},{"source":"16410","target":"16415"},{"source":"16410","target":"22181"},{"source":"16410","target":"22182"},{"source":"16410","target":"13861"},{"source":"16410","target":"16443"},{"source":"16410","target":"16412"},{"source":"16410","target":"16414"},{"source":"16410","target":"16413"},{"source":"16410","target":"244"},{"source":"16410","target":"22184"},{"source":"16410","target":"16458"},{"source":"16410","target":"16451"},{"source":"16410","target":"16445"},{"source":"13861","target":"13861"},{"source":"13861","target":"20374"},{"source":"16401","target":"16248"},{"source":"16401","target":"22213"},{"source":"16211","target":"22189"},{"source":"16211","target":"16177"},{"source":"16211","target":"244"},{"source":"16212","target":"22189"},{"source":"16212","target":"16479"},{"source":"16212","target":"244"},{"source":"13877","target":"244"},{"source":"16259","target":"1314"},{"source":"16380","target":"16372"},{"source":"16380","target":"16373"},{"source":"16380","target":"16370"},{"source":"16380","target":"16375"},{"source":"16380","target":"16371"},{"source":"16380","target":"22205"},{"source":"16431","target":"16425"},{"source":"16431","target":"16429"},{"source":"16431","target":"16424"},{"source":"16431","target":"16422"},{"source":"16431","target":"16423"},{"source":"16431","target":"16420"},{"source":"16431","target":"22217"},{"source":"16407","target":"16403"},{"source":"16407","target":"16404"},{"source":"16407","target":"16405"},{"source":"16407","target":"16402"},{"source":"16407","target":"22215"},{"source":"16182","target":"16178"},{"source":"16217","target":"2039"},{"source":"16217","target":"22189"},{"source":"16217","target":"22191"},{"source":"16217","target":"2040"},{"source":"16217","target":"3553"},{"source":"16217","target":"11236"},{"source":"21476","target":"21653"},{"source":"21476","target":"169"},{"source":"21476","target":"21646"},{"source":"21476","target":"170"},{"source":"21476","target":"171"},{"source":"21476","target":"1398"},{"source":"21476","target":"593"},{"source":"21476","target":"22645"},{"source":"21476","target":"217"},{"source":"21469","target":"213"},{"source":"21469","target":"593"},{"source":"21469","target":"1399"},{"source":"21469","target":"217"},{"source":"21472","target":"13002"},{"source":"21472","target":"3564"},{"source":"21472","target":"244"},{"source":"21472","target":"553"},{"source":"13700","target":"13701"},{"source":"13700","target":"21644"},{"source":"13700","target":"16205"},{"source":"13700","target":"21649"},{"source":"13700","target":"557"},{"source":"13700","target":"16210"},{"source":"13701","target":"231"},{"source":"13701","target":"176"},{"source":"13707","target":"13701"},{"source":"13707","target":"21644"},{"source":"13707","target":"21647"},{"source":"13707","target":"21476"},{"source":"13707","target":"11957"},{"source":"13707","target":"13809"},{"source":"13707","target":"21649"},{"source":"13707","target":"557"},{"source":"13809","target":"21528"},{"source":"13809","target":"169"},{"source":"13809","target":"170"},{"source":"13809","target":"171"},{"source":"13809","target":"587"},{"source":"13809","target":"21665"},{"source":"13809","target":"3789"},{"source":"13809","target":"3848"},{"source":"13809","target":"3793"},{"source":"13809","target":"21666"},{"source":"13809","target":"21667"},{"source":"13809","target":"21668"},{"source":"13809","target":"21670"},{"source":"13809","target":"21671"},{"source":"13809","target":"177"},{"source":"13809","target":"21672"},{"source":"13809","target":"21673"},{"source":"13809","target":"13802"},{"source":"13809","target":"21674"},{"source":"13809","target":"21675"},{"source":"13809","target":"13810"},{"source":"13809","target":"21676"},{"source":"13809","target":"21677"},{"source":"13809","target":"21678"},{"source":"13809","target":"21679"},{"source":"13809","target":"3798"},{"source":"13809","target":"21680"},{"source":"13809","target":"21681"},{"source":"13809","target":"13804"},{"source":"13802","target":"161"},{"source":"13802","target":"173"},{"source":"13810","target":"13803"},{"source":"13804","target":"11236"},{"source":"13804","target":"1489"},{"source":"13804","target":"238"},{"source":"13804","target":"21664"},{"source":"13804","target":"3553"},{"source":"13804","target":"169"},{"source":"13804","target":"170"},{"source":"13804","target":"171"},{"source":"13804","target":"587"},{"source":"13804","target":"13800"},{"source":"13804","target":"237"},{"source":"13762","target":"21469"},{"source":"13762","target":"11957"},{"source":"13762","target":"13809"},{"source":"13808","target":"21528"},{"source":"13808","target":"169"},{"source":"13808","target":"170"},{"source":"13808","target":"171"},{"source":"13808","target":"587"},{"source":"13808","target":"21665"},{"source":"13808","target":"21666"},{"source":"13808","target":"21667"},{"source":"13808","target":"21472"},{"source":"13808","target":"3789"},{"source":"13808","target":"3848"},{"source":"13808","target":"3793"},{"source":"13808","target":"21668"},{"source":"13808","target":"21669"},{"source":"16406","target":"2039"},{"source":"16406","target":"16404"},{"source":"16406","target":"2040"},{"source":"16406","target":"16402"},{"source":"16406","target":"16405"},{"source":"16406","target":"2041"},{"source":"21081","target":"21075"},{"source":"21081","target":"21644"},{"source":"21081","target":"21647"},{"source":"21081","target":"21476"},{"source":"21081","target":"11957"},{"source":"21081","target":"21252"},{"source":"21081","target":"21649"},{"source":"21081","target":"557"},{"source":"21075","target":"231"},{"source":"21075","target":"176"},{"source":"21252","target":"21528"},{"source":"21252","target":"169"},{"source":"21252","target":"170"},{"source":"21252","target":"171"},{"source":"21252","target":"587"},{"source":"21252","target":"21665"},{"source":"21252","target":"3789"},{"source":"21252","target":"3848"},{"source":"21252","target":"3793"},{"source":"21252","target":"21666"},{"source":"21252","target":"21667"},{"source":"21252","target":"21668"},{"source":"21252","target":"21670"},{"source":"21252","target":"21671"},{"source":"21252","target":"177"},{"source":"21252","target":"21672"},{"source":"21252","target":"21673"},{"source":"21252","target":"21245"},{"source":"21252","target":"21674"},{"source":"21252","target":"21675"},{"source":"21252","target":"21253"},{"source":"21252","target":"21676"},{"source":"21252","target":"21677"},{"source":"21252","target":"21678"},{"source":"21252","target":"21679"},{"source":"21252","target":"3798"},{"source":"21252","target":"21680"},{"source":"21252","target":"21681"},{"source":"21252","target":"21247"},{"source":"21245","target":"161"},{"source":"21245","target":"173"},{"source":"21253","target":"21246"},{"source":"21247","target":"11236"},{"source":"21247","target":"1489"},{"source":"21247","target":"238"},{"source":"21247","target":"21664"},{"source":"21247","target":"3553"},{"source":"21247","target":"169"},{"source":"21247","target":"170"},{"source":"21247","target":"171"},{"source":"21247","target":"587"},{"source":"21247","target":"21243"},{"source":"21247","target":"237"},{"source":"21225","target":"21469"},{"source":"21225","target":"11957"},{"source":"21225","target":"21252"},{"source":"21251","target":"21528"},{"source":"21251","target":"169"},{"source":"21251","target":"170"},{"source":"21251","target":"171"},{"source":"21251","target":"587"},{"source":"21251","target":"21665"},{"source":"21251","target":"21666"},{"source":"21251","target":"21667"},{"source":"21251","target":"21472"},{"source":"21251","target":"3789"},{"source":"21251","target":"3848"},{"source":"21251","target":"3793"},{"source":"21251","target":"21668"},{"source":"21251","target":"21669"}],"groups":[{"id":"cluster","title":"org.eclipse.jdt.internal.compiler.tool.EclipseFileObject.ss3"}]}
