{"relatedACDCClusters":{"org.eclipse.jdt.internal.compiler.classfmt.ss":{"id":"a8f835c2-1721-11ea-8ada-add5f6e8eea0","cluster":"org.eclipse.jdt.internal.compiler.classfmt.ss","elements":["org.eclipse.jdt.internal.compiler.classfmt.AnnotationMethodInfo","org.eclipse.jdt.internal.compiler.classfmt.AnnotationMethodInfoWithAnnotations","org.eclipse.jdt.internal.compiler.classfmt.NonNullDefaultAwareTypeAnnotationWalker","org.eclipse.jdt.internal.compiler.classfmt.NonNullDefaultAwareTypeAnnotationWalker$1","org.eclipse.jdt.internal.compiler.classfmt.MethodInfoWithTypeAnnotations","org.eclipse.jdt.internal.compiler.classfmt.MethodInfo","org.eclipse.jdt.internal.compiler.classfmt.MethodInfoWithParameterAnnotations","org.eclipse.jdt.internal.compiler.classfmt.AnnotationInfo","org.eclipse.jdt.internal.compiler.classfmt.ClassFileStruct","org.eclipse.jdt.internal.compiler.classfmt.MethodInfoWithAnnotations","org.eclipse.jdt.internal.compiler.classfmt.TypeAnnotationInfo","org.eclipse.jdt.internal.compiler.classfmt.ExternalAnnotationProvider$DispatchingAnnotationWalker","org.eclipse.jdt.internal.compiler.classfmt.ExternalAnnotationProvider","org.eclipse.jdt.internal.compiler.classfmt.ExternalAnnotationProvider$2","org.eclipse.jdt.internal.compiler.classfmt.ExternalAnnotationProvider$FieldAnnotationWalker","org.eclipse.jdt.internal.compiler.classfmt.ExternalAnnotationProvider$SuperTypesAnnotationWalker","org.eclipse.jdt.internal.compiler.classfmt.ExternalAnnotationProvider$TypeParametersAnnotationWalker","org.eclipse.jdt.internal.compiler.classfmt.ExternalAnnotationProvider$SingleMarkerAnnotation","org.eclipse.jdt.internal.compiler.classfmt.ExternalAnnotationProvider$BasicAnnotationWalker","org.eclipse.jdt.internal.compiler.classfmt.ExternalAnnotationProvider$MethodAnnotationWalker","org.eclipse.jdt.internal.compiler.classfmt.ExternalAnnotationProvider$1","java.lang.UnsupportedOperationException","org.eclipse.jdt.core.compiler.CharOperation","java.io.LineNumberReader","org.eclipse.jdt.internal.compiler.env.IBinaryAnnotation","org.eclipse.jdt.internal.compiler.classfmt.ElementValuePairInfo","org.eclipse.jdt.internal.compiler.env.IBinaryElementValuePair","org.eclipse.jdt.internal.compiler.classfmt.ExternalAnnotationProvider$IMethodAnnotationWalker","org.eclipse.jdt.internal.compiler.lookup.SignatureWrapper","org.eclipse.jdt.internal.compiler.util.HashtableOfIntValues","org.eclipse.jdt.internal.compiler.classfmt.FieldInfoWithAnnotation","org.eclipse.jdt.internal.compiler.classfmt.FieldInfo","org.eclipse.jdt.internal.compiler.classfmt.FieldInfoWithTypeAnnotation","org.eclipse.jdt.internal.compiler.classfmt.ClassFileReader","org.eclipse.jdt.internal.compiler.classfmt.InnerClassInfo","org.eclipse.jdt.internal.compiler.env.IBinaryNestedType","org.eclipse.jdt.internal.compiler.classfmt.ClassFileReader$ZipFileProducer"]}},"nodes":[{"id":"16212","name":"org.eclipse.jdt.internal.compiler.classfmt.ClassFileReader:decodeTypeAnnotations()","value":5,"children":{"org.eclipse.jdt.internal.compiler.classfmt.ClassFileReader:u2At()":true,"org.eclipse.jdt.internal.compiler.classfmt.TypeAnnotationInfo:<init>()":true,"java.lang.System:arraycopy()":true},"label":"ClassFileReader:decodeTypeAnnotations()","className":"org.eclipse.jdt.internal.compiler.classfmt.ClassFileReader","acdcCluster":"org.eclipse.jdt.internal.compiler.classfmt.ss","groupId":"cluster"},{"id":"16415","name":"org.eclipse.jdt.internal.compiler.classfmt.MethodInfo:<init>()","value":2,"children":{"org.eclipse.jdt.internal.compiler.classfmt.ClassFileStruct:<init>()":true},"label":"MethodInfo:<init>()","className":"org.eclipse.jdt.internal.compiler.classfmt.MethodInfo","acdcCluster":"org.eclipse.jdt.internal.compiler.classfmt.ss","groupId":"cluster"},{"id":"16445","name":"org.eclipse.jdt.internal.compiler.classfmt.MethodInfoWithAnnotations:<init>()","value":2,"children":{"org.eclipse.jdt.internal.compiler.classfmt.MethodInfo:<init>()":true},"label":"MethodInfoWithAnnotations:<init>()","className":"org.eclipse.jdt.internal.compiler.classfmt.MethodInfoWithAnnotations","acdcCluster":"org.eclipse.jdt.internal.compiler.classfmt.ss","groupId":"cluster"},{"id":"16437","name":"org.eclipse.jdt.internal.compiler.classfmt.MethodInfo:sizeInBytes()","value":1,"children":{},"label":"MethodInfo:sizeInBytes()","className":"org.eclipse.jdt.internal.compiler.classfmt.MethodInfo","acdcCluster":"org.eclipse.jdt.internal.compiler.classfmt.ss","groupId":"cluster"},{"id":"22192","name":"org.eclipse.jdt.internal.compiler.classfmt.ClassFileReader:u4At()","value":1,"children":{},"label":"ClassFileReader:u4At()","className":"org.eclipse.jdt.internal.compiler.classfmt.ClassFileReader","acdcCluster":"org.eclipse.jdt.internal.compiler.classfmt.ss","groupId":"cluster"},{"id":"16215","name":"org.eclipse.jdt.internal.compiler.classfmt.ClassFileReader:getConstantClassNameAt()","value":4,"children":{"org.eclipse.jdt.internal.compiler.classfmt.ClassFileReader:u2At()":true,"org.eclipse.jdt.internal.compiler.classfmt.ClassFileReader:utf8At()":true},"label":"ClassFileReader:getConstantClassNameAt()","className":"org.eclipse.jdt.internal.compiler.classfmt.ClassFileReader","acdcCluster":"org.eclipse.jdt.internal.compiler.classfmt.ss","groupId":"cluster"},{"id":"16384","name":"org.eclipse.jdt.internal.compiler.classfmt.FieldInfo:sizeInBytes()","value":1,"children":{},"label":"FieldInfo:sizeInBytes()","className":"org.eclipse.jdt.internal.compiler.classfmt.FieldInfo","acdcCluster":"org.eclipse.jdt.internal.compiler.classfmt.ss","groupId":"cluster"},{"id":"22190","name":"org.eclipse.jdt.internal.compiler.classfmt.ClassFileReader:u1At()","value":1,"children":{},"label":"ClassFileReader:u1At()","className":"org.eclipse.jdt.internal.compiler.classfmt.ClassFileReader","acdcCluster":"org.eclipse.jdt.internal.compiler.classfmt.ss","groupId":"cluster"},{"id":"16401","name":"org.eclipse.jdt.internal.compiler.classfmt.InnerClassInfo:<init>()","value":5,"children":{"org.eclipse.jdt.internal.compiler.classfmt.ClassFileStruct:<init>()":true,"org.eclipse.jdt.internal.compiler.classfmt.InnerClassInfo:u2At()":true},"label":"InnerClassInfo:<init>()","className":"org.eclipse.jdt.internal.compiler.classfmt.InnerClassInfo","acdcCluster":"org.eclipse.jdt.internal.compiler.classfmt.ss","groupId":"cluster"},{"id":"16206","name":"org.eclipse.jdt.internal.compiler.classfmt.ClassFileReader:<init>()","value":67,"children":{"org.eclipse.jdt.internal.compiler.classfmt.ClassFileReader:<init>()":true,"org.eclipse.jdt.internal.compiler.classfmt.ClassFileStruct:<init>()":true,"org.eclipse.jdt.internal.compiler.classfmt.ClassFileReader:u2At()":true,"org.eclipse.jdt.internal.compiler.classfmt.ClassFileReader:u1At()":true,"org.eclipse.jdt.internal.compiler.classfmt.ClassFileReader:getConstantClassNameAt()":true,"org.eclipse.jdt.internal.compiler.classfmt.FieldInfo:createField()":true,"org.eclipse.jdt.internal.compiler.classfmt.FieldInfo:sizeInBytes()":true,"org.eclipse.jdt.internal.compiler.classfmt.AnnotationMethodInfo:createAnnotationMethod()":true,"org.eclipse.jdt.internal.compiler.classfmt.MethodInfo:createMethod()":true,"org.eclipse.jdt.internal.compiler.classfmt.MethodInfo:sizeInBytes()":true,"org.eclipse.jdt.internal.compiler.classfmt.ClassFileReader:utf8At()":true,"org.eclipse.jdt.internal.compiler.classfmt.ClassFileReader:u4At()":true,"org.eclipse.jdt.core.compiler.CharOperation:equals()":true,"org.eclipse.jdt.internal.compiler.classfmt.InnerClassInfo:<init>()":true,"org.eclipse.jdt.internal.compiler.classfmt.InnerClassInfo:getEnclosingTypeName()":true,"org.eclipse.jdt.internal.compiler.classfmt.ClassFileReader:decodeAnnotations()":true,"org.eclipse.jdt.internal.compiler.classfmt.ClassFileReader:decodeTypeAnnotations()":true,"org.eclipse.jdt.core.compiler.CharOperation:splitOn()":true,"org.eclipse.jdt.internal.compiler.classfmt.ClassFileReader:initialize()":true,"org.eclipse.jdt.internal.compiler.classfmt.ClassFormatException:<init>()":true},"label":"ClassFileReader:<init>()","className":"org.eclipse.jdt.internal.compiler.classfmt.ClassFileReader","acdcCluster":"org.eclipse.jdt.internal.compiler.classfmt.ss","groupId":"cluster"},{"id":"16211","name":"org.eclipse.jdt.internal.compiler.classfmt.ClassFileReader:decodeAnnotations()","value":6,"children":{"org.eclipse.jdt.internal.compiler.classfmt.ClassFileReader:u2At()":true,"org.eclipse.jdt.internal.compiler.classfmt.AnnotationInfo:<init>()":true,"java.lang.System:arraycopy()":true},"label":"ClassFileReader:decodeAnnotations()","className":"org.eclipse.jdt.internal.compiler.classfmt.ClassFileReader","acdcCluster":"org.eclipse.jdt.internal.compiler.classfmt.ss","groupId":"cluster"},{"id":"16248","name":"org.eclipse.jdt.internal.compiler.classfmt.ClassFileStruct:<init>()","value":2,"children":{"java.lang.Object:<init>()":true},"label":"ClassFileStruct:<init>()","className":"org.eclipse.jdt.internal.compiler.classfmt.ClassFileStruct","acdcCluster":"org.eclipse.jdt.internal.compiler.classfmt.ss","groupId":"cluster"},{"id":"22189","name":"org.eclipse.jdt.internal.compiler.classfmt.ClassFileReader:u2At()","value":1,"children":{},"label":"ClassFileReader:u2At()","className":"org.eclipse.jdt.internal.compiler.classfmt.ClassFileReader","acdcCluster":"org.eclipse.jdt.internal.compiler.classfmt.ss","groupId":"cluster"},{"id":"22191","name":"org.eclipse.jdt.internal.compiler.classfmt.ClassFileReader:utf8At()","value":1,"children":{},"label":"ClassFileReader:utf8At()","className":"org.eclipse.jdt.internal.compiler.classfmt.ClassFileReader","acdcCluster":"org.eclipse.jdt.internal.compiler.classfmt.ss","groupId":"cluster"},{"id":"16479","name":"org.eclipse.jdt.internal.compiler.classfmt.TypeAnnotationInfo:<init>()","value":18,"children":{"org.eclipse.jdt.internal.compiler.classfmt.ClassFileStruct:<init>()":true,"org.eclipse.jdt.internal.compiler.classfmt.TypeAnnotationInfo:<init>()":true,"org.eclipse.jdt.internal.compiler.classfmt.TypeAnnotationInfo:u1At()":true,"org.eclipse.jdt.internal.compiler.classfmt.TypeAnnotationInfo:u2At()":true,"java.lang.StringBuilder:<init>()":true,"java.lang.StringBuilder:append()":true,"java.lang.StringBuilder:toString()":true,"java.lang.IllegalStateException:<init>()":true,"org.eclipse.jdt.internal.compiler.classfmt.AnnotationInfo:<init>()":true},"label":"TypeAnnotationInfo:<init>()","className":"org.eclipse.jdt.internal.compiler.classfmt.TypeAnnotationInfo","acdcCluster":"org.eclipse.jdt.internal.compiler.classfmt.ss"},{"id":"244","name":"java.lang.System:arraycopy()","value":1,"children":{},"label":"System:arraycopy()","className":"java.lang.System","acdcCluster":"org.apache.catalina.ssi.ss"},{"id":"22218","name":"org.eclipse.jdt.internal.compiler.classfmt.TypeAnnotationInfo:u1At()","value":1,"children":{},"label":"TypeAnnotationInfo:u1At()","className":"org.eclipse.jdt.internal.compiler.classfmt.TypeAnnotationInfo","acdcCluster":"org.eclipse.jdt.internal.compiler.classfmt.ss"},{"id":"22219","name":"org.eclipse.jdt.internal.compiler.classfmt.TypeAnnotationInfo:u2At()","value":1,"children":{},"label":"TypeAnnotationInfo:u2At()","className":"org.eclipse.jdt.internal.compiler.classfmt.TypeAnnotationInfo","acdcCluster":"org.eclipse.jdt.internal.compiler.classfmt.ss"},{"id":"169","name":"java.lang.StringBuilder:<init>()","value":1,"children":{},"label":"StringBuilder:<init>()","className":"java.lang.StringBuilder","acdcCluster":"org.apache.tomcat.util.descriptor.web.ss"},{"id":"170","name":"java.lang.StringBuilder:append()","value":1,"children":{},"label":"StringBuilder:append()","className":"java.lang.StringBuilder","acdcCluster":"org.apache.tomcat.util.descriptor.web.ss"},{"id":"171","name":"java.lang.StringBuilder:toString()","value":1,"children":{},"label":"StringBuilder:toString()","className":"java.lang.StringBuilder","acdcCluster":"org.apache.tomcat.util.descriptor.web.ss"},{"id":"1547","name":"java.lang.IllegalStateException:<init>()","value":1,"children":{},"label":"IllegalStateException:<init>()","className":"java.lang.IllegalStateException","acdcCluster":"org.apache.tomcat.websocket.ss"},{"id":"16177","name":"org.eclipse.jdt.internal.compiler.classfmt.AnnotationInfo:<init>()","value":5,"children":{"org.eclipse.jdt.internal.compiler.classfmt.ClassFileStruct:<init>()":true,"org.eclipse.jdt.internal.compiler.classfmt.AnnotationInfo:<init>()":true,"org.eclipse.jdt.internal.compiler.classfmt.AnnotationInfo:decodeAnnotation()":true,"org.eclipse.jdt.internal.compiler.classfmt.AnnotationInfo:scanAnnotation()":true},"label":"AnnotationInfo:<init>()","className":"org.eclipse.jdt.internal.compiler.classfmt.AnnotationInfo","acdcCluster":"org.eclipse.jdt.internal.compiler.classfmt.ss"},{"id":"16178","name":"org.eclipse.jdt.internal.compiler.classfmt.AnnotationInfo:decodeAnnotation()","value":10,"children":{"org.eclipse.jdt.internal.compiler.classfmt.AnnotationInfo:u2At()":true,"org.eclipse.jdt.internal.compiler.classfmt.AnnotationInfo:utf8At()":true,"org.eclipse.jdt.internal.compiler.classfmt.AnnotationInfo:decodeDefaultValue()":true,"org.eclipse.jdt.internal.compiler.classfmt.ElementValuePairInfo:<init>()":true},"label":"AnnotationInfo:decodeAnnotation()","className":"org.eclipse.jdt.internal.compiler.classfmt.AnnotationInfo","acdcCluster":"org.eclipse.jdt.internal.compiler.classfmt.ss"},{"id":"16185","name":"org.eclipse.jdt.internal.compiler.classfmt.AnnotationInfo:scanAnnotation()","value":15,"children":{"org.eclipse.jdt.internal.compiler.classfmt.AnnotationInfo:u2At()":true,"org.eclipse.jdt.internal.compiler.classfmt.AnnotationInfo:utf8At()":true,"org.eclipse.jdt.core.compiler.CharOperation:equals()":true,"org.eclipse.jdt.internal.compiler.classfmt.AnnotationInfo:readTargetValue()":true,"org.eclipse.jdt.internal.compiler.classfmt.AnnotationInfo:readRetentionPolicy()":true,"org.eclipse.jdt.internal.compiler.classfmt.AnnotationInfo:scanElementValue()":true},"label":"AnnotationInfo:scanAnnotation()","className":"org.eclipse.jdt.internal.compiler.classfmt.AnnotationInfo","acdcCluster":"org.eclipse.jdt.internal.compiler.classfmt.ss"},{"id":"22213","name":"org.eclipse.jdt.internal.compiler.classfmt.InnerClassInfo:u2At()","value":1,"children":{},"label":"InnerClassInfo:u2At()","className":"org.eclipse.jdt.internal.compiler.classfmt.InnerClassInfo","acdcCluster":"org.eclipse.jdt.internal.compiler.classfmt.ss"},{"id":"16363","name":"org.eclipse.jdt.internal.compiler.classfmt.FieldInfo:createField()","value":23,"children":{"org.eclipse.jdt.internal.compiler.classfmt.FieldInfo:<init>()":true,"org.eclipse.jdt.internal.compiler.classfmt.FieldInfo:u2At()":true,"org.eclipse.jdt.internal.compiler.classfmt.FieldInfo:utf8At()":true,"org.eclipse.jdt.core.compiler.CharOperation:equals()":true,"org.eclipse.jdt.internal.compiler.classfmt.FieldInfo:decodeAnnotations()":true,"org.eclipse.jdt.internal.compiler.classfmt.FieldInfo:decodeTypeAnnotations()":true,"java.lang.System:arraycopy()":true,"org.eclipse.jdt.internal.compiler.classfmt.FieldInfo:u4At()":true,"org.eclipse.jdt.internal.compiler.classfmt.FieldInfoWithTypeAnnotation:<init>()":true,"org.eclipse.jdt.internal.compiler.classfmt.FieldInfoWithAnnotation:<init>()":true},"label":"FieldInfo:createField()","className":"org.eclipse.jdt.internal.compiler.classfmt.FieldInfo","acdcCluster":"org.eclipse.jdt.internal.compiler.classfmt.ss"},{"id":"16191","name":"org.eclipse.jdt.internal.compiler.classfmt.AnnotationMethodInfo:createAnnotationMethod()","value":21,"children":{"org.eclipse.jdt.internal.compiler.classfmt.MethodInfo:<init>()":true,"org.eclipse.jdt.internal.compiler.classfmt.MethodInfo:u2At()":true,"org.eclipse.jdt.internal.compiler.classfmt.MethodInfo:utf8At()":true,"org.eclipse.jdt.core.compiler.CharOperation:equals()":true,"org.eclipse.jdt.internal.compiler.classfmt.AnnotationInfo:<init>()":true,"org.eclipse.jdt.internal.compiler.classfmt.AnnotationInfo:decodeDefaultValue()":true,"org.eclipse.jdt.internal.compiler.classfmt.AnnotationMethodInfo:decodeMethodAnnotations()":true,"java.lang.System:arraycopy()":true,"org.eclipse.jdt.internal.compiler.classfmt.MethodInfo:u4At()":true,"org.eclipse.jdt.internal.compiler.classfmt.AnnotationMethodInfoWithAnnotations:<init>()":true,"org.eclipse.jdt.internal.compiler.classfmt.AnnotationMethodInfo:<init>()":true,"org.eclipse.jdt.internal.compiler.classfmt.MethodInfoWithAnnotations:<init>()":true},"label":"AnnotationMethodInfo:createAnnotationMethod()","className":"org.eclipse.jdt.internal.compiler.classfmt.AnnotationMethodInfo","acdcCluster":"org.eclipse.jdt.internal.compiler.classfmt.ss"},{"id":"16410","name":"org.eclipse.jdt.internal.compiler.classfmt.MethodInfo:createMethod()","value":32,"children":{"org.eclipse.jdt.internal.compiler.classfmt.MethodInfo:<init>()":true,"org.eclipse.jdt.internal.compiler.classfmt.MethodInfo:u2At()":true,"org.eclipse.jdt.internal.compiler.classfmt.MethodInfo:utf8At()":true,"org.eclipse.jdt.core.compiler.CharOperation:equals()":true,"org.eclipse.jdt.internal.compiler.classfmt.MethodInfo:decodeMethodParameters()":true,"org.eclipse.jdt.internal.compiler.classfmt.MethodInfo:decodeMethodAnnotations()":true,"org.eclipse.jdt.internal.compiler.classfmt.MethodInfo:decodeParamAnnotations()":true,"org.eclipse.jdt.internal.compiler.classfmt.MethodInfo:decodeTypeAnnotations()":true,"java.lang.System:arraycopy()":true,"org.eclipse.jdt.internal.compiler.classfmt.MethodInfo:u4At()":true,"org.eclipse.jdt.internal.compiler.classfmt.MethodInfoWithTypeAnnotations:<init>()":true,"org.eclipse.jdt.internal.compiler.classfmt.MethodInfoWithParameterAnnotations:<init>()":true,"org.eclipse.jdt.internal.compiler.classfmt.MethodInfoWithAnnotations:<init>()":true},"label":"MethodInfo:createMethod()","className":"org.eclipse.jdt.internal.compiler.classfmt.MethodInfo","acdcCluster":"org.eclipse.jdt.internal.compiler.classfmt.ss"},{"id":"13861","name":"org.eclipse.jdt.core.compiler.CharOperation:equals()","value":10,"children":{"org.eclipse.jdt.core.compiler.CharOperation:equals()":true,"org.eclipse.jdt.internal.compiler.parser.ScannerHelper:toLowerCase()":true},"label":"CharOperation:equals()","className":"org.eclipse.jdt.core.compiler.CharOperation","acdcCluster":"org.eclipse.jdt.internal.compiler.classfmt.ss"},{"id":"16402","name":"org.eclipse.jdt.internal.compiler.classfmt.InnerClassInfo:getEnclosingTypeName()","value":4,"children":{"org.eclipse.jdt.internal.compiler.classfmt.InnerClassInfo:u2At()":true,"org.eclipse.jdt.internal.compiler.classfmt.InnerClassInfo:utf8At()":true},"label":"InnerClassInfo:getEnclosingTypeName()","className":"org.eclipse.jdt.internal.compiler.classfmt.InnerClassInfo","acdcCluster":"org.eclipse.jdt.internal.compiler.classfmt.ss"},{"id":"13877","name":"org.eclipse.jdt.core.compiler.CharOperation:splitOn()","value":5,"children":{"java.lang.System:arraycopy()":true},"label":"CharOperation:splitOn()","className":"org.eclipse.jdt.core.compiler.CharOperation","acdcCluster":"org.eclipse.jdt.internal.compiler.classfmt.ss"},{"id":"16239","name":"org.eclipse.jdt.internal.compiler.classfmt.ClassFileReader:initialize()","value":8,"children":{"org.eclipse.jdt.internal.compiler.classfmt.FieldInfo:initialize()":true,"org.eclipse.jdt.internal.compiler.classfmt.MethodInfo:initialize()":true,"org.eclipse.jdt.internal.compiler.classfmt.InnerClassInfo:initialize()":true,"org.eclipse.jdt.internal.compiler.classfmt.AnnotationInfo:initialize()":true,"org.eclipse.jdt.internal.compiler.classfmt.ClassFileReader:getEnclosingMethod()":true,"org.eclipse.jdt.internal.compiler.classfmt.ClassFileReader:reset()":true,"org.eclipse.jdt.internal.compiler.classfmt.ClassFormatException:<init>()":true},"label":"ClassFileReader:initialize()","className":"org.eclipse.jdt.internal.compiler.classfmt.ClassFileReader","acdcCluster":"org.eclipse.jdt.internal.compiler.classfmt.ss"},{"id":"16259","name":"org.eclipse.jdt.internal.compiler.classfmt.ClassFormatException:<init>()","value":4,"children":{"java.lang.Exception:<init>()":true},"label":"ClassFormatException:<init>()","className":"org.eclipse.jdt.internal.compiler.classfmt.ClassFormatException","acdcCluster":"org.eclipse.jdt.internal.compiler.apt.dispatch.ss"},{"id":"16364","name":"org.eclipse.jdt.internal.compiler.classfmt.FieldInfo:<init>()","value":2,"children":{"org.eclipse.jdt.internal.compiler.classfmt.ClassFileStruct:<init>()":true},"label":"FieldInfo:<init>()","className":"org.eclipse.jdt.internal.compiler.classfmt.FieldInfo","acdcCluster":"org.eclipse.jdt.internal.compiler.classfmt.ss"},{"id":"22202","name":"org.eclipse.jdt.internal.compiler.classfmt.FieldInfo:u2At()","value":1,"children":{},"label":"FieldInfo:u2At()","className":"org.eclipse.jdt.internal.compiler.classfmt.FieldInfo","acdcCluster":"org.eclipse.jdt.internal.compiler.classfmt.ss"},{"id":"22203","name":"org.eclipse.jdt.internal.compiler.classfmt.FieldInfo:utf8At()","value":1,"children":{},"label":"FieldInfo:utf8At()","className":"org.eclipse.jdt.internal.compiler.classfmt.FieldInfo","acdcCluster":"org.eclipse.jdt.internal.compiler.classfmt.ss"},{"id":"16365","name":"org.eclipse.jdt.internal.compiler.classfmt.FieldInfo:decodeAnnotations()","value":4,"children":{"org.eclipse.jdt.internal.compiler.classfmt.FieldInfo:u2At()":true,"org.eclipse.jdt.internal.compiler.classfmt.AnnotationInfo:<init>()":true,"java.lang.System:arraycopy()":true},"label":"FieldInfo:decodeAnnotations()","className":"org.eclipse.jdt.internal.compiler.classfmt.FieldInfo","acdcCluster":"org.eclipse.jdt.internal.compiler.classfmt.ss"},{"id":"16366","name":"org.eclipse.jdt.internal.compiler.classfmt.FieldInfo:decodeTypeAnnotations()","value":3,"children":{"org.eclipse.jdt.internal.compiler.classfmt.FieldInfo:u2At()":true,"org.eclipse.jdt.internal.compiler.classfmt.TypeAnnotationInfo:<init>()":true},"label":"FieldInfo:decodeTypeAnnotations()","className":"org.eclipse.jdt.internal.compiler.classfmt.FieldInfo","acdcCluster":"org.eclipse.jdt.internal.compiler.classfmt.ss"},{"id":"22204","name":"org.eclipse.jdt.internal.compiler.classfmt.FieldInfo:u4At()","value":1,"children":{},"label":"FieldInfo:u4At()","className":"org.eclipse.jdt.internal.compiler.classfmt.FieldInfo","acdcCluster":"org.eclipse.jdt.internal.compiler.classfmt.ss"},{"id":"16395","name":"org.eclipse.jdt.internal.compiler.classfmt.FieldInfoWithTypeAnnotation:<init>()","value":2,"children":{"org.eclipse.jdt.internal.compiler.classfmt.FieldInfoWithAnnotation:<init>()":true},"label":"FieldInfoWithTypeAnnotation:<init>()","className":"org.eclipse.jdt.internal.compiler.classfmt.FieldInfoWithTypeAnnotation","acdcCluster":"org.eclipse.jdt.internal.compiler.classfmt.ss"},{"id":"16389","name":"org.eclipse.jdt.internal.compiler.classfmt.FieldInfoWithAnnotation:<init>()","value":2,"children":{"org.eclipse.jdt.internal.compiler.classfmt.FieldInfo:<init>()":true},"label":"FieldInfoWithAnnotation:<init>()","className":"org.eclipse.jdt.internal.compiler.classfmt.FieldInfoWithAnnotation","acdcCluster":"org.eclipse.jdt.internal.compiler.classfmt.ss"},{"id":"22181","name":"org.eclipse.jdt.internal.compiler.classfmt.MethodInfo:u2At()","value":1,"children":{},"label":"MethodInfo:u2At()","className":"org.eclipse.jdt.internal.compiler.classfmt.MethodInfo","acdcCluster":"org.eclipse.jdt.internal.compiler.classfmt.ss"},{"id":"22182","name":"org.eclipse.jdt.internal.compiler.classfmt.MethodInfo:utf8At()","value":1,"children":{},"label":"MethodInfo:utf8At()","className":"org.eclipse.jdt.internal.compiler.classfmt.MethodInfo","acdcCluster":"org.eclipse.jdt.internal.compiler.classfmt.ss"},{"id":"16179","name":"org.eclipse.jdt.internal.compiler.classfmt.AnnotationInfo:decodeDefaultValue()","value":49,"children":{"org.eclipse.jdt.internal.compiler.classfmt.AnnotationInfo:u1At()":true,"org.eclipse.jdt.internal.compiler.classfmt.AnnotationInfo:u2At()":true,"org.eclipse.jdt.internal.compiler.classfmt.AnnotationInfo:i4At()":true,"org.eclipse.jdt.internal.compiler.impl.BooleanConstant:fromValue()":true,"org.eclipse.jdt.internal.compiler.impl.IntConstant:fromValue()":true,"org.eclipse.jdt.internal.compiler.impl.CharConstant:fromValue()":true,"org.eclipse.jdt.internal.compiler.impl.ByteConstant:fromValue()":true,"org.eclipse.jdt.internal.compiler.impl.ShortConstant:fromValue()":true,"org.eclipse.jdt.internal.compiler.classfmt.AnnotationInfo:doubleAt()":true,"org.eclipse.jdt.internal.compiler.impl.DoubleConstant:fromValue()":true,"org.eclipse.jdt.internal.compiler.classfmt.AnnotationInfo:floatAt()":true,"org.eclipse.jdt.internal.compiler.impl.FloatConstant:fromValue()":true,"org.eclipse.jdt.internal.compiler.classfmt.AnnotationInfo:i8At()":true,"org.eclipse.jdt.internal.compiler.impl.LongConstant:fromValue()":true,"org.eclipse.jdt.internal.compiler.classfmt.AnnotationInfo:utf8At()":true,"java.lang.String:valueOf()":true,"org.eclipse.jdt.internal.compiler.impl.StringConstant:fromValue()":true,"org.eclipse.jdt.internal.compiler.env.EnumConstantSignature:<init>()":true,"org.eclipse.jdt.internal.compiler.env.ClassSignature:<init>()":true,"org.eclipse.jdt.internal.compiler.classfmt.AnnotationInfo:<init>()":true,"org.eclipse.jdt.internal.compiler.classfmt.AnnotationInfo:decodeDefaultValue()":true,"java.lang.StringBuilder:<init>()":true,"java.lang.StringBuilder:append()":true,"java.lang.StringBuilder:toString()":true,"java.lang.IllegalStateException:<init>()":true},"label":"AnnotationInfo:decodeDefaultValue()","className":"org.eclipse.jdt.internal.compiler.classfmt.AnnotationInfo","acdcCluster":"org.eclipse.jdt.internal.compiler.classfmt.ss"},{"id":"22183","name":"org.eclipse.jdt.internal.compiler.classfmt.AnnotationMethodInfo:decodeMethodAnnotations()","value":1,"children":{},"label":"AnnotationMethodInfo:decodeMethodAnnotations()","className":"org.eclipse.jdt.internal.compiler.classfmt.AnnotationMethodInfo","acdcCluster":"org.eclipse.jdt.internal.compiler.classfmt.ss"},{"id":"22184","name":"org.eclipse.jdt.internal.compiler.classfmt.MethodInfo:u4At()","value":1,"children":{},"label":"MethodInfo:u4At()","className":"org.eclipse.jdt.internal.compiler.classfmt.MethodInfo","acdcCluster":"org.eclipse.jdt.internal.compiler.classfmt.ss"},{"id":"16196","name":"org.eclipse.jdt.internal.compiler.classfmt.AnnotationMethodInfoWithAnnotations:<init>()","value":2,"children":{"org.eclipse.jdt.internal.compiler.classfmt.AnnotationMethodInfo:<init>()":true},"label":"AnnotationMethodInfoWithAnnotations:<init>()","className":"org.eclipse.jdt.internal.compiler.classfmt.AnnotationMethodInfoWithAnnotations","acdcCluster":"org.eclipse.jdt.internal.compiler.classfmt.ss"},{"id":"16192","name":"org.eclipse.jdt.internal.compiler.classfmt.AnnotationMethodInfo:<init>()","value":2,"children":{"org.eclipse.jdt.internal.compiler.classfmt.MethodInfo:<init>()":true},"label":"AnnotationMethodInfo:<init>()","className":"org.eclipse.jdt.internal.compiler.classfmt.AnnotationMethodInfo","acdcCluster":"org.eclipse.jdt.internal.compiler.classfmt.ss"},{"id":"16443","name":"org.eclipse.jdt.internal.compiler.classfmt.MethodInfo:decodeMethodParameters()","value":8,"children":{"org.eclipse.jdt.internal.compiler.classfmt.MethodInfo:u1At()":true,"org.eclipse.jdt.internal.compiler.classfmt.MethodInfo:u2At()":true,"org.eclipse.jdt.internal.compiler.classfmt.MethodInfo:utf8At()":true,"java.lang.String:valueOf()":true,"java.lang.String:toCharArray()":true,"org.eclipse.jdt.core.compiler.CharOperation:concat()":true},"label":"MethodInfo:decodeMethodParameters()","className":"org.eclipse.jdt.internal.compiler.classfmt.MethodInfo","acdcCluster":"org.eclipse.jdt.internal.compiler.classfmt.ss"},{"id":"16412","name":"org.eclipse.jdt.internal.compiler.classfmt.MethodInfo:decodeMethodAnnotations()","value":3,"children":{"org.eclipse.jdt.internal.compiler.classfmt.MethodInfo:u2At()":true,"org.eclipse.jdt.internal.compiler.classfmt.MethodInfo:decodeAnnotations()":true},"label":"MethodInfo:decodeMethodAnnotations()","className":"org.eclipse.jdt.internal.compiler.classfmt.MethodInfo","acdcCluster":"org.eclipse.jdt.internal.compiler.classfmt.ss"},{"id":"16414","name":"org.eclipse.jdt.internal.compiler.classfmt.MethodInfo:decodeParamAnnotations()","value":4,"children":{"org.eclipse.jdt.internal.compiler.classfmt.MethodInfo:u1At()":true,"org.eclipse.jdt.internal.compiler.classfmt.MethodInfo:u2At()":true,"org.eclipse.jdt.internal.compiler.classfmt.MethodInfo:decodeAnnotations()":true},"label":"MethodInfo:decodeParamAnnotations()","className":"org.eclipse.jdt.internal.compiler.classfmt.MethodInfo","acdcCluster":"org.eclipse.jdt.internal.compiler.classfmt.ss"},{"id":"16413","name":"org.eclipse.jdt.internal.compiler.classfmt.MethodInfo:decodeTypeAnnotations()","value":3,"children":{"org.eclipse.jdt.internal.compiler.classfmt.MethodInfo:u2At()":true,"org.eclipse.jdt.internal.compiler.classfmt.TypeAnnotationInfo:<init>()":true},"label":"MethodInfo:decodeTypeAnnotations()","className":"org.eclipse.jdt.internal.compiler.classfmt.MethodInfo","acdcCluster":"org.eclipse.jdt.internal.compiler.classfmt.ss"},{"id":"16458","name":"org.eclipse.jdt.internal.compiler.classfmt.MethodInfoWithTypeAnnotations:<init>()","value":2,"children":{"org.eclipse.jdt.internal.compiler.classfmt.MethodInfoWithParameterAnnotations:<init>()":true},"label":"MethodInfoWithTypeAnnotations:<init>()","className":"org.eclipse.jdt.internal.compiler.classfmt.MethodInfoWithTypeAnnotations","acdcCluster":"org.eclipse.jdt.internal.compiler.classfmt.ss"},{"id":"16451","name":"org.eclipse.jdt.internal.compiler.classfmt.MethodInfoWithParameterAnnotations:<init>()","value":2,"children":{"org.eclipse.jdt.internal.compiler.classfmt.MethodInfoWithAnnotations:<init>()":true},"label":"MethodInfoWithParameterAnnotations:<init>()","className":"org.eclipse.jdt.internal.compiler.classfmt.MethodInfoWithParameterAnnotations","acdcCluster":"org.eclipse.jdt.internal.compiler.classfmt.ss"},{"id":"20374","name":"org.eclipse.jdt.internal.compiler.parser.ScannerHelper:toLowerCase()","value":2,"children":{"java.lang.Character:toLowerCase()":true},"label":"ScannerHelper:toLowerCase()","className":"org.eclipse.jdt.internal.compiler.parser.ScannerHelper","acdcCluster":"org.eclipse.jdt.internal.compiler.parser.ss"},{"id":"22214","name":"org.eclipse.jdt.internal.compiler.classfmt.InnerClassInfo:utf8At()","value":1,"children":{},"label":"InnerClassInfo:utf8At()","className":"org.eclipse.jdt.internal.compiler.classfmt.InnerClassInfo","acdcCluster":"org.eclipse.jdt.internal.compiler.classfmt.ss"},{"id":"16380","name":"org.eclipse.jdt.internal.compiler.classfmt.FieldInfo:initialize()","value":7,"children":{"org.eclipse.jdt.internal.compiler.classfmt.FieldInfo:getModifiers()":true,"org.eclipse.jdt.internal.compiler.classfmt.FieldInfo:getName()":true,"org.eclipse.jdt.internal.compiler.classfmt.FieldInfo:getConstant()":true,"org.eclipse.jdt.internal.compiler.classfmt.FieldInfo:getTypeName()":true,"org.eclipse.jdt.internal.compiler.classfmt.FieldInfo:getGenericSignature()":true,"org.eclipse.jdt.internal.compiler.classfmt.FieldInfo:reset()":true},"label":"FieldInfo:initialize()","className":"org.eclipse.jdt.internal.compiler.classfmt.FieldInfo","acdcCluster":"org.eclipse.jdt.internal.compiler.classfmt.ss"},{"id":"16431","name":"org.eclipse.jdt.internal.compiler.classfmt.MethodInfo:initialize()","value":8,"children":{"org.eclipse.jdt.internal.compiler.classfmt.MethodInfo:getModifiers()":true,"org.eclipse.jdt.internal.compiler.classfmt.MethodInfo:getSelector()":true,"org.eclipse.jdt.internal.compiler.classfmt.MethodInfo:getMethodDescriptor()":true,"org.eclipse.jdt.internal.compiler.classfmt.MethodInfo:getExceptionTypeNames()":true,"org.eclipse.jdt.internal.compiler.classfmt.MethodInfo:getGenericSignature()":true,"org.eclipse.jdt.internal.compiler.classfmt.MethodInfo:getArgumentNames()":true,"org.eclipse.jdt.internal.compiler.classfmt.MethodInfo:reset()":true},"label":"MethodInfo:initialize()","className":"org.eclipse.jdt.internal.compiler.classfmt.MethodInfo","acdcCluster":"org.eclipse.jdt.internal.compiler.classfmt.ss"},{"id":"16407","name":"org.eclipse.jdt.internal.compiler.classfmt.InnerClassInfo:initialize()","value":6,"children":{"org.eclipse.jdt.internal.compiler.classfmt.InnerClassInfo:getModifiers()":true,"org.eclipse.jdt.internal.compiler.classfmt.InnerClassInfo:getName()":true,"org.eclipse.jdt.internal.compiler.classfmt.InnerClassInfo:getSourceName()":true,"org.eclipse.jdt.internal.compiler.classfmt.InnerClassInfo:getEnclosingTypeName()":true,"org.eclipse.jdt.internal.compiler.classfmt.InnerClassInfo:reset()":true},"label":"InnerClassInfo:initialize()","className":"org.eclipse.jdt.internal.compiler.classfmt.InnerClassInfo","acdcCluster":"org.eclipse.jdt.internal.compiler.classfmt.ss"},{"id":"16182","name":"org.eclipse.jdt.internal.compiler.classfmt.AnnotationInfo:initialize()","value":2,"children":{"org.eclipse.jdt.internal.compiler.classfmt.AnnotationInfo:decodeAnnotation()":true},"label":"AnnotationInfo:initialize()","className":"org.eclipse.jdt.internal.compiler.classfmt.AnnotationInfo","acdcCluster":"org.eclipse.jdt.internal.compiler.classfmt.ss"},{"id":"16217","name":"org.eclipse.jdt.internal.compiler.classfmt.ClassFileReader:getEnclosingMethod()","value":12,"children":{"java.lang.StringBuffer:<init>()":true,"org.eclipse.jdt.internal.compiler.classfmt.ClassFileReader:u2At()":true,"org.eclipse.jdt.internal.compiler.classfmt.ClassFileReader:utf8At()":true,"java.lang.StringBuffer:append()":true,"java.lang.String:valueOf()":true,"java.lang.String:toCharArray()":true},"label":"ClassFileReader:getEnclosingMethod()","className":"org.eclipse.jdt.internal.compiler.classfmt.ClassFileReader","acdcCluster":"org.eclipse.jdt.internal.compiler.classfmt.ss"},{"id":"22194","name":"org.eclipse.jdt.internal.compiler.classfmt.ClassFileReader:reset()","value":1,"children":{},"label":"ClassFileReader:reset()","className":"org.eclipse.jdt.internal.compiler.classfmt.ClassFileReader","acdcCluster":"org.eclipse.jdt.internal.compiler.classfmt.ss"},{"id":"1314","name":"java.lang.Exception:<init>()","value":1,"children":{},"label":"Exception:<init>()","className":"java.lang.Exception","acdcCluster":"org.apache.tomcat.util.descriptor.web.ss"},{"id":"22176","name":"org.eclipse.jdt.internal.compiler.classfmt.AnnotationInfo:u1At()","value":1,"children":{},"label":"AnnotationInfo:u1At()","className":"org.eclipse.jdt.internal.compiler.classfmt.AnnotationInfo","acdcCluster":"org.eclipse.jdt.internal.compiler.classfmt.ss"},{"id":"22174","name":"org.eclipse.jdt.internal.compiler.classfmt.AnnotationInfo:u2At()","value":1,"children":{},"label":"AnnotationInfo:u2At()","className":"org.eclipse.jdt.internal.compiler.classfmt.AnnotationInfo","acdcCluster":"org.eclipse.jdt.internal.compiler.classfmt.ss"},{"id":"22177","name":"org.eclipse.jdt.internal.compiler.classfmt.AnnotationInfo:i4At()","value":1,"children":{},"label":"AnnotationInfo:i4At()","className":"org.eclipse.jdt.internal.compiler.classfmt.AnnotationInfo","acdcCluster":"org.eclipse.jdt.internal.compiler.classfmt.ss"},{"id":"17507","name":"org.eclipse.jdt.internal.compiler.impl.BooleanConstant:fromValue()","value":1,"children":{},"label":"BooleanConstant:fromValue()","className":"org.eclipse.jdt.internal.compiler.impl.BooleanConstant","acdcCluster":"org.eclipse.jdt.internal.compiler.parser.ss"},{"id":"17638","name":"org.eclipse.jdt.internal.compiler.impl.IntConstant:fromValue()","value":2,"children":{"org.eclipse.jdt.internal.compiler.impl.IntConstant:<init>()":true},"label":"IntConstant:fromValue()","className":"org.eclipse.jdt.internal.compiler.impl.IntConstant","acdcCluster":"org.eclipse.jdt.internal.compiler.parser.ss"},{"id":"17531","name":"org.eclipse.jdt.internal.compiler.impl.CharConstant:fromValue()","value":2,"children":{"org.eclipse.jdt.internal.compiler.impl.CharConstant:<init>()":true},"label":"CharConstant:fromValue()","className":"org.eclipse.jdt.internal.compiler.impl.CharConstant","acdcCluster":"org.eclipse.jdt.internal.compiler.parser.ss"},{"id":"17516","name":"org.eclipse.jdt.internal.compiler.impl.ByteConstant:fromValue()","value":2,"children":{"org.eclipse.jdt.internal.compiler.impl.ByteConstant:<init>()":true},"label":"ByteConstant:fromValue()","className":"org.eclipse.jdt.internal.compiler.impl.ByteConstant","acdcCluster":"org.eclipse.jdt.internal.compiler.parser.ss"},{"id":"17688","name":"org.eclipse.jdt.internal.compiler.impl.ShortConstant:fromValue()","value":2,"children":{"org.eclipse.jdt.internal.compiler.impl.ShortConstant:<init>()":true},"label":"ShortConstant:fromValue()","className":"org.eclipse.jdt.internal.compiler.impl.ShortConstant","acdcCluster":"org.eclipse.jdt.internal.compiler.parser.ss"},{"id":"22178","name":"org.eclipse.jdt.internal.compiler.classfmt.AnnotationInfo:doubleAt()","value":1,"children":{},"label":"AnnotationInfo:doubleAt()","className":"org.eclipse.jdt.internal.compiler.classfmt.AnnotationInfo","acdcCluster":"org.eclipse.jdt.internal.compiler.classfmt.ss"},{"id":"17605","name":"org.eclipse.jdt.internal.compiler.impl.DoubleConstant:fromValue()","value":2,"children":{"org.eclipse.jdt.internal.compiler.impl.DoubleConstant:<init>()":true},"label":"DoubleConstant:fromValue()","className":"org.eclipse.jdt.internal.compiler.impl.DoubleConstant","acdcCluster":"org.eclipse.jdt.internal.compiler.parser.ss"},{"id":"22179","name":"org.eclipse.jdt.internal.compiler.classfmt.AnnotationInfo:floatAt()","value":1,"children":{},"label":"AnnotationInfo:floatAt()","className":"org.eclipse.jdt.internal.compiler.classfmt.AnnotationInfo","acdcCluster":"org.eclipse.jdt.internal.compiler.classfmt.ss"},{"id":"17620","name":"org.eclipse.jdt.internal.compiler.impl.FloatConstant:fromValue()","value":2,"children":{"org.eclipse.jdt.internal.compiler.impl.FloatConstant:<init>()":true},"label":"FloatConstant:fromValue()","className":"org.eclipse.jdt.internal.compiler.impl.FloatConstant","acdcCluster":"org.eclipse.jdt.internal.compiler.parser.ss"},{"id":"22180","name":"org.eclipse.jdt.internal.compiler.classfmt.AnnotationInfo:i8At()","value":1,"children":{},"label":"AnnotationInfo:i8At()","className":"org.eclipse.jdt.internal.compiler.classfmt.AnnotationInfo","acdcCluster":"org.eclipse.jdt.internal.compiler.classfmt.ss"},{"id":"17666","name":"org.eclipse.jdt.internal.compiler.impl.LongConstant:fromValue()","value":2,"children":{"org.eclipse.jdt.internal.compiler.impl.LongConstant:<init>()":true},"label":"LongConstant:fromValue()","className":"org.eclipse.jdt.internal.compiler.impl.LongConstant","acdcCluster":"org.eclipse.jdt.internal.compiler.ast.ss"},{"id":"22175","name":"org.eclipse.jdt.internal.compiler.classfmt.AnnotationInfo:utf8At()","value":1,"children":{},"label":"AnnotationInfo:utf8At()","className":"org.eclipse.jdt.internal.compiler.classfmt.AnnotationInfo","acdcCluster":"org.eclipse.jdt.internal.compiler.classfmt.ss"},{"id":"3553","name":"java.lang.String:valueOf()","value":1,"children":{},"label":"String:valueOf()","className":"java.lang.String","acdcCluster":"org.apache.catalina.valves.ss"},{"id":"17703","name":"org.eclipse.jdt.internal.compiler.impl.StringConstant:fromValue()","value":2,"children":{"org.eclipse.jdt.internal.compiler.impl.StringConstant:<init>()":true},"label":"StringConstant:fromValue()","className":"org.eclipse.jdt.internal.compiler.impl.StringConstant","acdcCluster":"org.eclipse.jdt.internal.compiler.parser.ss"},{"id":"17073","name":"org.eclipse.jdt.internal.compiler.env.EnumConstantSignature:<init>()","value":2,"children":{"java.lang.Object:<init>()":true},"label":"EnumConstantSignature:<init>()","className":"org.eclipse.jdt.internal.compiler.env.EnumConstantSignature","acdcCluster":"org.eclipse.jdt.internal.compiler.parser.ss"},{"id":"17067","name":"org.eclipse.jdt.internal.compiler.env.ClassSignature:<init>()","value":2,"children":{"java.lang.Object:<init>()":true},"label":"ClassSignature:<init>()","className":"org.eclipse.jdt.internal.compiler.env.ClassSignature","acdcCluster":"org.eclipse.jdt.internal.compiler.parser.ss"},{"id":"22216","name":"org.eclipse.jdt.internal.compiler.classfmt.MethodInfo:u1At()","value":1,"children":{},"label":"MethodInfo:u1At()","className":"org.eclipse.jdt.internal.compiler.classfmt.MethodInfo","acdcCluster":"org.eclipse.jdt.internal.compiler.classfmt.ss"},{"id":"11236","name":"java.lang.String:toCharArray()","value":1,"children":{},"label":"String:toCharArray()","className":"java.lang.String","acdcCluster":"org.apache.catalina.valves.ss"},{"id":"13856","name":"org.eclipse.jdt.core.compiler.CharOperation:concat()","value":18,"children":{"java.lang.System:arraycopy()":true,"org.eclipse.jdt.core.compiler.CharOperation:concat()":true},"label":"CharOperation:concat()","className":"org.eclipse.jdt.core.compiler.CharOperation","acdcCluster":"org.eclipse.jdt.internal.compiler.classfmt.ss"},{"id":"16411","name":"org.eclipse.jdt.internal.compiler.classfmt.MethodInfo:decodeAnnotations()","value":2,"children":{"org.eclipse.jdt.internal.compiler.classfmt.AnnotationInfo:<init>()":true},"label":"MethodInfo:decodeAnnotations()","className":"org.eclipse.jdt.internal.compiler.classfmt.MethodInfo","acdcCluster":"org.eclipse.jdt.internal.compiler.classfmt.ss"},{"id":"22591","name":"java.lang.Character:toLowerCase()","value":1,"children":{},"label":"Character:toLowerCase()","className":"java.lang.Character","acdcCluster":"org.apache.tomcat.util.http.fileupload.ss"},{"id":"16372","name":"org.eclipse.jdt.internal.compiler.classfmt.FieldInfo:getModifiers()","value":3,"children":{"org.eclipse.jdt.internal.compiler.classfmt.FieldInfo:u2At()":true,"org.eclipse.jdt.internal.compiler.classfmt.FieldInfo:readModifierRelatedAttributes()":true},"label":"FieldInfo:getModifiers()","className":"org.eclipse.jdt.internal.compiler.classfmt.FieldInfo","acdcCluster":"org.eclipse.jdt.internal.compiler.classfmt.ss"},{"id":"16373","name":"org.eclipse.jdt.internal.compiler.classfmt.FieldInfo:getName()","value":4,"children":{"org.eclipse.jdt.internal.compiler.classfmt.FieldInfo:u2At()":true,"org.eclipse.jdt.internal.compiler.classfmt.FieldInfo:utf8At()":true},"label":"FieldInfo:getName()","className":"org.eclipse.jdt.internal.compiler.classfmt.FieldInfo","acdcCluster":"org.eclipse.jdt.internal.compiler.classfmt.ss"},{"id":"16370","name":"org.eclipse.jdt.internal.compiler.classfmt.FieldInfo:getConstant()","value":2,"children":{"org.eclipse.jdt.internal.compiler.classfmt.FieldInfo:readConstantAttribute()":true},"label":"FieldInfo:getConstant()","className":"org.eclipse.jdt.internal.compiler.classfmt.FieldInfo","acdcCluster":"org.eclipse.jdt.internal.compiler.classfmt.ss"},{"id":"16375","name":"org.eclipse.jdt.internal.compiler.classfmt.FieldInfo:getTypeName()","value":4,"children":{"org.eclipse.jdt.internal.compiler.classfmt.FieldInfo:u2At()":true,"org.eclipse.jdt.internal.compiler.classfmt.FieldInfo:utf8At()":true},"label":"FieldInfo:getTypeName()","className":"org.eclipse.jdt.internal.compiler.classfmt.FieldInfo","acdcCluster":"org.eclipse.jdt.internal.compiler.classfmt.ss"},{"id":"16371","name":"org.eclipse.jdt.internal.compiler.classfmt.FieldInfo:getGenericSignature()","value":3,"children":{"org.eclipse.jdt.internal.compiler.classfmt.FieldInfo:u2At()":true,"org.eclipse.jdt.internal.compiler.classfmt.FieldInfo:utf8At()":true},"label":"FieldInfo:getGenericSignature()","className":"org.eclipse.jdt.internal.compiler.classfmt.FieldInfo","acdcCluster":"org.eclipse.jdt.internal.compiler.classfmt.ss"},{"id":"22205","name":"org.eclipse.jdt.internal.compiler.classfmt.FieldInfo:reset()","value":1,"children":{},"label":"FieldInfo:reset()","className":"org.eclipse.jdt.internal.compiler.classfmt.FieldInfo","acdcCluster":"org.eclipse.jdt.internal.compiler.classfmt.ss"},{"id":"16425","name":"org.eclipse.jdt.internal.compiler.classfmt.MethodInfo:getModifiers()","value":3,"children":{"org.eclipse.jdt.internal.compiler.classfmt.MethodInfo:u2At()":true,"org.eclipse.jdt.internal.compiler.classfmt.MethodInfo:readModifierRelatedAttributes()":true},"label":"MethodInfo:getModifiers()","className":"org.eclipse.jdt.internal.compiler.classfmt.MethodInfo","acdcCluster":"org.eclipse.jdt.internal.compiler.classfmt.ss"},{"id":"16429","name":"org.eclipse.jdt.internal.compiler.classfmt.MethodInfo:getSelector()","value":4,"children":{"org.eclipse.jdt.internal.compiler.classfmt.MethodInfo:u2At()":true,"org.eclipse.jdt.internal.compiler.classfmt.MethodInfo:utf8At()":true},"label":"MethodInfo:getSelector()","className":"org.eclipse.jdt.internal.compiler.classfmt.MethodInfo","acdcCluster":"org.eclipse.jdt.internal.compiler.classfmt.ss"},{"id":"16424","name":"org.eclipse.jdt.internal.compiler.classfmt.MethodInfo:getMethodDescriptor()","value":4,"children":{"org.eclipse.jdt.internal.compiler.classfmt.MethodInfo:u2At()":true,"org.eclipse.jdt.internal.compiler.classfmt.MethodInfo:utf8At()":true},"label":"MethodInfo:getMethodDescriptor()","className":"org.eclipse.jdt.internal.compiler.classfmt.MethodInfo","acdcCluster":"org.eclipse.jdt.internal.compiler.classfmt.ss"},{"id":"16422","name":"org.eclipse.jdt.internal.compiler.classfmt.MethodInfo:getExceptionTypeNames()","value":2,"children":{"org.eclipse.jdt.internal.compiler.classfmt.MethodInfo:readExceptionAttributes()":true},"label":"MethodInfo:getExceptionTypeNames()","className":"org.eclipse.jdt.internal.compiler.classfmt.MethodInfo","acdcCluster":"org.eclipse.jdt.internal.compiler.classfmt.ss"},{"id":"16423","name":"org.eclipse.jdt.internal.compiler.classfmt.MethodInfo:getGenericSignature()","value":3,"children":{"org.eclipse.jdt.internal.compiler.classfmt.MethodInfo:u2At()":true,"org.eclipse.jdt.internal.compiler.classfmt.MethodInfo:utf8At()":true},"label":"MethodInfo:getGenericSignature()","className":"org.eclipse.jdt.internal.compiler.classfmt.MethodInfo","acdcCluster":"org.eclipse.jdt.internal.compiler.classfmt.ss"},{"id":"16420","name":"org.eclipse.jdt.internal.compiler.classfmt.MethodInfo:getArgumentNames()","value":2,"children":{"org.eclipse.jdt.internal.compiler.classfmt.MethodInfo:readCodeAttribute()":true},"label":"MethodInfo:getArgumentNames()","className":"org.eclipse.jdt.internal.compiler.classfmt.MethodInfo","acdcCluster":"org.eclipse.jdt.internal.compiler.classfmt.ss"},{"id":"22217","name":"org.eclipse.jdt.internal.compiler.classfmt.MethodInfo:reset()","value":1,"children":{},"label":"MethodInfo:reset()","className":"org.eclipse.jdt.internal.compiler.classfmt.MethodInfo","acdcCluster":"org.eclipse.jdt.internal.compiler.classfmt.ss"},{"id":"16403","name":"org.eclipse.jdt.internal.compiler.classfmt.InnerClassInfo:getModifiers()","value":2,"children":{"org.eclipse.jdt.internal.compiler.classfmt.InnerClassInfo:u2At()":true},"label":"InnerClassInfo:getModifiers()","className":"org.eclipse.jdt.internal.compiler.classfmt.InnerClassInfo","acdcCluster":"org.eclipse.jdt.internal.compiler.classfmt.ss"},{"id":"16404","name":"org.eclipse.jdt.internal.compiler.classfmt.InnerClassInfo:getName()","value":4,"children":{"org.eclipse.jdt.internal.compiler.classfmt.InnerClassInfo:u2At()":true,"org.eclipse.jdt.internal.compiler.classfmt.InnerClassInfo:utf8At()":true},"label":"InnerClassInfo:getName()","className":"org.eclipse.jdt.internal.compiler.classfmt.InnerClassInfo","acdcCluster":"org.eclipse.jdt.internal.compiler.classfmt.ss"},{"id":"16405","name":"org.eclipse.jdt.internal.compiler.classfmt.InnerClassInfo:getSourceName()","value":3,"children":{"org.eclipse.jdt.internal.compiler.classfmt.InnerClassInfo:u2At()":true,"org.eclipse.jdt.internal.compiler.classfmt.InnerClassInfo:utf8At()":true},"label":"InnerClassInfo:getSourceName()","className":"org.eclipse.jdt.internal.compiler.classfmt.InnerClassInfo","acdcCluster":"org.eclipse.jdt.internal.compiler.classfmt.ss"},{"id":"22215","name":"org.eclipse.jdt.internal.compiler.classfmt.InnerClassInfo:reset()","value":1,"children":{},"label":"InnerClassInfo:reset()","className":"org.eclipse.jdt.internal.compiler.classfmt.InnerClassInfo","acdcCluster":"org.eclipse.jdt.internal.compiler.classfmt.ss"},{"id":"2039","name":"java.lang.StringBuffer:<init>()","value":1,"children":{},"label":"StringBuffer:<init>()","className":"java.lang.StringBuffer","acdcCluster":"org.eclipse.jdt.internal.compiler.codegen.ss"},{"id":"2040","name":"java.lang.StringBuffer:append()","value":1,"children":{},"label":"StringBuffer:append()","className":"java.lang.StringBuffer","acdcCluster":"org.eclipse.jdt.internal.compiler.codegen.ss"},{"id":"161","name":"java.lang.Object:<init>()","value":1,"children":{},"label":"Object:<init>()","className":"java.lang.Object","acdcCluster":"org.apache.el.parser.ss"}],"edges":[{"source":"16212","target":"22189"},{"source":"16415","target":"16248"},{"source":"16215","target":"22189"},{"source":"16215","target":"22191"},{"source":"16401","target":"16248"},{"source":"16206","target":"16206"},{"source":"16206","target":"16211"},{"source":"16206","target":"16248"},{"source":"16206","target":"22189"},{"source":"16206","target":"22191"},{"source":"16211","target":"22189"},{"source":"16212","target":"16479"},{"source":"16212","target":"244"},{"source":"16479","target":"16248"},{"source":"16479","target":"16479"},{"source":"16479","target":"22218"},{"source":"16479","target":"22219"},{"source":"16479","target":"169"},{"source":"16479","target":"170"},{"source":"16479","target":"171"},{"source":"16479","target":"1547"},{"source":"16479","target":"16177"},{"source":"16177","target":"16248"},{"source":"16177","target":"16177"},{"source":"16177","target":"16178"},{"source":"16177","target":"16185"},{"source":"16445","target":"16415"},{"source":"16401","target":"22213"},{"source":"16206","target":"22190"},{"source":"16206","target":"16215"},{"source":"16206","target":"16363"},{"source":"16206","target":"16384"},{"source":"16206","target":"16191"},{"source":"16206","target":"16410"},{"source":"16206","target":"16437"},{"source":"16206","target":"22192"},{"source":"16206","target":"13861"},{"source":"16206","target":"16401"},{"source":"16206","target":"16402"},{"source":"16206","target":"16212"},{"source":"16206","target":"13877"},{"source":"16206","target":"16239"},{"source":"16206","target":"16259"},{"source":"16363","target":"16364"},{"source":"16363","target":"22202"},{"source":"16363","target":"22203"},{"source":"16363","target":"13861"},{"source":"16363","target":"16365"},{"source":"16363","target":"16366"},{"source":"16363","target":"244"},{"source":"16363","target":"22204"},{"source":"16363","target":"16395"},{"source":"16363","target":"16389"},{"source":"16191","target":"16415"},{"source":"16191","target":"22181"},{"source":"16191","target":"22182"},{"source":"16191","target":"13861"},{"source":"16191","target":"16177"},{"source":"16191","target":"16179"},{"source":"16191","target":"22183"},{"source":"16191","target":"244"},{"source":"16191","target":"22184"},{"source":"16191","target":"16196"},{"source":"16191","target":"16192"},{"source":"16191","target":"16445"},{"source":"16410","target":"16415"},{"source":"16410","target":"22181"},{"source":"16410","target":"22182"},{"source":"16410","target":"13861"},{"source":"16410","target":"16443"},{"source":"16410","target":"16412"},{"source":"16410","target":"16414"},{"source":"16410","target":"16413"},{"source":"16410","target":"244"},{"source":"16410","target":"22184"},{"source":"16410","target":"16458"},{"source":"16410","target":"16451"},{"source":"16410","target":"16445"},{"source":"13861","target":"13861"},{"source":"13861","target":"20374"},{"source":"16402","target":"22213"},{"source":"16402","target":"22214"},{"source":"13877","target":"244"},{"source":"16239","target":"16380"},{"source":"16239","target":"16431"},{"source":"16239","target":"16407"},{"source":"16239","target":"16182"},{"source":"16239","target":"16217"},{"source":"16239","target":"22194"},{"source":"16239","target":"16259"},{"source":"16259","target":"1314"},{"source":"16364","target":"16248"},{"source":"16365","target":"22202"},{"source":"16365","target":"16177"},{"source":"16365","target":"244"},{"source":"16366","target":"22202"},{"source":"16366","target":"16479"},{"source":"16395","target":"16389"},{"source":"16389","target":"16364"},{"source":"16179","target":"22176"},{"source":"16179","target":"22174"},{"source":"16179","target":"22177"},{"source":"16179","target":"17507"},{"source":"16179","target":"17638"},{"source":"16179","target":"17531"},{"source":"16179","target":"17516"},{"source":"16179","target":"17688"},{"source":"16179","target":"22178"},{"source":"16179","target":"17605"},{"source":"16179","target":"22179"},{"source":"16179","target":"17620"},{"source":"16179","target":"22180"},{"source":"16179","target":"17666"},{"source":"16179","target":"22175"},{"source":"16179","target":"3553"},{"source":"16179","target":"17703"},{"source":"16179","target":"17073"},{"source":"16179","target":"17067"},{"source":"16179","target":"16177"},{"source":"16179","target":"16179"},{"source":"16179","target":"169"},{"source":"16179","target":"170"},{"source":"16179","target":"171"},{"source":"16179","target":"1547"},{"source":"16196","target":"16192"},{"source":"16192","target":"16415"},{"source":"16443","target":"22216"},{"source":"16443","target":"22181"},{"source":"16443","target":"22182"},{"source":"16443","target":"3553"},{"source":"16443","target":"11236"},{"source":"16443","target":"13856"},{"source":"16412","target":"22181"},{"source":"16412","target":"16411"},{"source":"16414","target":"22216"},{"source":"16414","target":"22181"},{"source":"16414","target":"16411"},{"source":"16413","target":"22181"},{"source":"16413","target":"16479"},{"source":"16458","target":"16451"},{"source":"16451","target":"16445"},{"source":"20374","target":"22591"},{"source":"16380","target":"16372"},{"source":"16380","target":"16373"},{"source":"16380","target":"16370"},{"source":"16380","target":"16375"},{"source":"16380","target":"16371"},{"source":"16380","target":"22205"},{"source":"16431","target":"16425"},{"source":"16431","target":"16429"},{"source":"16431","target":"16424"},{"source":"16431","target":"16422"},{"source":"16431","target":"16423"},{"source":"16431","target":"16420"},{"source":"16431","target":"22217"},{"source":"16407","target":"16403"},{"source":"16407","target":"16404"},{"source":"16407","target":"16405"},{"source":"16407","target":"16402"},{"source":"16407","target":"22215"},{"source":"16182","target":"16178"},{"source":"16217","target":"2039"},{"source":"16217","target":"22189"},{"source":"16217","target":"22191"},{"source":"16217","target":"2040"},{"source":"16217","target":"3553"},{"source":"16217","target":"11236"},{"source":"16211","target":"16177"},{"source":"16211","target":"244"},{"source":"16248","target":"161"}],"groups":[{"id":"cluster","title":"org.eclipse.jdt.internal.compiler.classfmt.ClassFileReader.ss7"}]}
