{"relatedACDCClusters":{"org.apache.catalina.valves.rewrite.ss":{"id":"a8f883cd-1721-11ea-8ada-add5f6e8eea0","cluster":"org.apache.catalina.valves.rewrite.ss","elements":["org.apache.catalina.valves.rewrite.RewriteCond$LexicalCondition","org.apache.catalina.valves.rewrite.RewriteCond$Condition","org.apache.catalina.valves.rewrite.RewriteCond","org.apache.catalina.valves.rewrite.RewriteCond$ResourceCondition","org.apache.catalina.valves.rewrite.RewriteCond$PatternCondition","java.util.regex.Pattern","org.apache.catalina.valves.rewrite.Substitution$SubstitutionElement","org.apache.catalina.valves.rewrite.Substitution$RewriteCondBackReferenceElement","org.apache.catalina.valves.rewrite.Substitution$MapElement","org.apache.catalina.valves.rewrite.Substitution$ServerVariableSslElement","org.apache.catalina.valves.rewrite.Substitution$StaticElement","org.apache.catalina.valves.rewrite.Substitution$RewriteRuleBackReferenceElement","org.apache.catalina.valves.rewrite.Substitution$ServerVariableHttpElement","org.apache.catalina.valves.rewrite.Substitution$ServerVariableElement","org.apache.catalina.valves.rewrite.Substitution$ServerVariableEnvElement","org.apache.catalina.valves.rewrite.Substitution","java.util.regex.Matcher","org.apache.catalina.valves.rewrite.Resolver","org.apache.catalina.valves.rewrite.RewriteMap","org.apache.catalina.valves.rewrite.RewriteRule","org.apache.catalina.valves.rewrite.RewriteValve","org.apache.catalina.valves.rewrite.ResolverImpl","org.apache.catalina.util.URLEncoder"]}},"nodes":[{"id":"10252","name":"org.apache.catalina.valves.rewrite.ResolverImpl:<init>()","value":2,"children":{"org.apache.catalina.valves.rewrite.Resolver:<init>()":true},"label":"ResolverImpl:<init>()","className":"org.apache.catalina.valves.rewrite.ResolverImpl","acdcCluster":"org.apache.catalina.valves.rewrite.ss","groupId":"cluster"},{"id":"10245","name":"org.apache.catalina.valves.rewrite.Resolver:<init>()","value":2,"children":{"java.lang.Object:<init>()":true},"label":"Resolver:<init>()","className":"org.apache.catalina.valves.rewrite.Resolver","acdcCluster":"org.apache.catalina.valves.rewrite.ss","groupId":"cluster"},{"id":"161","name":"java.lang.Object:<init>()","value":1,"children":{},"label":"Object:<init>()","className":"java.lang.Object","acdcCluster":"org.apache.el.parser.ss"}],"edges":[{"source":"10252","target":"10245"},{"source":"10245","target":"161"}],"groups":[{"id":"cluster","title":"org.apache.catalina.valves.rewrite.ResolverImpl.ss2"}]}
